Workbook

Sheet Liste audit
A1: IDENTIFICATION-LOCALISATION-DONNEES DU SITE | J1: Installation PV | M1: BUREAU DE CONTÔLE DRE | O1: Mise en service | P1: MATERIELS | R1: CONTACT | V1: AUDIT | X1: INFO COMPLEMENTAIRES
A2: ID référent | B2: Nom des projets | C2: Puissance EXE | D2: SPV | E2: Latitude | F2: Longitude | G2: Adresse | H2: Dept | I2: Type de centrale | J2: Installateur | K2: Date réelle démarrage centrale PV | L2: Date réelle fin centrale PV | M2: Entreprise | N2: Date de reception réelle des DRE 155/162 | O2: Date MES | P2: SI | Q2: Panneaux | R2: Contact Chargé Exploitation | S2: Numéro Chargé d'exploitation | T2: Contact Gestion actif | U2: Numéro Gestion actif | V2: Audit en toiture | W2: Audit hors toiture | X2: Sous performance non identifié | Y2: Ratio PR réel VS PR théorique OCTOBRE | Z2: Raison probable | AA2: Date prévisionnelle d'audit | AB2: Date réelle d'audit | AC2: Présence auto controle | AD2: Présence PV réception lot PV | AE2: Présence CR visite chantier lot PV
A3: 31971 | B3: Antunez - SCI ANAUJA | C3: 269.45 | D3: F2 DAVAI ENRSPV8 | E3: 43.3654 | F3: 3.2529 | G3: 253 Bd Robert Koch, 34500 Béziers, France | H3: 34 | I3: Ombrière simple | J3: LE TRIANGLE | K3: 45588 | L3: 45688 | M3: SOCOTEC POWER SERVICES | N3: 45713 | O3: 45744 | P3: Triangle IAB | Q3: DMEGC-DM425M10T-B54HSW-HBW | R3: =_xlfn.XLOOKUP(Tableau2[[#This Row],[ID référent]],Feuil4!A:A,Feuil4!BD:BD) -> Parfait MEZEME ONA | S3: =IF(Tableau2[[#This Row],[Contact Chargé Exploitation]]="Parfait MEZEME ONA","06 63 06 94 73","06 74 09 71 44") -> 06 63 06 94 73 | T3: Jean-Paul THOROGOOD | U3: =IF(Tableau2[[#This Row],[Contact Gestion actif]]="Victor PONTAIS","06 69 21 76 42","06 74 94 09 90") -> 06 74 94 09 90 | W3: X | Y3: 1.0043709 | AC3: Non | AD3: Non | AE3: Non
A4: 89219 | B4: EARL CADOT | C4: 309.4 | D4: F3 DAVAI ENRSPV10 | E4: 46.24919 | F4: 3.88361 | G4: La Maisonneuve, 42310 Urbise, France | H4: 42 | I4: Bâtiment à construire - C | J4: 3C instal | K4: 45638 | L4: 45699 | M4: SOCOTEC POWER SERVICES | N4: 45699 | O4: 45748 | P4: JORIS RS-R | Q4: DMEGC-DM455M10RT-54HSW-HBW | R4: =_xlfn.XLOOKUP(Tableau2[[#This Row],[ID référent]],Feuil4!A:A,Feuil4!BD:BD) -> Yasser BADREZZAMANE | S4: =IF(Tableau2[[#This Row],[Contact Chargé Exploitation]]="Parfait MEZEME ONA","06 63 06 94 73","06 74 09 71 44") -> 06 74 09 71 44 | T4: Jean-Paul THOROGOOD | U4: =IF(Tableau2[[#This Row],[Contact Gestion actif]]="Victor PONTAIS","06 69 21 76 42","06 74 94 09 90") -> 06 74 94 09 90 | V4: X | W4: X | Y4: 0.99454308 | AC4: Oui | AD4: Oui | AE4: Non
A5: 83705 | B5: Azemar | C5: 319 | D5: F3 DAVAI ENRSPV13 | E5: 44.25786 | F5: 2.45787 | G5: 12160 Camboulazet, France | H5: 12 | I5: Bâtiment à construire - C | J5: 3C instal | K5: 45705 | L5: 45737 | M5: BUREAU VERITAS | N5: 45754 | O5: 45783 | P5: DOMESOLAR NPA 3.45 | Q5: DMEGC-DM455M10RT-B54HSW | R5: =_xlfn.XLOOKUP(Tableau2[[#This Row],[ID référent]],Feuil4!A:A,Feuil4!BD:BD) -> Parfait MEZEME ONA | S5: =IF(Tableau2[[#This Row],[Contact Chargé Exploitation]]="Parfait MEZEME ONA","06 63 06 94 73","06 74 09 71 44") -> 06 63 06 94 73 | T5: Jean-Paul THOROGOOD | U5: =IF(Tableau2[[#This Row],[Contact Gestion actif]]="Victor PONTAIS","06 69 21 76 42","06 74 94 09 90") -> 06 74 94 09 90 | W5: X | Y5: 0.97390725 | AC5: Oui | AD5: Oui | AE5: Non
A6: 17996 | B6: Mathieu Montet | C6: 256.055 | D6: F2 DAVAI ENRSPV12 | E6: 45.53534 | F6: 5.45229 | G6: 127 Route de la Tour, 38110 Montagnieu, France | H6: 38 | I6: Toiture existante / Rénovation | J6: PROSUNFRANCE | K6: 45404 | L6: 45506 | M6: SOCOTEC POWER SERVICES | N6: 45496 | O6: 45567 | P6: DOMESOLAR Hb²/NPA 3.45 | Q6: DMEGC-DM415M10-54HSW-V | R6: =_xlfn.XLOOKUP(Tableau2[[#This Row],[ID référent]],Feuil4!A:A,Feuil4!BD:BD) -> Yasser BADREZZAMANE | S6: =IF(Tableau2[[#This Row],[Contact Chargé Exploitation]]="Parfait MEZEME ONA","06 63 06 94 73","06 74 09 71 44") -> 06 74 09 71 44 | T6: Jean-Paul THOROGOOD | U6: =IF(Tableau2[[#This Row],[Contact Gestion actif]]="Victor PONTAIS","06 69 21 76 42","06 74 94 09 90") -> 06 74 94 09 90 | W6: X | Y6: 0.90032451 | AC6: Oui | AD6: Oui | AE6: Non
A7: 17966 | B7: Hangar Laurent ROUX | C7: 123.41 | D7: F2 DAVAI ENRSPV8 | E7: 44.92766 | F7: 2.99036 | G7: Cros et Vareine, 15260 Neuvéglise-sur-Truyère, France | H7: 15 | I7: Toiture existante / Rénovation | J7: OFT | K7: 45441 | L7: 45469 | M7: SOCOTEC POWER SERVICES | N7: 45531 | O7: 45587 | P7: DOMESOLAR Ital Solar | Q7: DMEGC-DM430M10T-54HSW-HBW | R7: =_xlfn.XLOOKUP(Tableau2[[#This Row],[ID référent]],Feuil4!A:A,Feuil4!BD:BD) -> Parfait MEZEME ONA | S7: =IF(Tableau2[[#This Row],[Contact Chargé Exploitation]]="Parfait MEZEME ONA","06 63 06 94 73","06 74 09 71 44") -> 06 63 06 94 73 | T7: Jean-Paul THOROGOOD | U7: =IF(Tableau2[[#This Row],[Contact Gestion actif]]="Victor PONTAIS","06 69 21 76 42","06 74 94 09 90") -> 06 74 94 09 90 | W7: X | Y7: 0.67177711 | Z7: Pb AGCP qui déclenche | AC7: Oui | AD7: Non | AE7: Non
A8: 70087 | B8: Hangar Bernard MAGE | C8: 300.82 | D8: F2 DAVAI ENRSPV8 | E8: 44.75755 | F8: 2.04496 | G8: Broussoles, 46210 Montet-et-Bouxal, France | H8: 46 | I8: Bâtiment à construire - A2 | J8: Acrom | K8: 45537 | L8: 45569 | M8: SOCOTEC POWER SERVICES | N8: 45586 | O8: 45609 | P8: DOMESOLAR NPA 3.45 | Q8: JKM445N-54HL4R-V | R8: =_xlfn.XLOOKUP(Tableau2[[#This Row],[ID référent]],Feuil4!A:A,Feuil4!BD:BD) -> Parfait MEZEME ONA | S8: =IF(Tableau2[[#This Row],[Contact Chargé Exploitation]]="Parfait MEZEME ONA","06 63 06 94 73","06 74 09 71 44") -> 06 63 06 94 73 | T8: Jean-Paul THOROGOOD | U8: =IF(Tableau2[[#This Row],[Contact Gestion actif]]="Victor PONTAIS","06 69 21 76 42","06 74 94 09 90") -> 06 74 94 09 90 | V8: X | W8: X | Y8: 1.0216865 | AC8: Oui | AD8: Oui | AE8: Non
A9: 30489 | B9: Hangar Pierre MOURGUES | C9: 222.5 | D9: F2 DAVAI ENRSPV9 | E9: 44.38426 | F9: 1.16738 | G9: Mondounet - Fargues, 46800 Porte-du-Quercy, France | H9: 46 | I9: Bâtiment à construire - C | J9: Acrom | K9: 45439 | L9: 45546 | M9: SOCOTEC POWER SERVICES | N9: 45560 | O9: 45611 | P9: DOMESOLAR NPA 3.45 | Q9: DMEGC-DM445M10RT-54HSW-HBW | R9: =_xlfn.XLOOKUP(Tableau2[[#This Row],[ID référent]],Feuil4!A:A,Feuil4!BD:BD) -> Parfait MEZEME ONA | S9: =IF(Tableau2[[#This Row],[Contact Chargé Exploitation]]="Parfait MEZEME ONA","06 63 06 94 73","06 74 09 71 44") -> 06 63 06 94 73 | T9: Victor PONTAIS | U9: =IF(Tableau2[[#This Row],[Contact Gestion actif]]="Victor PONTAIS","06 69 21 76 42","06 74 94 09 90") -> 06 69 21 76 42 | W9: X | Y9: 0.9285786 | AC9: Oui | AD9: Oui | AE9: Non
A10: 58962 | B10: Hangar Karl Biteau | C10: 324.22 | D10: F2 DAVAI ENRSPV8 | E10: 45.7447 | F10: -0.92605 | G10: 17250 Sainte-Gemme, France | H10: 17 | I10: Bâtiment à construire - C | J10: Eiffage | K10: 45404 | L10: 45422 | M10: SOCOTEC POWER SERVICES | N10: 45526 | O10: 45615 | P10: DOMESOLAR NPA 3.45 | Q10: DMEGC-DM430M10T-54HSW-HBW | R10: =_xlfn.XLOOKUP(Tableau2[[#This Row],[ID référent]],Feuil4!A:A,Feuil4!BD:BD) -> Parfait MEZEME ONA | S10: =IF(Tableau2[[#This Row],[Contact Chargé Exploitation]]="Parfait MEZEME ONA","06 63 06 94 73","06 74 09 71 44") -> 06 63 06 94 73 | T10: Jean-Paul THOROGOOD | U10: =IF(Tableau2[[#This Row],[Contact Gestion actif]]="Victor PONTAIS","06 69 21 76 42","06 74 94 09 90") -> 06 74 94 09 90 | V10: X | W10: X | Y10: 0.97688227 | AC10: Oui | AD10: Oui | AE10: Non
A11: 28173 | B11: Burgat Et Fils Tp | C11: 113.03 | D11: F2 DAVAI ENRSPV6 | E11: 43.04294 | F11: 2.23988 | G11: La Plaine 11300 Cournanel | H11: 11 | I11: Toiture existante / Rénovation | J11: SOLARTIS | K11: 45488 | L11: 45551 | M11: SOCOTEC POWER SERVICES | N11: 45569 | O11: 45616 | P11: DOMESOLAR Ital Solar | Q11: DMEGC-DM445M10RT-54HSW-HBW | R11: =_xlfn.XLOOKUP(Tableau2[[#This Row],[ID référent]],Feuil4!A:A,Feuil4!BD:BD) -> Parfait MEZEME ONA | S11: =IF(Tableau2[[#This Row],[Contact Chargé Exploitation]]="Parfait MEZEME ONA","06 63 06 94 73","06 74 09 71 44") -> 06 63 06 94 73 | T11: Jean-Paul THOROGOOD | U11: =IF(Tableau2[[#This Row],[Contact Gestion actif]]="Victor PONTAIS","06 69 21 76 42","06 74 94 09 90") -> 06 74 94 09 90 | W11: X | X11: X | Y11: 0.85352021 | AC11: Oui | AD11: Oui | AE11: Non
A12: 29246 | B12: HANGAR Angelina SIMMONET | C12: 173.55 | D12: F2 DAVAI ENRSPV6 | E12: 46.63388 | F12: 3.58233 | G12: L'Étang Fouché, 03230 Paray-le-Frésil, France | H12: 3 | I12: Bâtiment à construire - A1 | J12: LE TRIANGLE | K12: 45594 | L12: 45615 | M12: SOCOTEC POWER SERVICES | N12: 45628 | O12: 45667 | P12: Triangle ISB | Q12: DMEGC-DM455M10RT-54HSW-HBW | R12: =_xlfn.XLOOKUP(Tableau2[[#This Row],[ID référent]],Feuil4!A:A,Feuil4!BD:BD) -> Yasser BADREZZAMANE | S12: =IF(Tableau2[[#This Row],[Contact Chargé Exploitation]]="Parfait MEZEME ONA","06 63 06 94 73","06 74 09 71 44") -> 06 74 09 71 44 | T12: Jean-Paul THOROGOOD | U12: =IF(Tableau2[[#This Row],[Contact Gestion actif]]="Victor PONTAIS","06 69 21 76 42","06 74 94 09 90") -> 06 74 94 09 90 | W12: X | Y12: 0.9591879 | AC12: Oui | AD12: Oui | AE12: Non
A13: 76547 | B13: Maymat | C13: 345.8 | D13: F2 DAVAI ENRSPV9 | E13: 46.51456 | F13: 3.41436 | G13: Les Sorreaux, 03400 Toulon-sur-Allier, France | H13: 3 | I13: Bâtiment à construire - C | J13: LE TRIANGLE | K13: 45561 | L13: 45618 | M13: SOCOTEC POWER SERVICES | N13: 45624 | O13: 45672 | P13: Triangle ISB | Q13: DMEGC-DM455M10RT-54HSW-HBW | R13: =_xlfn.XLOOKUP(Tableau2[[#This Row],[ID référent]],Feuil4!A:A,Feuil4!BD:BD) -> Yasser BADREZZAMANE | S13: =IF(Tableau2[[#This Row],[Contact Chargé Exploitation]]="Parfait MEZEME ONA","06 63 06 94 73","06 74 09 71 44") -> 06 74 09 71 44 | T13: Victor PONTAIS | U13: =IF(Tableau2[[#This Row],[Contact Gestion actif]]="Victor PONTAIS","06 69 21 76 42","06 74 94 09 90") -> 06 69 21 76 42 | W13: X | X13: X | Y13: 0.84186718 | AC13: Oui | AD13: Oui | AE13: Non
A14: 22147 | B14: HANGAR Christian MIGNARD | C14: 97.11 | D14: F2 DAVAI ENRSPV9 | E14: 43.297058 | F14: 2.665955 | G14: Chemin de Rieux 11700 Pépieux | H14: 11 | I14: Bâtiment à construire - B | J14: Solartis | K14: 45579 | L14: 45623 | M14: SOCOTEC POWER SERVICES | N14: 45628 | O14: 45642 | P14: DOMESOLAR NPA 3.45 | Q14: DMEGC-DM415M10-54HSW-V | R14: =_xlfn.XLOOKUP(Tableau2[[#This Row],[ID référent]],Feuil4!A:A,Feuil4!BD:BD) -> Parfait MEZEME ONA | S14: =IF(Tableau2[[#This Row],[Contact Chargé Exploitation]]="Parfait MEZEME ONA","06 63 06 94 73","06 74 09 71 44") -> 06 63 06 94 73 | T14: Victor PONTAIS | U14: =IF(Tableau2[[#This Row],[Contact Gestion actif]]="Victor PONTAIS","06 69 21 76 42","06 74 94 09 90") -> 06 69 21 76 42 | V14: X | W14: X | Y14: 0.9985421 | AC14: Non | AD14: Non | AE14: Non
A15: 60830 | B15: DUMONT GUY | C15: 232.2 | D15: F2 DAVAI ENRSPV8 | E15: 46.628738 | F15: 3.585084 | G15: Les Sabots, 03230 Chevagnes, France | H15: 3 | I15: Bâtiment à construire - A1 | J15: LE TRIANGLE | K15: 45565 | L15: 45618 | M15: SOCOTEC POWER SERVICES | N15: 45623 | O15: 45687 | P15: Triangle ISB | Q15: DMEGC-DM430M10T-54HSW-HBW | R15: =_xlfn.XLOOKUP(Tableau2[[#This Row],[ID référent]],Feuil4!A:A,Feuil4!BD:BD) -> Yasser BADREZZAMANE | S15: =IF(Tableau2[[#This Row],[Contact Chargé Exploitation]]="Parfait MEZEME ONA","06 63 06 94 73","06 74 09 71 44") -> 06 74 09 71 44 | T15: Jean-Paul THOROGOOD | U15: =IF(Tableau2[[#This Row],[Contact Gestion actif]]="Victor PONTAIS","06 69 21 76 42","06 74 94 09 90") -> 06 74 94 09 90 | W15: X | Y15: 1.2162829 | AC15: Oui | AD15: Oui | AE15: Non
A16: 95686 | B16: MARTEL 184 Construction | C16: 499.95 | D16: F2 DAVAI ENRSPV9 | E16: 46.21212 | F16: 1.66779 | G16: Lieudit Les Ribières, 23240 Le Grand Bourg | H16: 23 | I16: Bâtiment à construire - A2 | J16: NEOXOM | K16: 45530 | L16: 45567 | M16: SOCOTEC POWER SERVICES | N16: 45601 | O16: 45692 | P16: DOMESOLAR NPA 3.45 | Q16: JKM450N-54HL4R-V | R16: =_xlfn.XLOOKUP(Tableau2[[#This Row],[ID référent]],Feuil4!A:A,Feuil4!BD:BD) -> Parfait MEZEME ONA | S16: =IF(Tableau2[[#This Row],[Contact Chargé Exploitation]]="Parfait MEZEME ONA","06 63 06 94 73","06 74 09 71 44") -> 06 63 06 94 73 | T16: Victor PONTAIS | U16: =IF(Tableau2[[#This Row],[Contact Gestion actif]]="Victor PONTAIS","06 69 21 76 42","06 74 94 09 90") -> 06 69 21 76 42 | W16: X | Y16: 0.68927501 | Z16: Modification des shelters jusqu'au 6 octobre | AC16: Non | AD16: Oui | AE16: Non
A17: 95689 | B17: BOUCHARDY 203 LOC | C17: 498.68 | D17: F2 DAVAI ENRSPV9 | E17: 46.18866 | F17: 1.70087 | G17: Saint-Martin, 23320 Saint-Vaury, France | H17: 23 | I17: Toiture existante / Rénovation | J17: OFT | K17: 45635 | L17: 45681 | M17: SOCOTEC POWER SERVICES | N17: 45691 | O17: 45728 | P17: DOMESOLAR NPA 3.45 | Q17: DMEGC-DM455M10RT-54HSW-HBW | R17: =_xlfn.XLOOKUP(Tableau2[[#This Row],[ID référent]],Feuil4!A:A,Feuil4!BD:BD) -> Parfait MEZEME ONA | S17: =IF(Tableau2[[#This Row],[Contact Chargé Exploitation]]="Parfait MEZEME ONA","06 63 06 94 73","06 74 09 71 44") -> 06 63 06 94 73 | T17: Victor PONTAIS | U17: =IF(Tableau2[[#This Row],[Contact Gestion actif]]="Victor PONTAIS","06 69 21 76 42","06 74 94 09 90") -> 06 69 21 76 42 | W17: X | X17: X | Y17: 0.8724129 | AC17: Oui | AD17: Oui | AE17: Non
A18: 95691 | B18: BOULOIR 206 LOC | C18: 499.14 | D18: F2 DAVAI ENRSPV9 | E18: 46.21057 | F18: 1.67252 | G18: 23240 Le Grand-Bourg, France | H18: 23 | I18: Toiture existante / Rénovation | J18: OFT | K18: 45642 | L18: 45688 | M18: SOCOTEC POWER SERVICES | N18: 45691 | O18: 45727 | P18: DOMESOLAR NPA 3.45 | Q18: DMEGC-DM455M10RT-54HSW-HBW | R18: =_xlfn.XLOOKUP(Tableau2[[#This Row],[ID référent]],Feuil4!A:A,Feuil4!BD:BD) -> Parfait MEZEME ONA | S18: =IF(Tableau2[[#This Row],[Contact Chargé Exploitation]]="Parfait MEZEME ONA","06 63 06 94 73","06 74 09 71 44") -> 06 63 06 94 73 | T18: Victor PONTAIS | U18: =IF(Tableau2[[#This Row],[Contact Gestion actif]]="Victor PONTAIS","06 69 21 76 42","06 74 94 09 90") -> 06 69 21 76 42 | W18: X | Y18: 0.9177162 | AC18: Oui | AD18: Oui | AE18: Non
A19: 83431 | B19: Hangar Renaud Sonnard | C19: 324.87 | D19: F3 DAVAI ENRSPV11 | E19: 46.41411 | F19: -0.53832 | G19: Les grandes versaines, 79160 Villiers-en-Plaine, France | H19: 79 | I19: Bâtiment à construire - A1 | J19: REGIESOLAIRE | K19: 45677 | L19: 45695 | M19: SOCOTEC POWER SERVICES | N19: 45707 | O19: 45736 | P19: DOMESOLAR NPA 3.45 | Q19: DMEGC-DM455M10RT-54HSW-HBW | R19: =_xlfn.XLOOKUP(Tableau2[[#This Row],[ID référent]],Feuil4!A:A,Feuil4!BD:BD) -> Yasser BADREZZAMANE | S19: =IF(Tableau2[[#This Row],[Contact Chargé Exploitation]]="Parfait MEZEME ONA","06 63 06 94 73","06 74 09 71 44") -> 06 74 09 71 44 | T19: Jean-Paul THOROGOOD | U19: =IF(Tableau2[[#This Row],[Contact Gestion actif]]="Victor PONTAIS","06 69 21 76 42","06 74 94 09 90") -> 06 74 94 09 90 | V19: X | W19: X | Y19: 1.1010636 | AC19: Non | AD19: Oui | AE19: Oui
A20: 96546 | B20: Hangar Fabrice COMBY | C20: 499.59 | D20: F3 DAVAI ENRSPV11 | E20: 45.452821 | F20: 1.2834 | G20: Besse, 19210 Saint-Éloy-les-Tuileries, France | H20: 19 | I20: Toiture existante / PV Ready | J20: HBBAT | K20: 45639 | L20: 45709 | M20: SOCOTEC POWER SERVICES | N20: 45722 | O20: 45741 | P20: DOMESOLAR NPA 3.45 | Q20: DMEGC-DM455M10RT-54HSW-HBW | R20: =_xlfn.XLOOKUP(Tableau2[[#This Row],[ID référent]],Feuil4!A:A,Feuil4!BD:BD) -> Parfait MEZEME ONA | S20: =IF(Tableau2[[#This Row],[Contact Chargé Exploitation]]="Parfait MEZEME ONA","06 63 06 94 73","06 74 09 71 44") -> 06 63 06 94 73 | T20: Jean-Paul THOROGOOD | U20: =IF(Tableau2[[#This Row],[Contact Gestion actif]]="Victor PONTAIS","06 69 21 76 42","06 74 94 09 90") -> 06 74 94 09 90 | V20: X | W20: X | X20: X | Y20: 0.8894752 | AC20: Oui | AD20: Oui | AE20: Non
A21: 82076 | B21: Hangar Julien Vaudin | C21: 348.88 | D21: F2 DAVAI ENRSPV7 | E21: 46.58741 | F21: 3.5494 | G21: Les Jacquets, 03230 Chevagnes, France | H21: 3 | I21: Toiture existante / Rénovation | J21: PROSUNFRANCE | K21: 45483 | L21: 45565 | M21: SOCOTEC POWER SERVICES | N21: 45574 | O21: 45751 | P21: DOMESOLAR NPA 3.45 | Q21: DMEGC-DM445M10RT-54HSW-HBW | R21: =_xlfn.XLOOKUP(Tableau2[[#This Row],[ID référent]],Feuil4!A:A,Feuil4!BD:BD) -> Yasser BADREZZAMANE | S21: =IF(Tableau2[[#This Row],[Contact Chargé Exploitation]]="Parfait MEZEME ONA","06 63 06 94 73","06 74 09 71 44") -> 06 74 09 71 44 | T21: Victor PONTAIS | U21: =IF(Tableau2[[#This Row],[Contact Gestion actif]]="Victor PONTAIS","06 69 21 76 42","06 74 94 09 90") -> 06 69 21 76 42 | W21: X | Y21: 0.97496649 | AC21: Oui | AD21: Oui | AE21: Non
A22: 98584 | B22: Hangar Richard VAN ZANTEN | C22: 330.785 | D22: F2 DAVAI ENRSPV7 | E22: 44.66239 | F22: 0.83643 | G22: La Tuque, 47210 Parranquet, France | H22: 47 | I22: Bâtiment à construire - A2 | J22: Acrom | K22: 45663 | L22: 45705 | M22: SOCOTEC POWER SERVICES | N22: 45729 | O22: 45763 | P22: DOMESOLAR NPA 3.45 | Q22: DMEGC-DM455M10RT-B54HSW | R22: =_xlfn.XLOOKUP(Tableau2[[#This Row],[ID référent]],Feuil4!A:A,Feuil4!BD:BD) -> Yasser BADREZZAMANE | S22: =IF(Tableau2[[#This Row],[Contact Chargé Exploitation]]="Parfait MEZEME ONA","06 63 06 94 73","06 74 09 71 44") -> 06 74 09 71 44 | T22: Victor PONTAIS | U22: =IF(Tableau2[[#This Row],[Contact Gestion actif]]="Victor PONTAIS","06 69 21 76 42","06 74 94 09 90") -> 06 69 21 76 42 | W22: X | Y22: 0.95449521 | AC22: Oui | AD22: Oui | AE22: Non
A23: 20614 | B23: HANGAR Benoit BERTELOOT | C23: 278.64 | D23: F2 DAVAI ENRSPV8 | E23: 48.107174 | F23: 3.120535 | G23: 127 Lieu Dit les Cleris 89150 Vernoy | H23: 89 | I23: Bâtiment à construire - A1 | J23: LE TRIANGLE | K23: 45376 | L23: 45660 | M23: SOCOTEC POWER SERVICES | N23: 45666 | O23: 45687 | P23: Triangle ISB | Q23: DMEGC-DM430M10T-54HSW-HBW | R23: =_xlfn.XLOOKUP(Tableau2[[#This Row],[ID référent]],Feuil4!A:A,Feuil4!BD:BD) -> Yasser BADREZZAMANE | S23: =IF(Tableau2[[#This Row],[Contact Chargé Exploitation]]="Parfait MEZEME ONA","06 63 06 94 73","06 74 09 71 44") -> 06 74 09 71 44 | T23: Jean-Paul THOROGOOD | U23: =IF(Tableau2[[#This Row],[Contact Gestion actif]]="Victor PONTAIS","06 69 21 76 42","06 74 94 09 90") -> 06 74 94 09 90 | V23: X | W23: X | Y23: 1.0327699 | AC23: Oui | AD23: Oui | AE23: Non
A24: 15843 | B24: Hangar Laurent ROUX | C24: 313.95 | D24: F2 DAVAI ENRSPV6 | E24: 44.92782 | F24: 2.98992 | G24: 10 Rue de Vareine 15260 Neuvéglise-sur-Truyère | H24: 15 | I24: Bâtiment à construire - A2 | J24: Yama Energies | K24: 45691 | L24: 45709 | M24: SOCOTEC POWER SERVICES | N24: 45713 | O24: 45769 | P24: DOMESOLAR NPA 3.45 | Q24: DMEGC-DM455M10RT-54HSW-HBW | R24: =_xlfn.XLOOKUP(Tableau2[[#This Row],[ID référent]],Feuil4!A:A,Feuil4!BD:BD) -> Parfait MEZEME ONA | S24: =IF(Tableau2[[#This Row],[Contact Chargé Exploitation]]="Parfait MEZEME ONA","06 63 06 94 73","06 74 09 71 44") -> 06 63 06 94 73 | T24: Jean-Paul THOROGOOD | U24: =IF(Tableau2[[#This Row],[Contact Gestion actif]]="Victor PONTAIS","06 69 21 76 42","06 74 94 09 90") -> 06 74 94 09 90 | W24: X | Y24: 0.95044437 | AC24: Oui | AD24: Oui | AE24: Non
A25: 90361 | B25: Serge Maltaverne | C25: 218.855 | D25: F3 DAVAI ENRSPV10 | E25: 46.6938 | F25: 4.10361 | G25: 638 Chard, 71320 Sainte-Radegonde, France | H25: 71 | I25: Toiture existante / Rénovation | J25: PROSUNFRANCE | K25: 45624 | L25: 45678 | M25: SOCOTEC POWER SERVICES | N25: 45693 | O25: 45799 | P25: DOMESOLAR NPA 3.45 | Q25: DMEGC-DM455M10RT-54HSW-HBW | R25: =_xlfn.XLOOKUP(Tableau2[[#This Row],[ID référent]],Feuil4!A:A,Feuil4!BD:BD) -> Yasser BADREZZAMANE | S25: =IF(Tableau2[[#This Row],[Contact Chargé Exploitation]]="Parfait MEZEME ONA","06 63 06 94 73","06 74 09 71 44") -> 06 74 09 71 44 | T25: Jean-Paul THOROGOOD | U25: =IF(Tableau2[[#This Row],[Contact Gestion actif]]="Victor PONTAIS","06 69 21 76 42","06 74 94 09 90") -> 06 74 94 09 90 | W25: X | Y25: 1.0325475 | AC25: Oui | AD25: Oui | AE25: Non
A26: 33559 | B26: Hangar Christophe CARRERE n°2 | C26: 278.005 | D26: F2 DAVAI ENRSPV7 | E26: 44.14804 | F26: 0.44966 | G26: Boy, 47600 Montagnac-sur-Auvignon, France | H26: 47 | I26: Bâtiment à construire - A1 | J26: Acrom | K26: 45642 | L26: 45747 | M26: SOCOTEC POWER SERVICES | N26: 45758 | O26: 45793 | P26: DOMESOLAR NPA 3.45 | Q26: DMEGC-DM455M10RT-B54HSW | R26: =_xlfn.XLOOKUP(Tableau2[[#This Row],[ID référent]],Feuil4!A:A,Feuil4!BD:BD) -> Parfait MEZEME ONA | S26: =IF(Tableau2[[#This Row],[Contact Chargé Exploitation]]="Parfait MEZEME ONA","06 63 06 94 73","06 74 09 71 44") -> 06 63 06 94 73 | T26: Victor PONTAIS | U26: =IF(Tableau2[[#This Row],[Contact Gestion actif]]="Victor PONTAIS","06 69 21 76 42","06 74 94 09 90") -> 06 69 21 76 42 | W26: X | Y26: 1.2212428 | AC26: Non | AD26: Oui | AE26: Non
A27: 95918 | B27: Hangar Frédéric CASTET | C27: 309.4 | D27: F2 DAVAI ENRSPV9 | E27: 43.043825 | F27: 0.859333 | G27: 11 Carrère de la Goutille, 31160 Estadens, France | H27: 31 | I27: Bâtiment à construire - C | J27: KEVEL | K27: 45719 | L27: 45741 | M27: BUREAU VERITAS | N27: 45750 | O27: 45803 | P27: DOMESOLAR NPA 3.45 | Q27: DMEGC-DM455M10RT-B54HSW | R27: =_xlfn.XLOOKUP(Tableau2[[#This Row],[ID référent]],Feuil4!A:A,Feuil4!BD:BD) -> Yasser BADREZZAMANE | S27: =IF(Tableau2[[#This Row],[Contact Chargé Exploitation]]="Parfait MEZEME ONA","06 63 06 94 73","06 74 09 71 44") -> 06 74 09 71 44 | T27: Victor PONTAIS | U27: =IF(Tableau2[[#This Row],[Contact Gestion actif]]="Victor PONTAIS","06 69 21 76 42","06 74 94 09 90") -> 06 69 21 76 42 | W27: X | Y27: 0.958312 | AC27: Oui | AD27: Oui | AE27: Non
A28: 95695 | B28: MARTEL 183 LOC | C28: 456.82 | D28: F2 DAVAI ENRSPV9 | E28: 46.212595 | F28: 1.6665264 | G28: LIEU-DIT LES RIBIERES LE GRAND BOURG | H28: 23 | I28: Toiture existante / Rénovation | J28: NEOXOM | K28: 45684 | L28: 45758 | M28: SOCOTEC POWER SERVICES | N28: 45723 | O28: 45743 | P28: DOMESOLAR NPA 3.45 | Q28: DMEGC-DM455M10RT-54HSW-HBW | R28: =_xlfn.XLOOKUP(Tableau2[[#This Row],[ID référent]],Feuil4!A:A,Feuil4!BD:BD) -> Parfait MEZEME ONA | S28: =IF(Tableau2[[#This Row],[Contact Chargé Exploitation]]="Parfait MEZEME ONA","06 63 06 94 73","06 74 09 71 44") -> 06 63 06 94 73 | T28: Victor PONTAIS | U28: =IF(Tableau2[[#This Row],[Contact Gestion actif]]="Victor PONTAIS","06 69 21 76 42","06 74 94 09 90") -> 06 69 21 76 42 | W28: X | Y28: 0.97029729 | AC28: Oui | AD28: Oui | AE28: Non
A29: 86550 | B29: Hangar Frederic Sinaud | C29: 499.59 | D29: F3 DAVAI ENRSPV11 | E29: 46.2183 | F29: 1.65147 | G29: 11 La Quaire, 23240 Saint-Priest-la-Plaine, France | H29: 23 | I29: Bâtiment à construire - C | J29: INNOVA | K29: 45684 | L29: 45716 | M29: SOCOTEC POWER SERVICES | N29: 45769 | O29: 45812 | P29: DOMESOLAR NPA 3.45 | Q29: DMEGC-DM455M10RT-54HSW-HBW | R29: =_xlfn.XLOOKUP(Tableau2[[#This Row],[ID référent]],Feuil4!A:A,Feuil4!BD:BD) -> Parfait MEZEME ONA | S29: =IF(Tableau2[[#This Row],[Contact Chargé Exploitation]]="Parfait MEZEME ONA","06 63 06 94 73","06 74 09 71 44") -> 06 63 06 94 73 | T29: Jean-Paul THOROGOOD | U29: =IF(Tableau2[[#This Row],[Contact Gestion actif]]="Victor PONTAIS","06 69 21 76 42","06 74 94 09 90") -> 06 74 94 09 90 | W29: X | Y29: 0.97393521 | AC29: Oui | AD29: Oui | AE29: Oui
A30: 90034 | B30: Hangar Frederic Sinaud | C30: 218.4 | D30: F3 DAVAI ENRSPV11 | E30: 46.23163 | F30: 1.52775 | G30: La Drable, 23300 Saint Priest la feuille | H30: 23 | I30: Bâtiment à construire - C | J30: INNOVA | K30: 45705 | L30: 45716 | M30: SOCOTEC POWER SERVICES | N30: 45769 | O30: 45812 | P30: DOMESOLAR NPA 3.45 | Q30: DMEGC-DM455M10RT-B54HSW | R30: =_xlfn.XLOOKUP(Tableau2[[#This Row],[ID référent]],Feuil4!A:A,Feuil4!BD:BD) -> Parfait MEZEME ONA | S30: =IF(Tableau2[[#This Row],[Contact Chargé Exploitation]]="Parfait MEZEME ONA","06 63 06 94 73","06 74 09 71 44") -> 06 63 06 94 73 | T30: Jean-Paul THOROGOOD | U30: =IF(Tableau2[[#This Row],[Contact Gestion actif]]="Victor PONTAIS","06 69 21 76 42","06 74 94 09 90") -> 06 74 94 09 90 | W30: X | Y30: 1.0085301 | AC30: Oui | AD30: Oui | AE30: Oui
A31: 90189 | B31: HARAS DE LA MAJORIE/MANOHA | C31: 499.59 | D31: F3 DAVAI ENRSPV10 | E31: 45.19709 | F31: 4.66906 | G31: L'Homme, 07790 Saint-Alban-d'Ay, France | H31: 7 | I31: Bâtiment à construire - C | J31: KEVEL | K31: 45726 | L31: 45758 | M31: SOCOTEC POWER SERVICES | N31: 45758 | O31: 45831 | P31: DOMESOLAR NPA 3.45 | Q31: DMEGC-DM455M10RT-54HSW-HBW | R31: =_xlfn.XLOOKUP(Tableau2[[#This Row],[ID référent]],Feuil4!A:A,Feuil4!BD:BD) -> Yasser BADREZZAMANE | S31: =IF(Tableau2[[#This Row],[Contact Chargé Exploitation]]="Parfait MEZEME ONA","06 63 06 94 73","06 74 09 71 44") -> 06 74 09 71 44 | T31: Jean-Paul THOROGOOD | U31: =IF(Tableau2[[#This Row],[Contact Gestion actif]]="Victor PONTAIS","06 69 21 76 42","06 74 94 09 90") -> 06 74 94 09 90 | W31: X | Y31: 1.0337699 | AC31: Oui | AD31: Oui | AE31: Non
A32: 99373 | B32: Hangar Yannick CLEMENT | C32: 331.24 | D32: F3 GIRASPV15 | E32: 43.04786 | F32: 0.85301 | G32: Gazailles, 31160 Estadens, France | H32: 31 | I32: Bâtiment à construire - C | J32: KEVEL | K32: 45733 | L32: 45761 | M32: BUREAU VERITAS | N32: 45775 | O32: 45800 | P32: DOMESOLAR NPA 3.45 | Q32: DMEGC-DM455M10RT-B54HSW | R32: =_xlfn.XLOOKUP(Tableau2[[#This Row],[ID référent]],Feuil4!A:A,Feuil4!BD:BD) -> Parfait MEZEME ONA | S32: =IF(Tableau2[[#This Row],[Contact Chargé Exploitation]]="Parfait MEZEME ONA","06 63 06 94 73","06 74 09 71 44") -> 06 63 06 94 73 | T32: Jean-Paul THOROGOOD | U32: =IF(Tableau2[[#This Row],[Contact Gestion actif]]="Victor PONTAIS","06 69 21 76 42","06 74 94 09 90") -> 06 74 94 09 90 | W32: X | Y32: 1.1032093 | AC32: Oui | AD32: Oui | AE32: Non
A33: 3384 | B33: Concept-TY Chambray 2 | C33: 118.37 | D33: F2 DAVAI ENRSPV7 | E33: 47.32796 | F33: 0.70112 | G33: Rue Etienne Cosson, 37170 Chambray-lès-Tours, France | H33: 37 | I33: Toiture existante / PV Ready | J33: REGIESOLAIRE | K33: 45614 | L33: 45744 | M33: SOCOTEC POWER SERVICES | N33: 45771 | O33: 45832 | P33: Soprasolar FixEvoTilt | Q33: JKM445N-54HL4R-V | R33: =_xlfn.XLOOKUP(Tableau2[[#This Row],[ID référent]],Feuil4!A:A,Feuil4!BD:BD) -> Yasser BADREZZAMANE | S33: =IF(Tableau2[[#This Row],[Contact Chargé Exploitation]]="Parfait MEZEME ONA","06 63 06 94 73","06 74 09 71 44") -> 06 74 09 71 44 | T33: Victor PONTAIS | U33: =IF(Tableau2[[#This Row],[Contact Gestion actif]]="Victor PONTAIS","06 69 21 76 42","06 74 94 09 90") -> 06 69 21 76 42 | W33: X | Y33: 0.96714355 | AC33: Oui | AD33: Oui | AE33: Non
A34: 35280 | B34: Hangar Patrick BLANCHET | C34: 159.25 | D34: F3 DAVAI ENRSPV14 | E34: 44.36059 | F34: 5.07619 | G34: Les Exclis, 26110 Venterol, France | H34: 26 | I34: Bâtiment à construire - C | J34: KEVEL | K34: 45775 | L34: 45789 | M34: SOCOTEC POWER SERVICES | N34: 45802 | O34: 45838 | P34: DOMESOLAR NPA 3.45 | Q34: DMEGC-DM455M10RT-B54HSW | R34: =_xlfn.XLOOKUP(Tableau2[[#This Row],[ID référent]],Feuil4!A:A,Feuil4!BD:BD) -> Yasser BADREZZAMANE | S34: =IF(Tableau2[[#This Row],[Contact Chargé Exploitation]]="Parfait MEZEME ONA","06 63 06 94 73","06 74 09 71 44") -> 06 74 09 71 44 | T34: Victor PONTAIS | U34: =IF(Tableau2[[#This Row],[Contact Gestion actif]]="Victor PONTAIS","06 69 21 76 42","06 74 94 09 90") -> 06 69 21 76 42 | W34: X | Y34: 0.94566271 | AC34: Oui | AD34: Oui | AE34: Non
A35: 3334 | B35: MATHIEU Vincent | C35: 218.4 | D35: F3 GIRASPV15 | E35: 43.24989 | F35: 2.64117 | G35: Lieu-dit Les Avals 11700 LA REDORTE | H35: 11 | I35: Bâtiment à construire - C | J35: KEVEL | K35: 45789 | L35: 45803 | M35: BUREAU VERITAS | N35: 45819 | O35: 45838 | P35: DOMESOLAR NPA 3.45 | Q35: DMEGC-DM455M10RT-B54HSW | R35: =_xlfn.XLOOKUP(Tableau2[[#This Row],[ID référent]],Feuil4!A:A,Feuil4!BD:BD) -> Yasser BADREZZAMANE | S35: =IF(Tableau2[[#This Row],[Contact Chargé Exploitation]]="Parfait MEZEME ONA","06 63 06 94 73","06 74 09 71 44") -> 06 74 09 71 44 | T35: Jean-Paul THOROGOOD | U35: =IF(Tableau2[[#This Row],[Contact Gestion actif]]="Victor PONTAIS","06 69 21 76 42","06 74 94 09 90") -> 06 74 94 09 90 | W35: X | Y35: 0.86722429 | Z35: Déclenchement AHCP récurrent | AC35: Oui | AD35: Oui | AE35: Non
A36: 82721 | B36: Cheraud | C36: 499.59 | D36: F3 DAVAI ENRSPV13 | E36: 47.355 | F36: -1.83701 | G36: Bellevue, 44260 Malville, France | H36: 44 | I36: Bâtiment à construire - A2 | J36: OFT | K36: 45748 | L36: 45775 | M36: SOCOTEC POWER SERVICES | N36: 45793 | O36: 45856 | P36: DOMESOLAR NPA 3.45 | Q36: DMEGC-DM455M10RT-B54HSW | R36: =_xlfn.XLOOKUP(Tableau2[[#This Row],[ID référent]],Feuil4!A:A,Feuil4!BD:BD) -> Parfait MEZEME ONA | S36: =IF(Tableau2[[#This Row],[Contact Chargé Exploitation]]="Parfait MEZEME ONA","06 63 06 94 73","06 74 09 71 44") -> 06 63 06 94 73 | T36: Jean-Paul THOROGOOD | U36: =IF(Tableau2[[#This Row],[Contact Gestion actif]]="Victor PONTAIS","06 69 21 76 42","06 74 94 09 90") -> 06 74 94 09 90 | W36: X | Y36: 1.0196579 | AC36: Oui | AD36: Oui | AE36: Non
A37: 95919 | B37: Hangar Frédéric CASTET | C37: 268.65 | D37: F3 DAVAI ENRSPV13 | E37: 43.043896 | F37: 0.859961 | G37: 11 carrère de la Gentille, ESTADENS, 31160 | H37: 31 | I37: Toiture existante / Rénovation | J37: NEOXOM | K37: 45769 | L37: 45785 | M37: BUREAU VERITAS | N37: 45750 | O37: 45803 | P37: DOMESOLAR NPA 3.45 | Q37: DMEGC-DM455M10RT-54HSW-HBW | R37: =_xlfn.XLOOKUP(Tableau2[[#This Row],[ID référent]],Feuil4!A:A,Feuil4!BD:BD) -> Yasser BADREZZAMANE | S37: =IF(Tableau2[[#This Row],[Contact Chargé Exploitation]]="Parfait MEZEME ONA","06 63 06 94 73","06 74 09 71 44") -> 06 74 09 71 44 | T37: Jean-Paul THOROGOOD | U37: =IF(Tableau2[[#This Row],[Contact Gestion actif]]="Victor PONTAIS","06 69 21 76 42","06 74 94 09 90") -> 06 74 94 09 90 | V37: X | W37: X | Y37: 0.94721199 | AC37: Non | AD37: Non | AE37: Non
A38: 32074 | B38: Didier - PRIEUR | C38: 499.59 | D38: F3 DAVAI ENRSPV10 | E38: 44.84159 | F38: 4.96118 | G38: Quartier de Montalivet 26120 Montmeyran | H38: 26 | I38: Bâtiment à construire - C | J38: KEVEL | K38: 45789 | L38: 45817 | M38: SOCOTEC POWER SERVICES | N38: 45831 | O38: 45862 | P38: DOMESOLAR NPA 3.45 | Q38: DMEGC-DM455M10RT-54HSW-HBW | R38: =_xlfn.XLOOKUP(Tableau2[[#This Row],[ID référent]],Feuil4!A:A,Feuil4!BD:BD) -> Yasser BADREZZAMANE | S38: =IF(Tableau2[[#This Row],[Contact Chargé Exploitation]]="Parfait MEZEME ONA","06 63 06 94 73","06 74 09 71 44") -> 06 74 09 71 44 | T38: Jean-Paul THOROGOOD | U38: =IF(Tableau2[[#This Row],[Contact Gestion actif]]="Victor PONTAIS","06 69 21 76 42","06 74 94 09 90") -> 06 74 94 09 90 | V38: X | W38: X | Y38: 0.95201209 | AC38: Oui | AD38: Oui | AE38: Non
A39: 95309 | B39: Hangar Eric LOGNON | C39: 324.87 | D39: F3 DAVAI ENRSPV11 | E39: 46.60446 | F39: 3.61907 | G39: Château des Millets, 03230 Chevagnes, France | H39: 3 | I39: Bâtiment à construire - A2 | J39: PROSUNFRANCE | K39: 45803 | L39: 45818 | M39: SOCOTEC POWER SERVICES | N39: 45821 | O39: 45863 | P39: DOMESOLAR NPA 3.45 | Q39: DMEGC-DM455M10RT-54HSW-HBW | R39: =_xlfn.XLOOKUP(Tableau2[[#This Row],[ID référent]],Feuil4!A:A,Feuil4!BD:BD) -> Yasser BADREZZAMANE | S39: =IF(Tableau2[[#This Row],[Contact Chargé Exploitation]]="Parfait MEZEME ONA","06 63 06 94 73","06 74 09 71 44") -> 06 74 09 71 44 | T39: Jean-Paul THOROGOOD | U39: =IF(Tableau2[[#This Row],[Contact Gestion actif]]="Victor PONTAIS","06 69 21 76 42","06 74 94 09 90") -> 06 74 94 09 90 | W39: X | Y39: 1.3386521 | AC39: Oui | AD39: Oui | AE39: Non
A40: 30516 | B40: Hangar LAMIOT | C40: 343.07 | D40: F3 DAVAI ENRSPV10 | E40: 45.73247 | F40: 4.2053 | G40: La Gélopière, 42110 Feurs, France | H40: 42 | I40: Bâtiment à construire - C | J40: PROSUNFRANCE | K40: 45712 | L40: 45819 | M40: SOCOTEC POWER SERVICES | N40: 45825 | O40: 45854 | P40: DOMESOLAR NPA 3.45 | Q40: DMEGC-DM455M10RT-B54HSW | R40: =_xlfn.XLOOKUP(Tableau2[[#This Row],[ID référent]],Feuil4!A:A,Feuil4!BD:BD) -> Yasser BADREZZAMANE | S40: =IF(Tableau2[[#This Row],[Contact Chargé Exploitation]]="Parfait MEZEME ONA","06 63 06 94 73","06 74 09 71 44") -> 06 74 09 71 44 | T40: Jean-Paul THOROGOOD | U40: =IF(Tableau2[[#This Row],[Contact Gestion actif]]="Victor PONTAIS","06 69 21 76 42","06 74 94 09 90") -> 06 74 94 09 90 | V40: X | W40: X | Y40: 0.99477332 | AC40: Oui | AD40: Oui | AE40: Non
A41: 49814 | B41: VIEL | C41: 211.575 | D41: F3 DAVAI ENRSPV11 | E41: 47.46443 | F41: -1.40235 | G41: La Haute Bellangerais, 44390 Les Touches, France | H41: 44 | I41: Bâtiment à construire - A1 | J41: OFT | K41: 45803 | L41: 45812 | M41: SOCOTEC POWER SERVICES | N41: 45833 | O41: 45866 | P41: DOMESOLAR NPA 3.45 | Q41: DMEGC-DM455M10RT-54HSW-HBW | R41: =_xlfn.XLOOKUP(Tableau2[[#This Row],[ID référent]],Feuil4!A:A,Feuil4!BD:BD) -> Yasser BADREZZAMANE | S41: =IF(Tableau2[[#This Row],[Contact Chargé Exploitation]]="Parfait MEZEME ONA","06 63 06 94 73","06 74 09 71 44") -> 06 74 09 71 44 | T41: Jean-Paul THOROGOOD | U41: =IF(Tableau2[[#This Row],[Contact Gestion actif]]="Victor PONTAIS","06 69 21 76 42","06 74 94 09 90") -> 06 74 94 09 90 | V41: X | W41: X | Y41: 0.55276302 | Z41: Remplacement onduleur 20/10 | AC41: Oui | AD41: Oui | AE41: Non
A42: 61191 | B42: Serge Maltaverne | C42: 260.26 | D42: F3 DAVAI ENRSPV10 | E42: 46.69424 | F42: 4.10364 | G42: 638 route Chard, 71320 Sainte-Radegonde, France | H42: 71 | I42: Bâtiment à construire - C | J42: PROSUNFRANCE | K42: 45803 | L42: 45821 | M42: SOCOTEC POWER SERVICES | N42: 45842 | O42: 45868 | P42: DOMESOLAR NPA 3.45 | Q42: DMEGC-DM455M10RT-B54HSW | R42: =_xlfn.XLOOKUP(Tableau2[[#This Row],[ID référent]],Feuil4!A:A,Feuil4!BD:BD) -> Yasser BADREZZAMANE | S42: =IF(Tableau2[[#This Row],[Contact Chargé Exploitation]]="Parfait MEZEME ONA","06 63 06 94 73","06 74 09 71 44") -> 06 74 09 71 44 | T42: Jean-Paul THOROGOOD | U42: =IF(Tableau2[[#This Row],[Contact Gestion actif]]="Victor PONTAIS","06 69 21 76 42","06 74 94 09 90") -> 06 74 94 09 90 | W42: X | Y42: 0.9932335 | AC42: Oui | AD42: Oui | AE42: Non
A43: 3251 | B43: SCI KILJOR | C43: 109.2 | D43: F3 DAVAI ENRSPV13 | E43: 44.81516 | F43: 4.78922 | G43: 6 Rue Albert Camus, 07800 La Voulte-sur-Rhône, France | H43: 7 | I43: Toiture existante / Rénovation | J43: NEOXOM | K43: 45789 | L43: 45807 | M43: SOCOTEC POWER SERVICES | N43: 45827 | O43: 45873 | P43: DOMESOLAR NPA 3.45 | Q43: DMEGC-DM455M10RT-54HSW-HBW | R43: =_xlfn.XLOOKUP(Tableau2[[#This Row],[ID référent]],Feuil4!A:A,Feuil4!BD:BD) -> Yasser BADREZZAMANE | S43: =IF(Tableau2[[#This Row],[Contact Chargé Exploitation]]="Parfait MEZEME ONA","06 63 06 94 73","06 74 09 71 44") -> 06 74 09 71 44 | T43: Jean-Paul THOROGOOD | U43: =IF(Tableau2[[#This Row],[Contact Gestion actif]]="Victor PONTAIS","06 69 21 76 42","06 74 94 09 90") -> 06 74 94 09 90 | W43: X | X43: X | Y43: 0.85059905 | AC43: Oui | AD43: Oui | AE43: Non
A44: 96147 | B44: Hangar Benjamin CHASSON | C44: 388.04 | D44: F3 DAVAI ENRSPV13 | E44: 44.89225 | F44: 4.87492 | G44: 465 Rue Jean Rostand, 26800 Portes-lès-Valence, France | H44: 26 | I44: Bâtiment à construire - C | J44: NEOXOM | K44: 45789 | L44: 45817 | M44: SOCOTEC POWER SERVICES | N44: 45827 | O44: 45859 | P44: DOMESOLAR NPA 3.45 | Q44: DMEGC-DM445M10RT-54HSW-HBW | R44: =_xlfn.XLOOKUP(Tableau2[[#This Row],[ID référent]],Feuil4!A:A,Feuil4!BD:BD) -> Yasser BADREZZAMANE | S44: =IF(Tableau2[[#This Row],[Contact Chargé Exploitation]]="Parfait MEZEME ONA","06 63 06 94 73","06 74 09 71 44") -> 06 74 09 71 44 | T44: Jean-Paul THOROGOOD | U44: =IF(Tableau2[[#This Row],[Contact Gestion actif]]="Victor PONTAIS","06 69 21 76 42","06 74 94 09 90") -> 06 74 94 09 90 | W44: X | Y44: 0.72874985 | Z44: Remplacement onduleur 20/10 | AC44: Oui | AD44: Oui | AE44: Non
A45: 81492 | B45: Bourgeois | C45: 225.68 | D45: F3 GIRASPV15 | E45: 47.44106 | F45: -1.27682 | G45: Le Roscouët, 44440 Teillé, France | H45: 44 | I45: Bâtiment à construire - A1 | J45: INNOVA | K45: 45776 | L45: 45797 | M45: SOCOTEC POWER SERVICES | N45: 45824 | O45: 45875 | P45: DOME SOLAR Helios B² | Q45: DMEGC-DM455M10RT-B54HSW | R45: =_xlfn.XLOOKUP(Tableau2[[#This Row],[ID référent]],Feuil4!A:A,Feuil4!BD:BD) -> Parfait MEZEME ONA | S45: =IF(Tableau2[[#This Row],[Contact Chargé Exploitation]]="Parfait MEZEME ONA","06 63 06 94 73","06 74 09 71 44") -> 06 63 06 94 73 | T45: Jean-Paul THOROGOOD | U45: =IF(Tableau2[[#This Row],[Contact Gestion actif]]="Victor PONTAIS","06 69 21 76 42","06 74 94 09 90") -> 06 74 94 09 90 | V45: X | W45: X | Y45: 0.98877631 | AC45: Non | AD45: Non | AE45: Non
A46: 3391 | B46: EARL GOUNY | C46: 331.24 | D46: F3 GIRASPV15 | E46: 44.56123 | F46: 0.24227 | G46: Gouny, 47350 Escassefort, France | H46: 47 | I46: Bâtiment à construire - C | J46: HBBAT | K46: 45727 | L46: 45817 | M46: SOCOTEC POWER SERVICES | N46: 45824 | O46: 45880 | P46: DOMESOLAR NPA 3.45 | Q46: DMEGC-DM455M10RT-54HSW-HBW | R46: =_xlfn.XLOOKUP(Tableau2[[#This Row],[ID référent]],Feuil4!A:A,Feuil4!BD:BD) -> Parfait MEZEME ONA | S46: =IF(Tableau2[[#This Row],[Contact Chargé Exploitation]]="Parfait MEZEME ONA","06 63 06 94 73","06 74 09 71 44") -> 06 63 06 94 73 | T46: Jean-Paul THOROGOOD | U46: =IF(Tableau2[[#This Row],[Contact Gestion actif]]="Victor PONTAIS","06 69 21 76 42","06 74 94 09 90") -> 06 74 94 09 90 | W46: X | Y46: 1.0442442 | AC46: Non | AD46: Oui | AE46: Non
A47: 3085 | B47: Hangar Maxime Bayle | C47: 324.87 | D47: F3 GIRASPV15 | E47: 43.30401 | F47: 2.07536 | G47: Château Lagoual, 11400 Lasbordes, France | H47: 11 | I47: Bâtiment à construire - A1 | J47: Yama Energies | K47: 45831 | L47: 45825 | M47: BUREAU VERITAS | N47: 45863 | O47: 45898 | P47: DOMESOLAR NPA 3.45 | Q47: DMEGC-DM455M10RT-B54HSW | R47: =_xlfn.XLOOKUP(Tableau2[[#This Row],[ID référent]],Feuil4!A:A,Feuil4!BD:BD) -> Yasser BADREZZAMANE | S47: =IF(Tableau2[[#This Row],[Contact Chargé Exploitation]]="Parfait MEZEME ONA","06 63 06 94 73","06 74 09 71 44") -> 06 74 09 71 44 | T47: Jean-Paul THOROGOOD | U47: =IF(Tableau2[[#This Row],[Contact Gestion actif]]="Victor PONTAIS","06 69 21 76 42","06 74 94 09 90") -> 06 74 94 09 90 | W47: X | Y47: 0.94645883 | AC47: Oui | AD47: Oui | AE47: Non
A48: 97565 | B48: Commune De Pomas | C48: 254.8 | D48: F3 DAVAI ENRSPV14 | E48: 43.11473 | F48: 2.2963 | G48: Rue de la Mairie, 11250 Pomas, France | H48: 11 | I48: Bâtiment à construire - C | J48: KEVEL | K48: 45803 | L48: 45826 | M48: BUREAU VERITAS | N48: 45849 | O48: 45890 | P48: DOMESOLAR NPA 3.45 | Q48: DMEGC-DM455M10RT-B54HSW | R48: =_xlfn.XLOOKUP(Tableau2[[#This Row],[ID référent]],Feuil4!A:A,Feuil4!BD:BD) -> Parfait MEZEME ONA | S48: =IF(Tableau2[[#This Row],[Contact Chargé Exploitation]]="Parfait MEZEME ONA","06 63 06 94 73","06 74 09 71 44") -> 06 63 06 94 73 | T48: Victor PONTAIS | U48: =IF(Tableau2[[#This Row],[Contact Gestion actif]]="Victor PONTAIS","06 69 21 76 42","06 74 94 09 90") -> 06 69 21 76 42 | W48: X | Y48: 0.95578183 | AC48: Oui | AD48: Oui | AE48: Non
A49: 95592 | B49: GFA LASCOMBES - ANTOINE MICOULEAU | C49: 277.095 | D49: F3 DAVAI ENRSPV14 | E49: 43.26257 | F49: 2.15214 | G49: Lascombes, 11170 Alzonne, France | H49: 11 | I49: Bâtiment à construire - A1 | J49: Yama Energies | K49: 45803 | L49: 45826 | M49: BUREAU VERITAS | N49: 45849 | O49: 45888 | P49: DOME SOLAR Helios B² | Q49: DMEGC-DM455M10RT-B54HSW | R49: =_xlfn.XLOOKUP(Tableau2[[#This Row],[ID référent]],Feuil4!A:A,Feuil4!BD:BD) -> Parfait MEZEME ONA | S49: =IF(Tableau2[[#This Row],[Contact Chargé Exploitation]]="Parfait MEZEME ONA","06 63 06 94 73","06 74 09 71 44") -> 06 63 06 94 73 | T49: Victor PONTAIS | U49: =IF(Tableau2[[#This Row],[Contact Gestion actif]]="Victor PONTAIS","06 69 21 76 42","06 74 94 09 90") -> 06 69 21 76 42 | V49: X | W49: X | Y49: 1.4681898 | AC49: Oui | AD49: Non | AE49: Non
A50: 34481 | B50: HANGAR Gérald Guillet | C50: 197.8 | D50: F2 DAVAI ENRSPV7 | E50: 45.98895 | F50: -0.21354 | G50: Bois Rond, 17510 Les Éduts, France | H50: 17 | I50: Bâtiment à construire - A2 | J50: Eiffage | K50: 45425 | L50: 45436 | M50: SOCOTEC POWER SERVICES | N50: 45439 | O50: 45554 | P50: DOMESOLAR NPA 3.45 | Q50: DMEGC-DM430M10T-54HSW-HBW | R50: =_xlfn.XLOOKUP(Tableau2[[#This Row],[ID référent]],Feuil4!A:A,Feuil4!BD:BD) -> Parfait MEZEME ONA | S50: =IF(Tableau2[[#This Row],[Contact Chargé Exploitation]]="Parfait MEZEME ONA","06 63 06 94 73","06 74 09 71 44") -> 06 63 06 94 73 | T50: Victor PONTAIS | U50: =IF(Tableau2[[#This Row],[Contact Gestion actif]]="Victor PONTAIS","06 69 21 76 42","06 74 94 09 90") -> 06 69 21 76 42 | W50: X | Y50: 1.2322138 | AC50: Non | AD50: Oui | AE50: Non
A51: 35451 | B51: Hangar Joris SAINT MARTIN | C51: 218.4 | D51: F3 DAVAI ENRSPV10 | E51: 43.56698 | F51: 0.0163 | G51: Palancot, 32160 Jû-Belloc, France | H51: 32 | I51: Bâtiment à construire - C | J51: Acrom | K51: 45614 | L51: 45639 | M51: SOCOTEC POWER SERVICES | N51: 45649 | O51: 45735 | P51: DOMESOLAR NPA 3.45 | Q51: DMEGC-DM455M10RT-54HSW-HBW | R51: =_xlfn.XLOOKUP(Tableau2[[#This Row],[ID référent]],Feuil4!A:A,Feuil4!BD:BD) -> Parfait MEZEME ONA | S51: =IF(Tableau2[[#This Row],[Contact Chargé Exploitation]]="Parfait MEZEME ONA","06 63 06 94 73","06 74 09 71 44") -> 06 63 06 94 73 | T51: Jean-Paul THOROGOOD | U51: =IF(Tableau2[[#This Row],[Contact Gestion actif]]="Victor PONTAIS","06 69 21 76 42","06 74 94 09 90") -> 06 74 94 09 90 | W51: X | Y51: 0.9742908 | AC51: Oui | AD51: Oui | AE51: Non
A52: 58166 | B52: GAYET 42 | C52: 309.4 | D52: F3 DAVAI ENRSPV10 | E52: 45.57895 | F52: 4.21851 | G52: 419 Chemin des Seigles, 42210 Craintilleux, France | H52: 42 | I52: Bâtiment à construire - C | J52: 3C instal | K52: 45740 | L52: 45754 | M52: SOCOTEC POWER SERVICES | N52: 45763 | O52: 45790 | P52: DOMESOLAR NPA 3.45 | Q52: DMEGC-DM455M10RT-B54HSW | R52: =_xlfn.XLOOKUP(Tableau2[[#This Row],[ID référent]],Feuil4!A:A,Feuil4!BD:BD) -> Yasser BADREZZAMANE | S52: =IF(Tableau2[[#This Row],[Contact Chargé Exploitation]]="Parfait MEZEME ONA","06 63 06 94 73","06 74 09 71 44") -> 06 74 09 71 44 | T52: Jean-Paul THOROGOOD | U52: =IF(Tableau2[[#This Row],[Contact Gestion actif]]="Victor PONTAIS","06 69 21 76 42","06 74 94 09 90") -> 06 74 94 09 90 | W52: X | Y52: 0.93134409 | AC52: Oui | AD52: Oui | AE52: Non
A53: 95992 | B53: Hangar Sebastien RUDELLE | C53: 309.4 | D53: F3 DAVAI ENRSPV11 | E53: 44.21679 | F53: 2.63349 | G53: Crayssac, 12120 Salmiech, France | H53: 12 | I53: Bâtiment à construire - C | J53: 3C instal | K53: 45719 | L53: 45771 | M53: BUREAU VERITAS | N53: 45790 | O53: 45826 | P53: DOMESOLAR NPA 3.45 | Q53: DMEGC-DM455M10RT-54HSW-HBW | R53: =_xlfn.XLOOKUP(Tableau2[[#This Row],[ID référent]],Feuil4!A:A,Feuil4!BD:BD) -> Parfait MEZEME ONA | S53: =IF(Tableau2[[#This Row],[Contact Chargé Exploitation]]="Parfait MEZEME ONA","06 63 06 94 73","06 74 09 71 44") -> 06 63 06 94 73 | T53: Jean-Paul THOROGOOD | U53: =IF(Tableau2[[#This Row],[Contact Gestion actif]]="Victor PONTAIS","06 69 21 76 42","06 74 94 09 90") -> 06 74 94 09 90 | W53: X | Y53: 0.9442935 | AC53: Non | AD53: Oui | AE53: Non
A54: 98563 | B54: =_xlfn.XLOOKUP(Tableau2[[#This Row],[ID référent]],Feuil4!A:A,Feuil4!B:B) -> TOURNIER | C54: =_xlfn.XLOOKUP(Tableau2[[#This Row],[ID référent]],Feuil4!A:A,Feuil4!P:P) -> 197.925 | D54: F2 DAVAI ENRSPV7 | E54: =_xlfn.XLOOKUP(Tableau2[[#This Row],[ID référent]],Feuil4!A:A,Feuil4!AF:AF) -> 43.3172 | F54: =_xlfn.XLOOKUP(Tableau2[[#This Row],[ID référent]],Feuil4!A:A,Feuil4!AG:AG) -> 1.12116 | G54: 548 Route de Marignac, 31430 Gratens, France | H54: =LEFT(_xlfn.XLOOKUP(Tableau2[[#This Row],[ID référent]],Feuil4!A:A,Feuil4!F:F),2) -> 31 | I54: Toiture existante / Rénovation | J54: =_xlfn.XLOOKUP(Tableau2[[#This Row],[ID référent]],Feuil4!A:A,Feuil4!AP:AP) -> KEVEL | K54: 45565 | L54: 45582 | M54: SOCOTEC POWER SERVICES | N54: 45583 | O54: =_xlfn.XLOOKUP(Tableau2[[#This Row],[ID référent]],Feuil4!A:A,Feuil4!D:D) -> 45670 | P54: DOMESOLAR Ital Solar | Q54: DMEGC-DM455M10RT-54HSW-HBW | R54: =_xlfn.XLOOKUP(Tableau2[[#This Row],[ID référent]],Feuil4!A:A,Feuil4!BD:BD) -> Parfait MEZEME ONA | S54: =IF(Tableau2[[#This Row],[Contact Chargé Exploitation]]="Parfait MEZEME ONA","06 63 06 94 73","06 74 09 71 44") -> 06 63 06 94 73 | T54: Victor PONTAIS | U54: =IF(Tableau2[[#This Row],[Contact Gestion actif]]="Victor PONTAIS","06 69 21 76 42","06 74 94 09 90") -> 06 69 21 76 42 | W54: X | X54: X | Y54: 0.76 | AC54: Oui | AD54: Oui | AE54: Non

Sheet Feuil4
A1: ID Pipedrive | B1: undefined | C1: Projet/SPV | D1: Date Mise en Service | E1: Adresse | F1: Code Postale | G1: Ville | H1: Contrat de bail | I1: Type de centrale | J1: Client | K1: Type de Contrat | L1: Numéro BTA | M1: Numéro CARD-I | N1: Nombre de PDL | O1: Numéro PRM | P1: Puissance crête (kWc) | Q1: Puissance maximale (kVA) | R1: Puissance souscrite (kVA) | S1: Productible P50 kWh/kWc/an | T1: Production P50 kWh/an | U1: Productible Variabilité P50 | V1: PR Go construction | W1: Productible Go Construction kWh/kWc | X1: Domaine de tension | Y1: Date Achat T0 | Z1: Tarif d'Achat (€/kWh) | AA1: Convention Tarif Essais | AB1: Contrat ACC | AC1: Acheteur | AD1: GRD | AE1: Surface modules (m²) | AF1: Latitude | AG1: Longitude | AH1: Financement | AI1: Mentions particulières | AJ1: Mainteneur | AK1: Nom complet du Client | AL1: Email principal du client | AM1: Email secondaire client | AN1: Téléphone principal client | AO1: Téléphone secondaire client | AP1: Installateur électrique | AQ1: Installateur structure | AR1: Loyer | AS1: Échéance | AT1: Echéance Année en cours | AU1: Type de Loyer | AV1: TVA Applicable | AW1: % du CA | AX1: Montant du Loyer fixe | AY1: Fréquence | AZ1: Loyer >20ans | BA1: Type de Loyer Post 20ans | BB1: % Du CA Post 20ans | BC1: Montant du Loyer fixe (>20ans) | BD1: Chargé d'Exploitation | BE1: Gestionnaire d'Actif | BF1: Chef de Projet | BG1: Chargé d'affaire | BH1: Reference Contrat Maintenance | BI1: Reference Contrat Developpement | BJ1: Reference Contrat O&M | BK1: Refacturation Girasole Services | BL1: Refacturation Télésurveillance F2 | BM1: Date Début Exploitation | BN1: Date PV Transfert en Exploitation signé | BO1: Date PV de fin de garantie de performance signé | BP1: Montant Pénalités EPC 1an | BQ1: Montant Pénalités Retard Contrat d'achat | BR1: Titulaire du Bail | BS1: Adresse Titulaire du Bail | BT1: Ville Titulaire du Bail | BU1: Code Postale Titulaire du Bail | BV1: SIREN (si applicable) | BW1: Date fin du Bail | BX1: Activité sous toiture | BY1: Date Début Contrat d'Achat OA | BZ1: Date fin du Contrat d'Achat OA | CA1: Date signature Contrat D'achat OA | CB1: Indexation du Loyer | CC1: Type d'élément | CD1: Chemin d'accès
A2: 3338 | B2: CHEVRIER | C2: DAVAI ENRSPV10 | D2: 45959 | E2: 712 Rue de la Croix de Romont | F2: 88390 | G2: Darnieulles | H2: BaC | I2: Toiture inclinée | J2: Agriculteur | K2: S21 | L2: BTA1200149 | M2: 9818700 | N2: 1 | O2: 50095153915292 | P2: 318.5 | Q2: 250 | R2: 249 | S2: 1156 | T2: 368186 | U2: 0.054 | V2: 0.86647242 | W2: 1136.6797 | X2: BT | Y2: 45314 | Z2: 0.1208 | AA2: FALSE | AB2: FALSE | AC2: EDF OA | AD2: ENEDIS | AE2: 1398.676 | AF2: 48.19827 | AG2: 6.33986 | AH2: N°3 - Kyoto (SPV 10,13 &14) | AI2: Mot de passe onduleur : 0000000a | AJ2: EIFFAGE | AK2: THOMAS CHEVRIER | AL2: gaecdallonzy@laposte.net | AN2: +33619062549 | AP2: VOLTISSIMA | AQ2: CANCE | AR2: FALSE | AV2: FALSE | AZ2: FALSE | BD2: Yasser BADREZZAMANE | BE2: Johan LAGARDE | BF2: Ibtissam ABSSI | BG2: Sébastien GUYOUX | BH2: MTN-CONT-004-Contrat_EIFFAGE_maintenance_PV_BT-001 | BI2: DEV-CONT-SPV010-Contrat_DEV_EPC_DAVAI_ENR-1 | BJ2: EX-CONT-SPV010-Contrat_Suivi_O&M_Gestion_Actifs_DAVAI_ENR-1 | BK2: 856 | BL2: 188.2895 | BX2: Stockage matériel + fourrage | CB2: FALSE | CC2: Élément | CD2: sites/ServiceOM-AssetManagement/Lists/Exploitation Data Centrale
A3: 98570 | B3: LATREILLE | C3: DAVAI ENRSPV14 | D3: 45958 | E3: Vaurs | F3: 19430 | G3: Sexcles | H3: BE | I3: Toiture inclinée | J3: Agriculteur | K3: S21 | L3: BTA1110971 | M3: 9255850 | N3: 1 | O3: 50031335405373 | P3: 352.17 | Q3: 280 | R3: 249 | S3: 1179.6 | T3: 415419.73 | U3: 0.054 | V3: 0.878 | W3: 1179.6 | X3: BT | Y3: 45161 | Z3: 0.1238 | AA3: FALSE | AB3: FALSE | AC3: EDF OA | AD3: ENEDIS | AE3: 1546.536 | AF3: 45.02811 | AG3: 2.02617 | AH3: N°3 - Kyoto (SPV 10,13 &14) | AI3: RAS | AJ3: EIFFAGE | AK3: Didier LATREILLE | AL3: didierlatreille0263@orange.fr | AN3: +33682109080 | AP3: 3C INSTAL | AQ3: BIOTECK | AR3: FALSE | AV3: FALSE | AZ3: FALSE | BD3: Parfait MEZEME ONA | BE3: Victor PONTAIS | BF3: Martin DE GUERRE | BG3: Alexandre COL | BH3: MTN-CONT-004-Contrat_EIFFAGE_maintenance_PV_BT-001 | BI3: DEV-CONT-SPV014_Contrat_DEV_EPC_DAVAI_ENR-1 (signed) (1) | BJ3: EX-CONT-SPV014-Contrat_Suivi_OM_Gestion_Actifs_DAVAI -ENR-01 (1) | BK3: 856 | BL3: 200.64639 | BX3: stabulation et stockage | CB3: FALSE | CC3: Élément | CD3: sites/ServiceOM-AssetManagement/Lists/Exploitation Data Centrale
A4: 99025 | B4: GARRELOU | C4: DAVAI ENRSPV14 | D4: 45958 | E4: Les Trieux | F4: 19220 | G4: Bassignac-le-Haut | H4: BE | I4: Toiture inclinée | J4: Agriculteur | K4: S21 | L4: BTA1160782 | M4: 9292350 | N4: 1 | O4: 50004127237174 | P4: 191 | Q4: 170 | R4: 146 | S4: 1164 | T4: 222324 | U4: 0.0504 | V4: 0.874 | W4: 1170 | X4: BT | Y4: 45250 | Z4: 0.1208 | AA4: FALSE | AB4: FALSE | AC4: EDF OA | AD4: ENEDIS | AE4: 837 | AF4: 45.19779 | AG4: 2.09035 | AH4: N°3 - Kyoto (SPV 10,13 &14) | AI4: RAS | AJ4: EIFFAGE | AK4: Romain Garrelou | AL4: romain.garrelou@hotmail.com | AN4: +33 6 37 24 67 62 | AP4: NEOXOM | AQ4: ACC | AR4: FALSE | AV4: FALSE | AZ4: FALSE | BD4: Parfait MEZEME ONA | BE4: Victor PONTAIS | BF4: Martin DE GUERRE | BG4: Alexandre COL | BH4: MTN-CONT-004-Contrat_EIFFAGE_maintenance_PV_BT-001 | BI4: DEV-CONT-SPV014_Contrat_DEV_EPC_DAVAI_ENR-1 (signed) (1) | BJ4: EX-CONT-SPV014-Contrat_Suivi_OM_Gestion_Actifs_DAVAI -ENR-01 (1) | BK4: 856 | BL4: 141.497 | BX4: Stabulation + Stockage Fourrage | CB4: FALSE | CC4: Élément | CD4: sites/ServiceOM-AssetManagement/Lists/Exploitation Data Centrale
A5: 99131 | B5: LANNES | C5: GIRASPV16 | D5: 45957 | E5: Lieu-dit Mamour | F5: 11270 | G5: La Cassaigne | H5: BaC | I5: Toiture inclinée | J5: Agriculteur | K5: S21 | L5: BTA1269517 | M5: 9622450 | N5: 1 | O5: 50018307634341 | P5: 308 | Q5: 248 | R5: 248 | S5: 1182 | T5: 364056 | U5: 0.054 | V5: 0.8611 | W5: 1230.02 | X5: BT | Y5: 45425 | Z5: 0.1118 | AA5: FALSE | AB5: FALSE | AC5: EDF OA | AD5: ENEDIS | AE5: 1351 | AF5: 43.18474 | AG5: 1.99512 | AH5: N°4 | AI5: RAS | AJ5: EIFFAGE | AK5: Quentin LANNES | AL5: earlbds@gmail.com | AN5: +33630546473 | AP5: KEVEL | AQ5: MOMSTEEL | AR5: FALSE | AV5: FALSE | AZ5: FALSE | BD5: Parfait MEZEME ONA | BE5: Victor PONTAIS | BF5: Charbel BOUZERDAN | BG5: Gabriel AYMA | BH5: MTN-CONT-004-Contrat_EIFFAGE_maintenance_PV_BT-001 | BI5: DEV-CONT-SPV016_Contrat_DEV_EPC_DAVAI_ENR-1 | BJ5: EX-CONT-SPV016-Contrat_Suivi_OM_Gestion_Actifs_DAVAI -ENR-01 | BK5: 856 | BL5: 184.436 | BX5: Stockage matériels et légumes | CB5: FALSE | CC5: Élément | CD5: sites/ServiceOM-AssetManagement/Lists/Exploitation Data Centrale
A6: 3427 | B6: ESCOULA | C6: DAVAI ENRSPV14 | D6: 45957 | E6: Trouley | F6: 65140 | G6: Trouley-Labarthe | H6: BaC | I6: Toiture inclinée | J6: Agriculteur | K6: S21 | L6: BTA1204745|BTA1204781 | M6: 9683200|9702850 | N6: 2 | O6: 50018019831551|50010783941577 | P6: 500 | Q6: 500 | R6: 408 | S6: 1181.5 | T6: 590750 | U6: 0.054 | V6: 0.877 | W6: 1178.2 | X6: BT | Y6: 45327 | Z6: 0.117 | AA6: FALSE | AB6: FALSE | AC6: EDF OA | AD6: ENEDIS | AE6: 2194 | AF6: 43.31659 | AG6: 0.24262 | AH6: N°3 - Kyoto (SPV 10,13 &14) | AI6: RAS | AJ6: EIFFAGE | AK6: Thierry ESCOULA | AL6: thierry.escoula1@orange.fr | AN6: +33678642764 | AP6: ACROM | AQ6: GIRAUD | AR6: FALSE | AV6: FALSE | AZ6: FALSE | BD6: Parfait MEZEME ONA | BE6: Victor PONTAIS | BF6: Gwendal HART | BG6: Victor REVUELTA | BH6: MTN-CONT-004-Contrat_EIFFAGE_maintenance_PV_BT-001 | BI6: DEV-CONT-SPV014_Contrat_DEV_EPC_DAVAI_ENR-1 (signed) (1) | BJ6: EX-CONT-SPV014-Contrat_Suivi_OM_Gestion_Actifs_DAVAI -ENR-01 (1) | BK6: 856 | BL6: 254.9 | BX6: Ovins, Bovins, matériel et fourrage | CB6: FALSE | CC6: Élément | CD6: sites/ServiceOM-AssetManagement/Lists/Exploitation Data Centrale
A7: 95955 | B7: CONSOLI | C7: DAVAI ENRSPV13 | D7: 45953 | E7: Rte de l'Escauderie | F7: 24130 | G7: Prigonrieux | H7: BaC | I7: Toiture inclinée | J7: Agriculteur | K7: S21 | L7: BTA1141881 | M7: 8961150 | N7: 1 | O7: 50060857585907 | P7: 319 | Q7: 249 | R7: 249 | S7: 1145 | T7: 365255 | U7: 0.054 | V7: 0.8654 | W7: 1144.11 | X7: BT | Y7: 45216 | Z7: 0.1238 | AA7: FALSE | AB7: FALSE | AC7: EDF OA | AD7: ENEDIS | AE7: 1399 | AF7: 44.85555 | AG7: 0.43414 | AH7: N°3 - Kyoto (SPV 10,13 &14) | AI7: RAS | AJ7: EIFFAGE | AK7: CONSOLI | AL7: consoli.et.fils@wanadoo.fr | AN7: +33689273405 | AP7: ACROM | AQ7: MOMSTEEL | AR7: FALSE | AV7: FALSE | AZ7: FALSE | BD7: Parfait MEZEME ONA | BE7: Johan LAGARDE | BF7: Gwendal HART | BG7: Victor REVUELTA | BH7: MTN-CONT-004-Contrat_EIFFAGE_maintenance_PV_BT-001 | BI7: DEV-CONT-SPV013-Contrat_DEV_EPC_DAVAI_ENR-1 | BJ7: EX-CONT-SPV013-Contrat_Suivi_OM_Gestion_Actifs_DAVAI -ENR-01 | BK7: 856 | BL7: 188.473 | BX7: Stockage de camions + stockage de matériel | CB7: FALSE | CC7: Élément | CD7: sites/ServiceOM-AssetManagement/Lists/Exploitation Data Centrale
A8: 33087 | B8: BAILLY | C8: DAVAI ENRSPV10 | D8: 45952 | E8: La Cave | F8: 03230 | G8: Garnat-sur-Engièvre | H8: BaC | I8: Toiture inclinée | J8: Agriculteur | K8: S21 | L8: BTA1038999 | BTA1038997 | M8: 9124750 | 9085000 | N8: 2 | O8: 50048702663389 | 50063174443341 | P8: 499.59 | Q8: 440 | R8: 417.6 | S8: 1209 | T8: 604004.31 | U8: 0.054 | V8: 0.8761 | W8: 1191.44 | X8: BT | Y8: 45036 | Z8: 0.1312 | AA8: FALSE | AB8: FALSE | AC8: EDF OA | AD8: ENEDIS | AE8: 2193.922 | AF8: 46.64674 | AG8: 3.67873 | AH8: N°3 - Kyoto (SPV 10,13 &14) | AI8: Mot de passe onduleur : Exploitation2023 | AJ8: EIFFAGE | AK8: Matthieu BAILLY | AL8: mouss.bailly@wanadoo.fr | AN8: +33672402650 | AO8: +33248721293 | AP8: PROSUNFRANCE | AQ8: CRAI + EMCB | AR8: FALSE | AV8: FALSE | AZ8: FALSE | BD8: Yasser BADREZZAMANE | BE8: Johan LAGARDE | BF8: Nicolas PETROPAVLOVSKY | BG8: Sébastien GUYOUX | BH8: MTN-CONT-004-Contrat_EIFFAGE_maintenance_PV_BT-001 | BI8: DEV-CONT-SPV010-Contrat_DEV_EPC_DAVAI_ENR-1 | BJ8: EX-CONT-SPV010-Contrat_Suivi_O&M_Gestion_Actifs_DAVAI_ENR-1 | BK8: 856 | BL8: 254.74953 | BX8: Stockage matériel (44%), fourrage de paille (44%), animaux (12%) | CB8: FALSE | CC8: Élément | CD8: sites/ServiceOM-AssetManagement/Lists/Exploitation Data Centrale
A9: 3405 | B9: GROS | C9: GIRASPV17 | D9: 45952 | E9: 1892 Chem. des Brugues | F9: 82370 | G9: Nohic | H9: BaC | I9: Toiture inclinée | J9: Agriculteur | K9: S21 | L9: BTA1163927 | M9: 9669500 | N9: 1 | O9: 50094286186899 | P9: 264 | Q9: 220 | R9: 220 | S9: 1258 | T9: 332112 | U9: 0.054 | V9: 0.8854 | W9: 1258 | X9: BT | Y9: 45252 | Z9: 0.1208 | AA9: FALSE | AB9: FALSE | AC9: EDF OA | AD9: ENEDIS | AE9: 1159 | AF9: 43.87073 | AG9: 1.43036 | AH9: N°4 | AI9: RAS | AJ9: EIFFAGE | AK9: Véronique GROS | AL9: marc.blavette@wanadoo.fr | AN9: +33603293138 | AP9: Non indiqué | AQ9: MOMSTEEL | AR9: FALSE | AV9: FALSE | AZ9: FALSE | BD9: Parfait MEZEME ONA | BE9: Johan LAGARDE | BF9: Gwendal HART | BG9: Nicolas CADENE | BH9: MTN-CONT-004-Contrat_EIFFAGE_maintenance_PV_BT-001 | BI9: DEV-CONT-SPV017_Contrat_DEV_EPC_DAVAI_ENR-1 | BJ9: EX-CONT-SPV017-Contrat_Suivi_OM_Gestion_Actifs_DAVAI -ENR-01 | BK9: 856 | BL9: 168.288 | BX9: Rond de Ionge + boxes à chevaux/Stockage de matériel/Stockage de paille, foin et fourrage | CB9: FALSE | CC9: Élément | CD9: sites/ServiceOM-AssetManagement/Lists/Exploitation Data Centrale
A10: 99375 | B10: CLEMENT | C10: DAVAI ENRSPV14 | D10: 45951 | E10: 6 Gouterouch | F10: 31160 | G10: Estadens | H10: BE | I10: Toiture inclinée | J10: Agriculteur | K10: S21 | L10: BTA1144036 | M10: 9881650 | N10: 1 | O10: 50092984346706 | P10: 106 | Q10: 99 | R10: 99 | S10: 1175 | T10: 124550 | U10: 0.054 | V10: 0.8509 | W10: 1175 | X10: BT | Y10: 45226 | Z10: 0.1238 | AA10: FALSE | AB10: FALSE | AC10: EDF OA | AD10: ENEDIS | AE10: 468 | AF10: 43.0483 | AG10: 0.8525 | AH10: N°3 - Kyoto (SPV 10,13 &14) | AI10: RAS | AJ10: EIFFAGE | AK10: Yannick CLEMENT | AL10: clement.yannick31@gmail.com | AN10: +33610332718 | AP10: NEOXOM | AQ10: ACC | AR10: FALSE | AV10: FALSE | AZ10: FALSE | BD10: Parfait MEZEME ONA | BE10: Victor PONTAIS | BF10: Gwendal HART | BG10: Nicolas CADENE | BH10: MTN-CONT-004-Contrat_EIFFAGE_maintenance_PV_BT-001 | BI10: DEV-CONT-SPV014_Contrat_DEV_EPC_DAVAI_ENR-1 (signed) (1) | BJ10: EX-CONT-SPV014-Contrat_Suivi_OM_Gestion_Actifs_DAVAI -ENR-01 (1) | BK10: 856 | BL10: 110.302 | BX10: Stabulation | CB10: FALSE | CC10: Élément | CD10: sites/ServiceOM-AssetManagement/Lists/Exploitation Data Centrale
A11: 95611 | B11: TOUCHAIS | C11: DAVAI ENRSPV13 | D11: 45946 | E11: 3 Joffre | F11: 33580 | G11: Le Puy | H11: BaC | I11: Toiture inclinée | J11: Agriculteur | K11: S21 | L11: BTA1209116 | M11: 9030700 | N11: 1 | O11: 50055501601691 | P11: 309 | Q11: 249 | R11: 249 | S11: 1166 | T11: 360294 | U11: 0.054 | V11: 0.8685 | W11: 1159.9 | X11: BT | Y11: 45335 | Z11: 0.1174 | AA11: FALSE | AB11: FALSE | AC11: EDF OA | AD11: ENEDIS | AE11: 1359 | AF11: 44.655162 | AG11: 0.049253 | AH11: N°3 - Kyoto (SPV 10,13 &14) | AI11: RAS | AJ11: EIFFAGE | AK11: Benoit TOUCHAIS | AL11: elevage.touchais33@gmail.com | AN11: +33674642000 | AP11: OFT | AQ11: CANCE | AR11: FALSE | AV11: FALSE | AZ11: FALSE | BD11: Parfait MEZEME ONA | BE11: Johan LAGARDE | BF11: Ibtissam ABSSI | BG11: Victor REVUELTA | BH11: MTN-CONT-004-Contrat_EIFFAGE_maintenance_PV_BT-001 | BI11: DEV-CONT-SPV013-Contrat_DEV_EPC_DAVAI_ENR-1 | BJ11: EX-CONT-SPV013-Contrat_Suivi_OM_Gestion_Actifs_DAVAI -ENR-01 | BK11: 856 | BL11: 184.803 | BX11: Stockage de matériel agricole + fourrage + céréales | CB11: FALSE | CC11: Élément | CD11: sites/ServiceOM-AssetManagement/Lists/Exploitation Data Centrale
A12: 95610 | B12: TOUCHAIS | C12: GIRASPV16 | D12: 45946 | E12: 3 Joffre | F12: 33580 | G12: Le Puy | H12: BaC | I12: Toiture inclinée | J12: Agriculteur | K12: S21 | L12: BTA1209125|BTA1208955 | M12: 8895850|8895950 | N12: 2 | O12: 50054199141585|50019322151607 | P12: 499 | Q12: 440 | R12: 410 | S12: 1254 | T12: 625746 | U12: 0.054 | V12: 0.8382 | W12: 1214.89 | X12: BT | Y12: 45335 | Z12: 0.117 | AA12: FALSE | AB12: FALSE | AC12: EDF OA | AD12: ENEDIS | AE12: 2194 | AF12: 44.65593 | AG12: 0.04986 | AH12: N°4 | AI12: RAS | AJ12: EIFFAGE | AK12: Benoit TOUCHAIS | AL12: elevage.touchais33@gmail.com | AN12: +33674642000 | AP12: OFT | AQ12: CANCE | AR12: FALSE | AV12: FALSE | AZ12: FALSE | BD12: Parfait MEZEME ONA | BE12: Victor PONTAIS | BF12: Ibtissam ABSSI | BG12: Victor REVUELTA | BH12: MTN-CONT-004-Contrat_EIFFAGE_maintenance_PV_BT-001 | BI12: DEV-CONT-SPV016_Contrat_DEV_EPC_DAVAI_ENR-1 | BJ12: EX-CONT-SPV016-Contrat_Suivi_OM_Gestion_Actifs_DAVAI -ENR-01 | BK12: 856 | BL12: 254.533 | BX12: Stabulation, stockage de matériel, stockage de céréales et stockage de fourrage + Laiterie | CB12: FALSE | CC12: Élément | CD12: sites/ServiceOM-AssetManagement/Lists/Exploitation Data Centrale
A13: 94563 | B13: GAILLARD | C13: DAVAI ENRSPV13 | D13: 45945 | E13: Le Ménial | F13: 43170 | G13: Venteuges | H13: BE | I13: Toiture inclinée | J13: Agriculteur | K13: S21 | L13: BTA1033678| | M13: 8534450|8532950 | N13: 2 | O13: 50079383380103|50072147490146 | P13: 386 | Q13: 370 | R13: 330 | S13: 1148.5 | T13: 443321 | U13: 0.054 | V13: 0.8818 | W13: 1165.76 | X13: BT | Y13: 44767 | Z13: 0.1312 | AA13: FALSE | AB13: FALSE | AC13: EDF OA | AD13: ENEDIS | AE13: 1696 | AF13: 44.97237 | AG13: 3.50346 | AH13: N°3 - Kyoto (SPV 10,13 &14) | AI13: RAS | AJ13: EIFFAGE | AK13: Franck GAILLARD | AL13: franckgaillard43@orange.fr | AN13: +33608672385 | AO13: +33608672384 | AP13: PROSUNFRANCE | AQ13: PROSUNFRANCE | AR13: FALSE | AV13: FALSE | AZ13: FALSE | BD13: Parfait MEZEME ONA | BE13: Johan LAGARDE | BF13: Stéphane Vialettes | BG13: Alexandre COL | BH13: MTN-CONT-004-Contrat_EIFFAGE_maintenance_PV_BT-001 | BI13: DEV-CONT-SPV013-Contrat_DEV_EPC_DAVAI_ENR-1 | BJ13: EX-CONT-SPV013-Contrat_Suivi_OM_Gestion_Actifs_DAVAI -ENR-01 | BK13: 856 | BL13: 213.062 | BX13: Stabulation | CB13: FALSE | CC13: Élément | CD13: sites/ServiceOM-AssetManagement/Lists/Exploitation Data Centrale
A14: 99435 | B14: ROQUEFORT | C14: DAVAI ENRSPV14 | D14: 45943 | E14: Le Coustalou | F14: 12300 | G14: Livinhac-le-Haut | H14: BE | I14: Toiture inclinée | J14: Agriculteur | K14: S21 | L14: BTA1112191 | M14: 9610550 | N14: 1 | O14: 50030177229112 | P14: 345 | Q14: 249 | R14: 249 | S14: 1182 | T14: 407790 | U14: 0.054 | V14: 0.875 | W14: 1191.5 | X14: BT | Y14: 45163 | Z14: 0.1238 | AA14: FALSE | AB14: FALSE | AC14: EDF OA | AD14: ENEDIS | AE14: 1517 | AF14: 44.59297 | AG14: 2.22688 | AH14: N°3 - Kyoto (SPV 10,13 &14) | AI14: RAS | AJ14: EIFFAGE | AK14: Cédric ROQUEFORT | AL14: cedric.roquefort@orange.fr | AN14: 06 72 89 77 57 | AP14: YAMA ENERGIES | AQ14: BIOTECK | AR14: TRUE | AS14: 46022 | AT14: 46022 | AU14: Fixe Indexé | AV14: FALSE | AX14: 4312.5 | AY14: Annuelle | AZ14: TRUE | BA14: fixe | BD14: Parfait MEZEME ONA | BE14: Victor PONTAIS | BF14: Martin DE GUERRE | BG14: Nicolas CADENE | BH14: MTN-CONT-004-Contrat_EIFFAGE_maintenance_PV_BT-001 | BI14: DEV-CONT-SPV014_Contrat_DEV_EPC_DAVAI_ENR-1 (signed) (1) | BJ14: EX-CONT-SPV014-Contrat_Suivi_OM_Gestion_Actifs_DAVAI -ENR-01 (1) | BK14: 856 | BL14: 198.015 | BX14: Stabulation et stockage | CB14: TRUE | CC14: Élément | CD14: sites/ServiceOM-AssetManagement/Lists/Exploitation Data Centrale
A15: 83798 | B15: MORELLO | C15: DAVAI ENRSPV12 | D15: 45938 | E15: Mas Thibert | F15: 13104 | G15: Arles | H15: BaC;#BE | I15: Toiture inclinée | J15: Agriculteur | K15: S21 | L15: BTA0981875 | M15: 8006450 | N15: 1 | O15: 50019619044477 | P15: 339.47 | Q15: 330 | R15: 249.9 | S15: 1335 | T15: 453192.45 | U15: 0.053 | V15: 0.844 | W15: 1321.4 | X15: BT | Y15: 44762 | Z15: 0.1287 | AA15: FALSE | AB15: FALSE | AC15: EDF OA | AD15: ENEDIS | AE15: 1597.348 | AF15: 43.64061 | AG15: 4.55457 | AH15: N°2 - Finergreen - Construction 2023 | AI15: 2 Bâtiments BAC + BE | AJ15: EIFFAGE | AK15: Anna MORELLO | AL15: anna.marello@hotmail.fr | AN15: +33621844296 | AO15: +393339690030 | AP15: HBBAT | AQ15: HBBAT | AR15: FALSE | AV15: FALSE | AZ15: FALSE | BD15: Yasser BADREZZAMANE | BE15: Jean-Paul THOROGOOD | BF15: Charbel BOUZERDAN | BG15: Hilal KAAOUANA | BH15: MTN-CONT-004-Contrat_EIFFAGE_maintenance_PV_BT-001 | BI15: DEV-CONT-SPV012-Contrat_DEV_EPC_DAVAI_ENR-1 | BJ15: EX-CONT-SPV012-Contrat_Suivi_O&M_Gestion_Actifs_DAVAI_ENR-1 | BK15: 856 | BL15: 189.68549 | BX15: stockage de matériel/foin et fourrage | CB15: FALSE | CC15: Élément | CD15: sites/ServiceOM-AssetManagement/Lists/Exploitation Data Centrale
A16: 94565 | B16: GAUDON | C16: DAVAI ENRSPV10 | D16: 45937 | E16: La Garenne | F16: 03500 | G16: Meillard | H16: BaC | I16: Toiture inclinée | J16: Agriculteur | K16: S21 | L16: BTA0957900 | BTA | M16: 8683600 | 9010700 | N16: 2 | O16: 50074030875808 | 50088502655851 | P16: 499.59 | Q16: 440 | R16: 440 | S16: 1222.432 | T16: 610714.8 | U16: 0.054 | V16: 0.8721 | W16: 964.48 | X16: BT | Y16: 44853 | Z16: 0.1312 | AA16: FALSE | AB16: FALSE | AC16: EDF OA | AD16: ENEDIS | AE16: 2193.923 | AF16: 46.37657 | AG16: 3.25555 | AH16: N°3 - Kyoto (SPV 10,13 &14) | AI16: Mot de passe onduleur : Exploitation2023 | AJ16: EIFFAGE | AK16: DAMIEN GAUDON | AL16: gaudon.damien@gmail.com | AN16: +33625052624 | AP16: PROSUNFRANCE | AQ16: CANCE | AR16: FALSE | AV16: FALSE | AZ16: FALSE | BD16: Yasser BADREZZAMANE | BE16: Johan LAGARDE | BF16: Charbel BOUZERDAN | BG16: Sébastien GUYOUX | BH16: MTN-CONT-004-Contrat_EIFFAGE_maintenance_PV_BT-001 | BI16: DEV-CONT-SPV010-Contrat_DEV_EPC_DAVAI_ENR-1 | BJ16: EX-CONT-SPV010-Contrat_Suivi_O&M_Gestion_Actifs_DAVAI_ENR-1 | BK16: 856 | BL16: 254.74953 | BX16: stockage de matériel/stabulation/foin et fourrage | CB16: FALSE | CC16: Élément | CD16: sites/ServiceOM-AssetManagement/Lists/Exploitation Data Centrale
A17: 97678 | B17: CORREDERA | C17: DAVAI ENRSPV10 | D17: 45936 | E17: 89 Route Serre d'Odun | F17: 31420 | G17: Cassagnabère-Tournas | H17: BE | I17: Toiture inclinée | J17: Agriculteur | K17: S21 | L17: BTA1021666 | M17: 9403500 | N17: 1 | O17: 50090238172678 | P17: 209 | Q17: 175 | R17: 175 | S17: 1187.63 | T17: 248214.67 | U17: 0.054 | V17: 0.8755 | W17: 1187.63 | X17: BT | Y17: 45007 | Z17: 0.1312 | AA17: FALSE | AB17: FALSE | AC17: EDF OA | AD17: ENEDIS | AE17: 919 | AF17: 43.21504 | AG17: 0.77149 | AH17: N°3 - Kyoto (SPV 10,13 &14) | AI17: RAS | AJ17: EIFFAGE | AK17: Richard CORREDERA | AL17: richard.corredera@rc-trans.com | AN17: 0622657255 | AP17: KEVEL | AQ17: SO | AR17: FALSE | AV17: FALSE | AZ17: FALSE | BD17: Parfait MEZEME ONA | BE17: Johan LAGARDE | BF17: Gwendal HART | BG17: Nicolas CADENE | BH17: MTN-CONT-004-Contrat_EIFFAGE_maintenance_PV_BT-001 | BI17: DEV-CONT-SPV010-Contrat_DEV_EPC_DAVAI_ENR-1 | BJ17: EX-CONT-SPV010-Contrat_Suivi_O&M_Gestion_Actifs_DAVAI_ENR-1 | BK17: 856 | BL17: 148.103 | BX17: Stockage matériel agricole | CB17: FALSE | CC17: Élément | CD17: sites/ServiceOM-AssetManagement/Lists/Exploitation Data Centrale
A18: 3365 | B18: CHARTRAIN | C18: GIRASPV15 | D18: 45932 | E18: La Touche | F18: 72330 | G18: Oizé | H18: BaC | I18: Toiture inclinée | J18: Agriculteur | K18: S21 | L18: BTA1200960 | M18: 9657300 | N18: 1 | O18: 50005284403392 | P18: 320.32 | Q18: 250 | R18: 247 | S18: 1198 | T18: 383743.36 | U18: 0.054 | V18: 0.876 | W18: 1190.1 | X18: BT | Y18: 45313 | Z18: 0.1209 | AA18: FALSE | AB18: FALSE | AC18: EDF OA | AD18: ENEDIS | AE18: 1406.668 | AF18: 47.80672 | AG18: 0.1157 | AH18: N°3 - Fuji (SPV 11&15) | AI18: RAS | AJ18: EIFFAGE | AK18: Florian CHARTRAIN | AL18: lapetiteboulas@orange.fr | AN18: +33658126588 | AP18: INNOVA | AQ18: BARBOT | AR18: FALSE | AV18: FALSE | AZ18: FALSE | BD18: Yasser BADREZZAMANE | BE18: Jean-Paul THOROGOOD | BF18: Ibtissam ABSSI | BG18: Loïc GUILLEUX | BH18: MTN-CONT-004-Contrat_EIFFAGE_maintenance_PV_BT-001 | BI18: DEV-CONT-SPV015_Contrat_DEV_EPC_DAVAI_ENR-1 (signed) (1) | BJ18: EX-CONT-SPV015-Contrat_Suivi_OM_Gestion_Actifs_DAVAI -ENR-01 | BK18: 856 | BL18: 188.95744 | BX18: Stockage matériel, fourrage et paille | CB18: FALSE | CC18: Élément | CD18: sites/ServiceOM-AssetManagement/Lists/Exploitation Data Centrale
A19: 94568 | B19: BOUILLET | C19: DAVAI ENRSPV13 | D19: 45932 | E19: Les Quatre Vents | F19: 03470 | G19: Saligny-sur-Roudon | H19: BaC | I19: Toiture inclinée | J19: Agriculteur | K19: S21 | L19: BTA0962241 | BTA0961960 | M19: 9086750 | 9250450 | N19: 2 | O19: 50001672415830 | 50087200635771 | P19: 499.59 | Q19: 440 | R19: 440 | S19: 1200.6593 | T19: 599837.38 | U19: 0.054 | V19: 0.874 | W19: 1210.83 | X19: BT | Y19: 44869 | Z19: 0.1311 | AA19: FALSE | AB19: FALSE | AC19: EDF OA | AD19: ENEDIS | AE19: 2193.92 | AF19: 46.47175 | AG19: 3.77821 | AH19: N°3 - Kyoto (SPV 10,13 &14) | AI19: Mot de passe onduleur : Exploitation2023 | AJ19: EIFFAGE | AK19: FABRICE BOUILLET | AL19: fabrice.bouillet70@gmail.com | AN19: +33676318305 | AP19: PROSUNFRANCE | AQ19: CANCE | AR19: FALSE | AV19: FALSE | AZ19: FALSE | BD19: Yasser BADREZZAMANE | BE19: Johan LAGARDE | BF19: Charbel BOUZERDAN | BG19: Sébastien GUYOUX | BH19: MTN-CONT-004-Contrat_EIFFAGE_maintenance_PV_BT-001 | BI19: DEV-CONT-SPV013-Contrat_DEV_EPC_DAVAI_ENR-1 | BJ19: EX-CONT-SPV013-Contrat_Suivi_OM_Gestion_Actifs_DAVAI -ENR-01 | BK19: 856 | BL19: 254.74953 | BX19: stockage de matériel/stabulation/foin et fourrage | CB19: FALSE | CC19: Élément | CD19: sites/ServiceOM-AssetManagement/Lists/Exploitation Data Centrale
A20: 93459 | B20: GUENIOT | C20: GIRASPV15 | D20: 45931 | E20: ZA Volzac | F20: 15100 | G20: Saint-Flour | H20: BaC | I20: Toiture inclinée | J20: Tertiaire | K20: S21 | L20: BTA1189363 | M20: 9841150 | N20: 1 | O20: 50002534214233 | P20: 284.375 | Q20: 250 | R20: 239 | S20: 1281 | T20: 364284.38 | U20: 0.054 | V20: 0.879 | W20: 1305.3 | X20: BT | Y20: 45300 | Z20: 0.1208 | AA20: FALSE | AB20: FALSE | AC20: EDF OA | AD20: ENEDIS | AE20: 1248.818 | AF20: 45.02889 | AG20: 3.06218 | AH20: N°3 - Fuji (SPV 11&15) | AI20: RAS | AJ20: EIFFAGE | AK20: Patrice GUENIOT | AL20: p.gueniot@gmail.com | AN20: +33682515030 | AO20: +33630237363 | AP20: 3C INSTAL | AQ20: MOMSTEEL | AR20: FALSE | AV20: FALSE | AZ20: FALSE | BD20: Yasser BADREZZAMANE | BE20: Jean-Paul THOROGOOD | BF20: Martin DE GUERRE | BG20: Alexandre COL | BH20: Contrat OM PV toiture - ENERLIS - V10 18.11.2020 exécuté | BI20: DEV-CONT-SPV015_Contrat_DEV_EPC_DAVAI_ENR-1 (signed) (1) | BJ20: EX-CONT-SPV015-Contrat_Suivi_OM_Gestion_Actifs_DAVAI -ENR-01 | BK20: 856 | BL20: 175.76562 | BX20: Siège de l’entreprise, stockage de matériaux de TP, de matériaux et de véhicules | CB20: FALSE | CC20: Élément | CD20: sites/ServiceOM-AssetManagement/Lists/Exploitation Data Centrale
A21: 98047 | B21: TURROU | C21: DAVAI ENRSPV13 | D21: 45931 | E21: Les Campespieux | F21: 65380 | G21: Bénac | H21: BaC | I21: Toiture inclinée | J21: Agriculteur | K21: S21 | L21: BTA1202102 | BTA1202304 | M21: 9647750 | 9648250 | N21: 2 | O21: 50058684362448 | 50009769744265 | P21: 494.4 | Q21: 440 | R21: 416 | S21: 1172 | T21: 579436.8 | U21: 0.054 | V21: 0.87389713 | W21: 1152.1331 | X21: BT | Y21: 45314 | Z21: 0.1208 | AA21: FALSE | AB21: FALSE | AC21: EDF OA | AD21: ENEDIS | AE21: 2157.956 | AF21: 43.15845 | AG21: 0.02822 | AH21: N°3 - Kyoto (SPV 10,13 &14) | AI21: Mot de passe onduleur : Exploitation2023 | AJ21: EIFFAGE | AK21: Lorraine TURROU | AL21: etrierdebigorre@outlook.fr | AN21: +33485880404 | AO21: +33665671903 | AP21: ACROM | AQ21: HBBAT | AR21: FALSE | AV21: FALSE | AZ21: FALSE | BD21: Yasser BADREZZAMANE | BE21: Johan LAGARDE | BF21: Gwendal HART | BG21: Victor REVUELTA | BH21: MTN-CONT-004-Contrat_EIFFAGE_maintenance_PV_BT-001 | BI21: DEV-CONT-SPV013-Contrat_DEV_EPC_DAVAI_ENR-1 | BJ21: EX-CONT-SPV013-Contrat_Suivi_OM_Gestion_Actifs_DAVAI -ENR-01 | BK21: 856 | BL21: 252.8448 | BX21: Manège équestre, Stockage matériel + fourrage | CB21: FALSE | CC21: Élément | CD21: sites/ServiceOM-AssetManagement/Lists/Exploitation Data Centrale
A22: 99135 | B22: DELLA LIBERA CARBONNIERES | C22: DAVAI ENRSPV14 | D22: 45924 | E22: Carbonnières | F22: 47800 | G22: Lavergne | H22: BE | I22: Toiture plate | J22: Agriculteur | K22: S21 | L22: BTA1136662 | M22: 9550800 | N22: 1 | O22: 50001522816933 | P22: 296.205 | Q22: 250 | R22: 239 | S22: 1257 | T22: 372329.68 | U22: 0.054 | V22: 0.868 | W22: 1247.4 | X22: BT | Y22: 45209 | Z22: 0.1238 | AA22: FALSE | AB22: FALSE | AC22: EDF OA | AD22: ENEDIS | AE22: 1300.768 | AF22: 44.58495 | AG22: 0.41326 | AH22: N°3 - Kyoto (SPV 10,13 &14) | AI22: Mot de passe onduleur : Exploitation2023 | AJ22: EIFFAGE | AK22: Mickael DELLA LIBERA | AL22: della-libera.mickael@orange.fr | AN22: +33679213316 | AP22: HBBAT | AQ22: HBBAT | AR22: FALSE | AV22: FALSE | AZ22: FALSE | BD22: Yasser BADREZZAMANE | BE22: Victor PONTAIS | BF22: Gwendal HART | BG22: Victor REVUELTA | BH22: MTN-CONT-004-Contrat_EIFFAGE_maintenance_PV_BT-001 | BI22: DEV-CONT-SPV014_Contrat_DEV_EPC_DAVAI_ENR-1 (signed) (1) | BJ22: EX-CONT-SPV014-Contrat_Suivi_OM_Gestion_Actifs_DAVAI -ENR-01 (1) | BK22: 856 | BL22: 180.10724 | BX22: Stockage matériel, fourrage et stabulation | CB22: FALSE | CC22: Élément | CD22: sites/ServiceOM-AssetManagement/Lists/Exploitation Data Centrale
A23: 99129 | B23: DELLA LIBERA FRAYSSE | C23: DAVAI ENRSPV14 | D23: 45924 | E23: FRAYSSE | F23: 47800 | G23: Lavergne | H23: BaC | I23: Toiture inclinée | J23: Agriculteur | K23: S21 | L23: BTA1136591 | M23: 9142500 | N23: 1 | O23: 50094286926814 | P23: 318.5 | Q23: 250 | R23: 249 | S23: 1169 | T23: 372326.5 | U23: 0.054 | V23: 0.871 | W23: 1170.2 | X23: BT | Y23: 45209 | Z23: 0.1238 | AA23: FALSE | AB23: FALSE | AC23: EDF OA | AD23: ENEDIS | AE23: 1398.676 | AF23: 44.58824 | AG23: 0.41015 | AH23: N°3 - Kyoto (SPV 10,13 &14) | AI23: Mot de passe onduleur : Exploitation2023 | AJ23: EIFFAGE | AK23: Mickael DELLA LIBERA | AL23: della-libera.mickael@orange.fr | AN23: +33679213316 | AP23: HBBAT | AQ23: HBBAT | AR23: FALSE | AV23: FALSE | AZ23: FALSE | BD23: Yasser BADREZZAMANE | BE23: Victor PONTAIS | BF23: Gwendal HART | BG23: Victor REVUELTA | BH23: MTN-CONT-004-Contrat_EIFFAGE_maintenance_PV_BT-001 | BI23: DEV-CONT-SPV014_Contrat_DEV_EPC_DAVAI_ENR-1 (signed) (1) | BJ23: EX-CONT-SPV014-Contrat_Suivi_OM_Gestion_Actifs_DAVAI -ENR-01 (1) | BK23: 856 | BL23: 188.2895 | BX23: Stockage matériel et fourrage | CB23: FALSE | CC23: Élément | CD23: sites/ServiceOM-AssetManagement/Lists/Exploitation Data Centrale
A24: 87676 | B24: ROUSSEAU | C24: DAVAI ENRSPV13 | D24: 45923 | E24: Pièce du Moulin | F24: 44540 | G24: VALLONS-DE-L' ERDRE | H24: BaC | I24: Toiture inclinée | J24: Agriculteur | K24: S21 | L24: BTA1089522 | M24: 9471850 | N24: 1 | O24: 50030323043093 | P24: 324.87 | Q24: 250 | R24: 250 | S24: 1143 | T24: 371326.41 | U24: 0.054 | V24: 0.8744 | W24: 1156.06 | X24: BT | Y24: 45124 | Z24: 0.1274 | AA24: FALSE | AB24: FALSE | AC24: EDF OA | AD24: ENEDIS | AE24: 1426.64 | AF24: 47.5429 | AG24: -1.19527 | AH24: N°3 - Kyoto (SPV 10,13 &14) | AI24: RAS | AJ24: EIFFAGE | AK24: ROUSSEAU Clément | AL24: clement.rousseau44540@outlook.fr | AN24: +33666200742 | AP24: REGISOLAIR | AQ24: CANCE | AR24: FALSE | AV24: FALSE | AZ24: FALSE | BD24: Yasser BADREZZAMANE | BE24: Johan LAGARDE | BF24: Nicolas PETROPAVLOVSKY | BG24: Loïc GUILLEUX | BH24: MTN-CONT-004-Contrat_EIFFAGE_maintenance_PV_BT-001 | BI24: DEV-CONT-SPV013-Contrat_DEV_EPC_DAVAI_ENR-1 | BJ24: EX-CONT-SPV013-Contrat_Suivi_OM_Gestion_Actifs_DAVAI -ENR-01 | BK24: 856 | BL24: 190.62729 | BX24: Stockage matériel, céréales, paille, foin limité à 50% de la surface au sol du bâtiment. | CB24: FALSE | CC24: Élément | CD24: sites/ServiceOM-AssetManagement/Lists/Exploitation Data Centrale
A25: 3280 | B25: SCI LE CORMIER | C25: DAVAI ENRSPV10 | D25: 45918 | E25: Rue Charles Messier | F25: 49300 | G25: Cholet | H25: BE | I25: Toiture plate | J25: Industrie | K25: S21 | L25: BTA1202118 | M25: 9855150 | N25: 1 | O25: 50005429137222 | P25: 249.795 | Q25: 220 | R25: 203 | S25: 1090 | T25: 272276.55 | U25: 0.054 | V25: 0.87297127 | W25: 1092.0871 | X25: BT | Y25: 45315 | Z25: 0.1209 | AA25: FALSE | AB25: FALSE | AC25: EDF OA | AD25: ENEDIS | AE25: 1096.961 | AF25: 47.0359 | AG25: -0.91024 | AH25: N°3 - Kyoto (SPV 10,13 &14) | AI25: Mot de passe onduleur : Exploitation2023 L'accès au bâtiment peut se faire sans passage de portail et via une échelle à crinoline | AJ25: EIFFAGE | AK25: Julien HUMEAU | AL25: jhumeau@oxygen-sarl.fr | AN25: +33622481509 | AP25: INNOVA | AQ25: MASSE Charpentier | AR25: FALSE | AS25: 45932 | AT25: 45932 | AU25: En une fois | AV25: TRUE | AX25: 90000 | AZ25: FALSE | BD25: Yasser BADREZZAMANE | BE25: Johan LAGARDE | BF25: Nicolas PETROPAVLOVSKY | BG25: Loïc GUILLEUX | BH25: MTN-CONT-004-Contrat_EIFFAGE_maintenance_PV_BT-001 | BI25: DEV-CONT-SPV010-Contrat_DEV_EPC_DAVAI_ENR-1 | BJ25: EX-CONT-SPV010-Contrat_Suivi_O&M_Gestion_Actifs_DAVAI_ENR-1 | BK25: 856 | BL25: 163.07477 | BX25: Artisanat | CB25: FALSE | CC25: Élément | CD25: sites/ServiceOM-AssetManagement/Lists/Exploitation Data Centrale
A26: 89054 | B26: CANTALOUBE | C26: GIRASPV15 | D26: 45917 | E26: La Soudairie | F26: 44850 | G26: Ligné | H26: BaC | I26: Toiture inclinée | J26: Agriculteur | K26: S21 | L26: BTA1196117 | BTA1196086 | M26: 9209500 | 9212050 | N26: 2 | O26: 50068960419348 | 50065631909632 | P26: 499.59 | Q26: 440 | R26: 406 | S26: 1060.64 | T26: 529885.14 | U26: 0.054 | V26: 0.88 | W26: 1076.1 | X26: BT | Y26: 45309 | Z26: 0.1209 | AA26: FALSE | AB26: FALSE | AC26: EDF OA | AD26: ENEDIS | AE26: 2193.923 | AF26: 47.41259 | AG26: -1.41108 | AH26: N°3 - Fuji (SPV 11&15) | AI26: Mot de passe onduleur: Exploitation2023 | AJ26: EIFFAGE | AK26: Mathieu CANTALOUBE | AL26: mathcanta@orange.fr | AN26: +33660119398 | AO26: +33164346262 | AP26: INNOVA | AQ26: GIRAUD | AR26: FALSE | AV26: FALSE | AZ26: FALSE | BD26: Yasser BADREZZAMANE | BE26: Jean-Paul THOROGOOD | BF26: Nicolas PETROPAVLOVSKY | BG26: Loïc GUILLEUX | BH26: MTN-CONT-004-Contrat_EIFFAGE_maintenance_PV_BT-001 | BI26: DEV-CONT-SPV015_Contrat_DEV_EPC_DAVAI_ENR-1 (signed) (1) | BJ26: EX-CONT-SPV015-Contrat_Suivi_OM_Gestion_Actifs_DAVAI -ENR-01 | BK26: 856 | BL26: 254.74953 | BX26: Stockage matériel, stockage paille, foin et fourrage dans la limite de 50% | CB26: FALSE | CC26: Élément | CD26: sites/ServiceOM-AssetManagement/Lists/Exploitation Data Centrale
A27: 96571 | B27: GAEC DE PASSAY | C27: DAVAI ENRSPV11 | D27: 45916 | E27: Le Passay | F27: 72460 | G27: Sillé-le-Philippe | H27: BaC | I27: Toiture inclinée | J27: Agriculteur | K27: S21 | L27: BTA1042636 | M27: 9718400 | N27: 1 | O27: 50019904987275 | P27: 257.985 | Q27: 220 | R27: 204 | S27: 1189 | T27: 306744.16 | U27: 0.054 | V27: 0.87134863 | W27: 1167.6072 | X27: BT | Y27: 45040 | Z27: 0.1313 | AA27: FALSE | AB27: FALSE | AC27: EDF OA | AD27: ENEDIS | AE27: 1132.927 | AF27: 48.10556 | AG27: 0.36343 | AH27: N°3 - Fuji (SPV 11&15) | AI27: Mot de passe onduleur : Exploitation2023 | AJ27: EIFFAGE | AK27: DAVID BOURDIN | AL27: gaecdepassay@orange.fr | AN27: +33620044552 | AP27: INNOVA | AQ27: CANCE | AR27: FALSE | AV27: FALSE | AZ27: FALSE | BD27: Yasser BADREZZAMANE | BE27: Jean-Paul THOROGOOD | BF27: Nicolas PETROPAVLOVSKY | BG27: Loïc GUILLEUX | BH27: MTN-CONT-004-Contrat_EIFFAGE_maintenance_PV_BT-001 | BI27: DEV-CONT-SPV011-Contrat_DEV_EPC_DAVAI_ENR-1 | BJ27: EX-CONT-SPV011-Contrat_Suivi_O&M_Gestion_Actifs_DAVAI_ENR-1 | BK27: 856 | BL27: 166.0805 | BX27: Stockage de matériel, céréales à plat pour l’élevage des porcs et fourrages (paille et foin). | CB27: FALSE | CC27: Élément | CD27: sites/ServiceOM-AssetManagement/Lists/Exploitation Data Centrale
A28: 3468 | B28: DALGRANDE | C28: DAVAI ENRSPV14 | D28: 45911 | E28: 190 Impasse des Peyrouliers | F28: 31620 | G28: Fronton | H28: BaC | I28: Toiture inclinée | J28: Agriculteur | K28: S21 | L28: BTA1208134 | M28: 9526350 | N28: 1 | O28: 50017875447671 | P28: 277.095 | Q28: 224 | R28: 224 | S28: 1247 | T28: 345537.47 | U28: 0.054 | V28: 0.87 | W28: 1220.6 | X28: BT | Y28: 45322 | Z28: 0.1208 | AA28: FALSE | AB28: FALSE | AC28: EDF OA | AD28: ENEDIS | AE28: 1216.848 | AF28: 43.88434 | AG28: 1.37123 | AH28: N°3 - Kyoto (SPV 10,13 &14) | AI28: Communication KO (Onduleurs KACO) | AJ28: EIFFAGE | AK28: Julien DALGRANDE | AL28: julien.dalgrande@live.fr | AN28: +33676197227 | AP28: YAMA ENERGIES | AQ28: GIRAUD | AR28: FALSE | AV28: FALSE | AZ28: FALSE | BD28: Parfait MEZEME ONA | BE28: Victor PONTAIS | BF28: Gwendal HART | BG28: Nicolas CADENE | BH28: MTN-CONT-004-Contrat_EIFFAGE_maintenance_PV_BT-001 | BI28: DEV-CONT-SPV014_Contrat_DEV_EPC_DAVAI_ENR-1 (signed) (1) | BJ28: EX-CONT-SPV014-Contrat_Suivi_OM_Gestion_Actifs_DAVAI -ENR-01 (1) | BK28: 856 | BL28: 173.09386 | BX28: Stockage de fourrage et de matériel | CB28: FALSE | CC28: Élément | CD28: sites/ServiceOM-AssetManagement/Lists/Exploitation Data Centrale
A29: 97461 | B29: MAGNON | C29: DAVAI ENRSPV11 | D29: 45909 | E29: 6 Jupille | F29: 23000 | G29: Anzême | H29: BE | I29: Toiture inclinée | J29: Agriculteur | K29: S21 | L29: BTA1017643 | M29: 9119550 | N29: 1 | O29: 50041322984460 | P29: 326.235 | Q29: 265 | R29: 249.9 | S29: 1098 | T29: 358206.03 | U29: 0.054 | V29: 0.87773865 | W29: 1092.9413 | X29: BT | Y29: 45001 | Z29: 0.1287 | AA29: FALSE | AB29: FALSE | AC29: EDF OA | AD29: ENEDIS | AE29: 1432.643 | AF29: 46.27757 | AG29: 1.84941 | AH29: N°3 - Fuji (SPV 11&15) | AI29: Mot de passe onduleur : Exploitation2023 2 Bâtiments | AJ29: EIFFAGE | AK29: Pierre MAGNON | AL29: olivier.magnon@free.fr | AN29: +33684395516 | AO29: +33326592203 | AP29: NEOXOM | AQ29: ACC | AR29: FALSE | AV29: FALSE | AZ29: FALSE | BD29: Yasser BADREZZAMANE | BE29: Jean-Paul THOROGOOD | BF29: Gwendal HART | BG29: Alexandre COL | BH29: MTN-CONT-004-Contrat_EIFFAGE_maintenance_PV_BT-001 | BI29: DEV-CONT-SPV011-Contrat_DEV_EPC_DAVAI_ENR-1 | BJ29: EX-CONT-SPV011-Contrat_Suivi_O&M_Gestion_Actifs_DAVAI_ENR-1 | BK29: 856 | BL29: 191.12824 | BX29: Stabulation (100%) | CB29: FALSE | CC29: Élément | CD29: sites/ServiceOM-AssetManagement/Lists/Exploitation Data Centrale
A30: 90284 | B30: SAVARD | C30: DAVAI ENRSPV11 | D30: 45905 | E30: Avènes | F30: 48150 | G30: Meyrueis | H30: BaC | I30: Toiture inclinée | J30: Agriculteur | K30: S21 | L30: BTA1095627 | M30: 9446500 | N30: 1 | O30: 50098774377768 | P30: 124.215 | Q30: 110 | R30: 110 | S30: 1280 | T30: 158995.2 | U30: 0.054 | V30: 0.7874 | W30: 1259.11 | X30: BT | Y30: 45120 | Z30: 0.1274 | AA30: FALSE | AB30: FALSE | AC30: EDF OA | AD30: ENEDIS | AE30: 545.483 | AF30: 44.18066 | AG30: 3.45765 | AH30: N°3 - Fuji (SPV 11&15) | AI30: Ombrage lors de la MES | AJ30: EIFFAGE | AK30: Christian SAVARD | AL30: chrs.savard@gmail.com | AN30: +33665161349 | AP30: 3C INSTAL | AQ30: MOMSTEEL | AR30: FALSE | AV30: FALSE | AZ30: FALSE | BD30: Parfait MEZEME ONA | BE30: Jean-Paul THOROGOOD | BF30: Martin DE GUERRE | BG30: Gabriel AYMA | BH30: MTN-CONT-004-Contrat_EIFFAGE_maintenance_PV_BT-001 | BI30: DEV-CONT-SPV011-Contrat_DEV_EPC_DAVAI_ENR-1 | BJ30: EX-CONT-SPV011-Contrat_Suivi_O&M_Gestion_Actifs_DAVAI_ENR-1 | BK30: 856 | BL30: 116.9869 | BX30: Manège et stockage | CB30: FALSE | CC30: Élément | CD30: sites/ServiceOM-AssetManagement/Lists/Exploitation Data Centrale
A31: 96677 | B31: EARL LES ECURIES D'AIROLLE - VALLAT | C31: DAVAI ENRSPV14 | D31: 45901 | E31: 2095 Rte des Faures | F31: 26300 | G31: Alixan | H31: BaC | I31: Toiture inclinée | J31: Agriculteur | K31: S21 | L31: BTA1176895 | M31: 9609700 | N31: 1 | O31: 50072434357920 | P31: 318.5 | Q31: 250 | R31: 249 | S31: 1227 | T31: 390799.5 | U31: 0.054 | V31: 0.869 | W31: 1230.9 | X31: BT | Y31: 45282 | Z31: 0.1209 | AA31: FALSE | AB31: FALSE | AC31: EDF OA | AD31: ENEDIS | AE31: 1398.676 | AF31: 44.98934 | AG31: 5.05305 | AH31: N°3 - Kyoto (SPV 10,13 &14) | AI31: Mot de passe onduleur : Exploitation2023 | AJ31: EIFFAGE | AK31: Frédéric VALLAT | AL31: frederic-vallat@sfr.fr | AN31: +33625819455 | AO31: +33475367462 | AP31: ADS | AQ31: GIRAUD | AR31: FALSE | AV31: FALSE | AZ31: FALSE | BD31: Yasser BADREZZAMANE | BE31: Victor PONTAIS | BF31: Sophie ROGIER | BG31: Hilal KAAOUANA | BH31: MTN-CONT-004-Contrat_EIFFAGE_maintenance_PV_BT-001 | BI31: DEV-CONT-SPV014_Contrat_DEV_EPC_DAVAI_ENR-1 (signed) (1) | BJ31: EX-CONT-SPV014-Contrat_Suivi_OM_Gestion_Actifs_DAVAI -ENR-01 (1) | BK31: 856 | BL31: 188.2895 | BX31: Carrière couverte + stockage matériel et fourrage | CB31: FALSE | CC31: Élément | CD31: sites/ServiceOM-AssetManagement/Lists/Exploitation Data Centrale
A32: 58967 | B32: OLIVARES - ECURIE DAME DE COEUR | C32: GIRASPV17 | D32: 45898 | E32: LA MATHE NORD | F32: 11700 | G32: Pépieux | H32: BaC | I32: Toiture inclinée | J32: Agriculteur | K32: S21 | L32: BTA1313148 | M32: 9627400 | N32: 1 | O32: 50072721245761 | P32: 318.5 | Q32: 250 | R32: 249 | S32: 1275 | T32: 406087.5 | U32: 0.054 | V32: 0.8701 | W32: 1281 | X32: BT | Y32: 45492 | Z32: 0.1118 | AA32: FALSE | AB32: FALSE | AC32: EDF OA | AD32: ENEDIS | AE32: 1398.676 | AF32: 43.29196 | AG32: 2.67764 | AH32: N°4 | AI32: Mot de passe onduleur : Exploitation2023 | AJ32: EIFFAGE | AK32: Anais OLIVARES | AL32: anais_o@msn.com | AN32: +33626323768 | AP32: KEVEL | AQ32: GIRAUD | AR32: FALSE | AV32: FALSE | AZ32: FALSE | BD32: Yasser BADREZZAMANE | BE32: Johan LAGARDE | BF32: Maxime DENIAU | BG32: Gabriel AYMA | BH32: MTN-CONT-004-Contrat_EIFFAGE_maintenance_PV_BT-001 | BI32: DEV-CONT-SPV017_Contrat_DEV_EPC_DAVAI_ENR-1 | BJ32: EX-CONT-SPV017-Contrat_Suivi_OM_Gestion_Actifs_DAVAI -ENR-01 | BK32: 856 | BL32: 188.2895 | BX32: Manège équestre | CB32: FALSE | CC32: Élément | CD32: sites/ServiceOM-AssetManagement/Lists/Exploitation Data Centrale
A33: 3085 | B33: BAYLE | C33: GIRASPV15 | D33: 45898 | E33: Le Château Lagoual | F33: 11400 | G33: Lasbordes | H33: BaC | I33: Toiture inclinée | J33: Agriculteur | K33: S21 | L33: BTA1189250 | M33: 9637900 | N33: 1 | O33: 50098048833238 | P33: 324.87 | Q33: 250 | R33: 249 | S33: 1299 | T33: 422006.13 | U33: 0.054 | V33: 0.862 | W33: 1302.4 | X33: BT | Y33: 45300 | Z33: 0.1208 | AA33: FALSE | AB33: FALSE | AC33: EDF OA | AD33: ENEDIS | AE33: 1426.649 | AF33: 43.30401 | AG33: 2.07536 | AH33: N°3 - Fuji (SPV 11&15) | AI33: Mot de passe onduleur : Exploitation2023 | AJ33: EIFFAGE | AK33: Maxime BAYLE | AL33: baylemaxime2305@gmail.com | AN33: +33622514060 | AP33: YAMA ENERGIES | AQ33: GIRAUD | AR33: FALSE | AV33: FALSE | AZ33: FALSE | BD33: Yasser BADREZZAMANE | BE33: Jean-Paul THOROGOOD | BF33: Maxime DENIAU | BG33: Gabriel AYMA | BH33: MTN-CONT-004-Contrat_EIFFAGE_maintenance_PV_BT-001 | BI33: DEV-CONT-SPV015_Contrat_DEV_EPC_DAVAI_ENR-1 (signed) (1) | BJ33: EX-CONT-SPV015-Contrat_Suivi_OM_Gestion_Actifs_DAVAI -ENR-01 | BK33: 856 | BL33: 190.62729 | BX33: Stockage matériel (50%), Stockage céréales (50%) | CB33: FALSE | CC33: Élément | CD33: sites/ServiceOM-AssetManagement/Lists/Exploitation Data Centrale
A34: 97565 | B34: POMAS | C34: DAVAI ENRSPV14 | D34: 45890 | E34: Pech Laroque | F34: 11250 | G34: Pomas | H34: BaC | I34: Toiture inclinée | J34: Collectivités | K34: S21 | L34: BTA1202985 | M34: 9246350 | N34: 1 | O34: 50042042293948 | P34: 254.8 | Q34: 208 | R34: 208 | S34: 1242 | T34: 316461.6 | U34: 0.054 | V34: 0.868 | W34: 1220.1 | X34: BT | Y34: 45320 | Z34: 0.1208 | AA34: FALSE | AB34: FALSE | AC34: EDF OA | AD34: ENEDIS | AE34: 1118.94 | AF34: 43.11473 | AG34: 2.2963 | AH34: N°3 - Kyoto (SPV 10,13 &14) | AI34: RAS | AJ34: EIFFAGE | AK34: Commune de Pomas | AL34: mairiepomas@mairie-pomas.fr | AN34: +33 4 68 69 42 67 | AO34: 06 85 54 20 16 | AP34: KEVEL | AQ34: GIRAUD | AR34: FALSE | AV34: FALSE | AZ34: FALSE | BD34: Parfait MEZEME ONA | BE34: Victor PONTAIS | BF34: Maxime DENIAU | BG34: Gabriel AYMA | BH34: MTN-CONT-004-Contrat_EIFFAGE_maintenance_PV_BT-001 | BI34: DEV-CONT-SPV014_Contrat_DEV_EPC_DAVAI_ENR-1 (signed) (1) | BJ34: EX-CONT-SPV014-Contrat_Suivi_OM_Gestion_Actifs_DAVAI -ENR-01 (1) | BK34: 856 | BL34: 164.9116 | BX34: Boulodrome + dépôt communal + Box à la location | CB34: FALSE | CC34: Élément | CD34: sites/ServiceOM-AssetManagement/Lists/Exploitation Data Centrale
A35: 95592 | B35: MICOULEAU | C35: DAVAI ENRSPV14 | D35: 45888 | E35: Lascombes | F35: 11170 | G35: Alzonne | H35: BaC | I35: Toiture inclinée | J35: Agriculteur | K35: S21 | L35: BTA1098789 | M35: 9108300 | N35: 1 | O35: 50072869634698 | P35: 277.095 | Q35: 220 | R35: 220 | S35: 1325 | T35: 367150.88 | U35: 0.054 | V35: 0.866 | W35: 1329.9 | X35: BT | Y35: 45133 | Z35: 0.1274 | AA35: FALSE | AB35: FALSE | AC35: EDF OA | AD35: ENEDIS | AE35: 1216.848 | AF35: 43.26257 | AG35: 2.15214 | AH35: N°3 - Kyoto (SPV 10,13 &14) | AI35: RAS | AJ35: EIFFAGE | AK35: Norbert MICOULEAU | AL35: norbert.micouleau@wanadoo.fr | AN35: +33685485237 | AP35: YAMA ENERGIES | AQ35: MOMSTEEL | AR35: FALSE | AV35: FALSE | AZ35: FALSE | BD35: Parfait MEZEME ONA | BE35: Victor PONTAIS | BF35: Maxime DENIAU | BG35: Vincent KEZADRI | BH35: MTN-CONT-004-Contrat_EIFFAGE_maintenance_PV_BT-001 | BI35: DEV-CONT-SPV014_Contrat_DEV_EPC_DAVAI_ENR-1 (signed) (1) | BJ35: EX-CONT-SPV014-Contrat_Suivi_OM_Gestion_Actifs_DAVAI -ENR-01 (1) | BK35: 856 | BL35: 173.09386 | BX35: Stockage de matériel, de céréales | CB35: FALSE | CC35: Élément | CD35: sites/ServiceOM-AssetManagement/Lists/Exploitation Data Centrale
A36: 88182 | B36: CAVANHAC | C36: DAVAI ENRSPV10 | D36: 45881 | E36: 515 Route de Monberon | F36: 82370 | G36: Varennes | H36: BaC | I36: Toiture inclinée | J36: Agriculteur | K36: S21 | L36: BTA1101470 | M36: 8962750 | N36: 1 | O36: 50062304944999 | P36: 277.095 | Q36: 220 | R36: 220 | S36: 1233 | T36: 341658.14 | U36: 0.054 | V36: 0.8712 | W36: 1221.95 | X36: BT | Y36: 45134 | Z36: 0.1274 | AA36: FALSE | AB36: FALSE | AC36: EDF OA | AD36: ENEDIS | AE36: 1216.848 | AF36: 43.90624 | AG36: 1.48606 | AH36: N°3 - Kyoto (SPV 10,13 &14) | AI36: RAS | AJ36: EIFFAGE | AK36: Eric CAVANHAC | AL36: cavanhace@wanadoo.fr | AN36: +33635340590 | AP36: ACROM | AQ36: CANCE | AR36: FALSE | AV36: FALSE | AZ36: FALSE | BD36: Parfait MEZEME ONA | BE36: Johan LAGARDE | BF36: Gwendal HART | BG36: Charlie BLAIZEAU | BH36: MTN-CONT-004-Contrat_EIFFAGE_maintenance_PV_BT-001 | BI36: DEV-CONT-SPV010-Contrat_DEV_EPC_DAVAI_ENR-1 | BJ36: EX-CONT-SPV010-Contrat_Suivi_O&M_Gestion_Actifs_DAVAI_ENR-1 | BK36: 856 | BL36: 173.09386 | BX36: Stockage de matériel, engrais (max 50 big bag), sacs de semence, paille (maxi 750m3), petit atelier | CB36: FALSE | CC36: Élément | CD36: sites/ServiceOM-AssetManagement/Lists/Exploitation Data Centrale
A37: 3391 | B37: LABEAUVIE | C37: GIRASPV15 | D37: 45880 | E37: Gouny | F37: 47350 | G37: Escassefort | H37: BaC | I37: Toiture inclinée | J37: Agriculteur | K37: S21 | L37: BTA1202493 | M37: 9141250 | N37: 1 | O37: 50090089248752 | P37: 331.24 | Q37: 249.9 | R37: 249.9 | S37: 1126 | T37: 372976.24 | U37: 0.054 | V37: 0.844 | W37: 1135.6 | X37: BT | Y37: 45315 | Z37: 0.1208 | AA37: FALSE | AB37: FALSE | AC37: EDF OA | AD37: ENEDIS | AE37: 1454.623 | AF37: 44.56123 | AG37: 0.24227 | AH37: N°3 - Fuji (SPV 11&15) | AI37: RAS | AJ37: EIFFAGE | AK37: Laurent LABEAUVIE | AL37: elg47@orange.fr | AN37: 06 74 45 39 07 | AP37: HBBAT | AQ37: HBBAT | AR37: FALSE | AV37: FALSE | AZ37: FALSE | BD37: Parfait MEZEME ONA | BE37: Jean-Paul THOROGOOD | BF37: Gwendal HART | BG37: Charlie BLAIZEAU | BH37: MTN-CONT-004-Contrat_EIFFAGE_maintenance_PV_BT-001 | BI37: DEV-CONT-SPV015_Contrat_DEV_EPC_DAVAI_ENR-1 (signed) (1) | BJ37: EX-CONT-SPV015-Contrat_Suivi_OM_Gestion_Actifs_DAVAI -ENR-01 | BK37: 856 | BL37: 192.96508 | BX37: Stockage matériel, fourrage | CB37: FALSE | CC37: Élément | CD37: sites/ServiceOM-AssetManagement/Lists/Exploitation Data Centrale
A38: 81492 | B38: BOURGEOIS | C38: GIRASPV15 | D38: 45875 | E38: Champ de l'Annerie | F38: 44522 | G38: MESANGER | H38: BaC | I38: Toiture inclinée | J38: Agriculteur | K38: S21 | L38: BTA1139364 | M38: 9365400 | N38: 1 | O38: 50085894155690 | P38: 225.68 | Q38: 165 | R38: 165 | S38: 1136 | T38: 256372.48 | U38: 0.054 | V38: 0.875 | W38: 1163.5 | X38: BT | Y38: 45217 | Z38: 0.1246 | AB38: FALSE | AC38: EDF OA | AD38: ENEDIS | AE38: 991.062 | AF38: 47.44106 | AG38: -1.27682 | AH38: N°3 - Fuji (SPV 11&15) | AI38: RAS | AJ38: EIFFAGE | AK38: Hervé Bourgeois | AL38: herve.bourgeois413@orange.fr | AN38: 0609116376 | AO38: 0648229179 | AP38: INNOVA | AQ38: GIRAUD | AR38: FALSE | AV38: FALSE | AZ38: FALSE | BD38: Parfait MEZEME ONA | BE38: Jean-Paul THOROGOOD | BF38: Nicolas PETROPAVLOVSKY | BG38: Loïc GUILLEUX | BH38: MTN-CONT-004-Contrat_EIFFAGE_maintenance_PV_BT-001 | BI38: DEV-CONT-SPV015_Contrat_DEV_EPC_DAVAI_ENR-1 (signed) (1) | BJ38: EX-CONT-SPV015-Contrat_Suivi_OM_Gestion_Actifs_DAVAI -ENR-01 | BK38: 856 | BL38: 154.22456 | BX38: Stockage de fourrage 50% et stockage matériel 50% | CB38: FALSE | CC38: Élément | CD38: sites/ServiceOM-AssetManagement/Lists/Exploitation Data Centrale
A39: 71369 | B39: RIVIERE | C39: DAVAI ENRSPV11 | D39: 45874 | E39: Enchanet | F39: 15700 | G39: Pleaux | H39: BaC | I39: Toiture inclinée | J39: Agriculteur | K39: S21 | L39: BTA1105919 | M39: 9275350 | N39: 1 | O39: 50064619602367 | P39: 263.9 | Q39: 220 | R39: 220 | S39: 1024 | T39: 270233.6 | U39: 0.054 | V39: 0.7693 | W39: 1023.19 | X39: BT | Y39: 45154 | Z39: 0.124 | AB39: FALSE | AC39: EDF OA | AD39: ENEDIS | AE39: 1158.903 | AF39: 45.08749 | AG39: 2.20248 | AH39: N°3 - Fuji (SPV 11&15) | AI39: Mot de passe onduleur : Exploitation2023 | AJ39: EIFFAGE | AK39: Christian RIVIERE | AL39: rucherdenchanet@orange.fr | AN39: +33673400780 | AP39: 3C INSTAL | AQ39: MOMSTEEL | AR39: FALSE | AV39: FALSE | AZ39: FALSE | BD39: Yasser BADREZZAMANE | BE39: Jean-Paul THOROGOOD | BF39: Maxime DENIAU | BG39: Alexandre COL | BH39: MTN-CONT-004-Contrat_EIFFAGE_maintenance_PV_BT-001 | BI39: DEV-CONT-SPV011-Contrat_DEV_EPC_DAVAI_ENR-1 | BJ39: EX-CONT-SPV011-Contrat_Suivi_O&M_Gestion_Actifs_DAVAI_ENR-1 | BK39: 856 | BL39: 168.2513 | BX39: Stockage matériel, stockage paille, foin et fourrage, ruches et bois dans la limite de 50% | CB39: FALSE | CC39: Élément | CD39: sites/ServiceOM-AssetManagement/Lists/Exploitation Data Centrale
A40: 3251 | B40: SCI KILJOR | C40: DAVAI ENRSPV13 | D40: 45873 | E40: Lieu dit Ponson | F40: 07800 | G40: La Voulte-sur-Rhône | H40: BE | I40: Toiture inclinée | J40: Tertiaire | K40: S21 | L40: BTA1212567 | M40: 9590800 | N40: 1 | O40: 50040884577780 | P40: 109.2 | Q40: 110 | R40: 99 | S40: 1196 | T40: 130603.2 | U40: 0.054 | V40: 0.8659 | W40: 1211.44 | X40: BT | Y40: 45336 | Z40: 0.1151 | AB40: FALSE | AC40: EDF OA | AD40: ENEDIS | AE40: 479.546 | AF40: 44.81516 | AG40: 4.78922 | AH40: N°3 - Kyoto (SPV 10,13 &14) | AI40: RAS | AJ40: EIFFAGE | AK40: Cyrille FROMENT | AL40: cyril.froment07@gmail.com | AN40: +33609395304 | AP40: NEOXOM | AQ40: ACC | AR40: FALSE | AV40: FALSE | AZ40: FALSE | BD40: Yasser BADREZZAMANE | BE40: Johan LAGARDE | BF40: Sophie ROGIER | BG40: Hilal KAAOUANA | BH40: MTN-CONT-004-Contrat_EIFFAGE_maintenance_PV_BT-001 | BI40: DEV-CONT-SPV013-Contrat_DEV_EPC_DAVAI_ENR-1 | BJ40: EX-CONT-SPV013-Contrat_Suivi_OM_Gestion_Actifs_DAVAI -ENR-01 | BK40: 856 | BL40: 111.4764 | BR40: KILJOR | BS40: 4 Grand Rue | BT40: BEAUCHASTEL | BU40: 07800 | BV40: 530643675 | BX40: stockage et stationnement d’engins | CB40: FALSE | CC40: Élément | CD40: sites/ServiceOM-AssetManagement/Lists/Exploitation Data Centrale
A41: 95524 | B41: GAEC ROCHE THOREAU | C41: DAVAI ENRSPV10 | D41: 45869 | E41: Saint-Laurent-des-Mortiers, Lieu dit la Roche Thoreau | F41: 53290 | G41: Bierné-les-Villages | H41: BaC | I41: Toiture inclinée | J41: Agriculteur | K41: S21 | L41: BTA1044343 | M41: 9069450 | N41: 1 | O41: 50013536615650 | P41: 309.4 | Q41: 250 | R41: 249.99 | S41: 1143 | T41: 353644.2 | U41: 0.054 | V41: 0.8752 | W41: 1156.01 | X41: BT | Y41: 45057 | Z41: 0.1274 | AB41: FALSE | AC41: EDF OA | AD41: ENEDIS | AE41: 1358.713 | AF41: 47.76742 | AG41: -0.53195 | AH41: N°3 - Kyoto (SPV 10,13 &14) | AI41: Mot de passe onduleur : Exploitation2023 | AJ41: EIFFAGE | AK41: Emmanuel NEUVILLE | AL41: roche-thoreau@orange.fr | AN41: +33681521888 | AO41: +33689422133 | AP41: REGISOLAIR | AQ41: GIRAUD | AR41: FALSE | AV41: FALSE | AZ41: FALSE | BD41: Yasser BADREZZAMANE | BE41: Johan LAGARDE | BF41: Nicolas PETROPAVLOVSKY | BG41: Loïc GUILLEUX | BH41: MTN-CONT-004-Contrat_EIFFAGE_maintenance_PV_BT-001 | BI41: DEV-CONT-SPV010-Contrat_DEV_EPC_DAVAI_ENR-1 | BJ41: EX-CONT-SPV010-Contrat_Suivi_O&M_Gestion_Actifs_DAVAI_ENR-1 | BK41: 856 | BL41: 184.9498 | BX41: Stockage matériel (35%), fourrage (45%) et céréales (20%) | CB41: FALSE | CC41: Élément | CD41: sites/ServiceOM-AssetManagement/Lists/Exploitation Data Centrale
A42: 49553 | B42: VILLARD | C42: DAVAI ENRSPV11 | D42: 45869 | E42: Garrigue de l'Asclade RD 83 | F42: 13310 | G42: Saint-Martin-de-Crau | H42: BaC | I42: Toiture inclinée | J42: Agriculteur | K42: S21 | L42: BTA1012066 | M42: 9082850 | N42: 1 | O42: 50013393606778 | P42: 189.735 | Q42: 220 | R42: 176 | S42: 1423 | T42: 269992.91 | U42: 0.054 | V42: 0.8591 | W42: 1393.05 | X42: BT | Y42: 45000 | Z42: 0.1312 | AB42: FALSE | AC42: EDF OA | AD42: ENEDIS | AE42: 833.211 | AF42: 43.66714 | AG42: 4.78965 | AH42: N°3 - Fuji (SPV 11&15) | AI42: Mot de passe onduleur : Exploitation2023 | AJ42: EIFFAGE | AK42: Christophe VILLARD | AL42: ecuriesdelasclade@orange.fr | AN42: +33626808005 | AO42: +331628763040 | AP42: NEOXOM | AQ42: ROINE | AR42: FALSE | AV42: FALSE | AZ42: FALSE | BD42: Yasser BADREZZAMANE | BE42: Jean-Paul THOROGOOD | BF42: Charbel BOUZERDAN | BG42: Hilal KAAOUANA | BH42: MTN-CONT-004-Contrat_EIFFAGE_maintenance_PV_BT-001 | BI42: DEV-CONT-SPV011-Contrat_DEV_EPC_DAVAI_ENR-1 | BJ42: EX-CONT-SPV011-Contrat_Suivi_O&M_Gestion_Actifs_DAVAI_ENR-1 | BK42: 856 | BL42: 141.03275 | BX42: manège | CB42: FALSE | CC42: Élément | CD42: sites/ServiceOM-AssetManagement/Lists/Exploitation Data Centrale
A43: 61191 | B43: MALTAVERNE | C43: DAVAI ENRSPV10 | D43: 45868 | E43: 638 route Chard | F43: 71320 | G43: Sainte-Radegonde | H43: BaC | I43: Toiture inclinée | J43: Agriculteur | K43: S21 | L43: BTA1100644 | M43: 9812450 | N43: 1 | O43: 50028442077361 | P43: 260.26 | Q43: 220 | R43: 220 | S43: 1112 | T43: 289409.12 | U43: 0.054 | V43: 0.8745 | W43: 1094.04 | X43: BT | Y43: 45134 | Z43: 0.1274 | AB43: FALSE | AC43: EDF OA | AD43: ENEDIS | AE43: 1142.918 | AF43: 46.69424 | AG43: 4.10364 | AH43: N°3 - Kyoto (SPV 10,13 &14) | AI43: Mot de passe onduleur : Exploitation2023 | AJ43: EIFFAGE | AK43: Serge MALTAVERNE | AL43: maltaverne71320@gmail.com | AN43: +33748122092 | AP43: PROSUNFRANCE | AQ43: WOLF | AR43: FALSE | AV43: FALSE | AZ43: FALSE | BD43: Yasser BADREZZAMANE | BE43: Johan LAGARDE | BF43: Nicolas PETROPAVLOVSKY | BG43: Sébastien GUYOUX | BH43: MTN-CONT-004-Contrat_EIFFAGE_maintenance_PV_BT-001 | BI43: DEV-CONT-SPV010-Contrat_DEV_EPC_DAVAI_ENR-1 | BJ43: EX-CONT-SPV010-Contrat_Suivi_O&M_Gestion_Actifs_DAVAI_ENR-1 | BK43: 856 | BL43: 166.91542 | BX43: Stabulation (70%), stockage de matériel, fourrage et céréales (30%) | CB43: FALSE | CC43: Élément | CD43: sites/ServiceOM-AssetManagement/Lists/Exploitation Data Centrale
A44: 96576 | B44: LACROIX | C44: DAVAI ENRSPV13 | D44: 45867 | E44: La Choisière, La Mare Lunelle Roulée | F44: 72600 | G44: Villeneuve-en-Perseigne | H44: BaC | I44: Toiture inclinée | J44: Agriculteur | K44: S21 | L44: BTA1049177 | M44: 9037400 | N44: 1 | O44: 50007024105104 | P44: 277.095 | Q44: 250 | R44: 250 | S44: 1153 | T44: 319490.53 | U44: 0.054 | V44: 0.88 | W44: 1151.98 | X44: BT | Y44: 45061 | Z44: 0.1274 | AB44: FALSE | AC44: EDF OA | AD44: ENEDIS | AE44: 1216.848 | AF44: 48.46493 | AG44: 0.30003 | AH44: N°3 - Kyoto (SPV 10,13 &14) | AI44: Mot de passe onduleur : Exploitation2023 | AJ44: EIFFAGE | AK44: Olivier LACROIX | AL44: zaboulili@orange.fr | AN44: +33676047978 | AO44: +33479690236 | AP44: LE TRIANGLE | AQ44: TRIANGLE | AR44: FALSE | AV44: FALSE | AZ44: FALSE | BD44: Yasser BADREZZAMANE | BE44: Johan LAGARDE | BF44: Nicolas PETROPAVLOVSKY | BG44: Loïc GUILLEUX | BH44: MTN-CONT-004-Contrat_EIFFAGE_maintenance_PV_BT-001 | BI44: DEV-CONT-SPV013-Contrat_DEV_EPC_DAVAI_ENR-1 | BJ44: EX-CONT-SPV013-Contrat_Suivi_OM_Gestion_Actifs_DAVAI -ENR-01 | BK44: 856 | BL44: 173.09386 | BX44: stabulation, stockage matériel + fourrage. | CB44: FALSE | CC44: Élément | CD44: sites/ServiceOM-AssetManagement/Lists/Exploitation Data Centrale
A45: 49814 | B45: VIEL | C45: DAVAI ENRSPV11 | D45: 45866 | E45: La Haute Bellangeraie | F45: 44390 | G45: Les Touches | H45: BaC | I45: Toiture inclinée | J45: Agriculteur | K45: S21 | L45: BTA1048685 | M45: 9081750 | N45: 1 | O45: 50005867363958 | P45: 211.575 | Q45: 220 | R45: 170 | S45: 1183 | T45: 250293.23 | U45: 0.054 | V45: 0.8782 | W45: 1165.63 | X45: BT | Y45: 45042 | Z45: 0.1312 | AB45: FALSE | AC45: EDF OA | AD45: ENEDIS | AE45: 929.12 | AF45: 47.46443 | AG45: -1.40235 | AH45: N°3 - Fuji (SPV 11&15) | AI45: Mot de passe onduleur : Exploitaiton2023 | AJ45: EIFFAGE | AK45: Jean-Marc VIEL | AL45: Bailleur n'a pas d'email | AN45: +33617582211 | AO45: +33240724321 | AP45: OFT | AQ45: CANCE | AR45: FALSE | AV45: FALSE | AZ45: FALSE | BD45: Yasser BADREZZAMANE | BE45: Jean-Paul THOROGOOD | BF45: Nicolas PETROPAVLOVSKY | BG45: Loïc GUILLEUX | BH45: MTN-CONT-004-Contrat_EIFFAGE_maintenance_PV_BT-001 | BI45: DEV-CONT-SPV011-Contrat_DEV_EPC_DAVAI_ENR-1 | BJ45: EX-CONT-SPV011-Contrat_Suivi_O&M_Gestion_Actifs_DAVAI_ENR-1 | BK45: 856 | BL45: 149.04802 | BR45: Jean-Marc VIEL | BS45: La Haute Bellangerais | BT45: Les Touches | BU45: 44390 | BX45: Stockage matériel + fourrage | CB45: FALSE | CC45: Élément | CD45: sites/ServiceOM-AssetManagement/Lists/Exploitation Data Centrale
A46: 95308 | B46: LOGNON | C46: DAVAI ENRSPV11 | D46: 45863 | E46: Château des Millets | F46: 03230 | G46: Chevagnes | H46: BaC | I46: Toiture inclinée | J46: Agriculteur | K46: S21 | L46: BTA0949434 | M46: 9138350 | N46: 1 | O46: 50060998814809 | P46: 156.975 | Q46: 150 | R46: 173 | S46: 1039 | T46: 163097.02 | U46: 0.054 | V46: 0.8702 | W46: 1062.39 | X46: BT | Y46: 44810 | Z46: 0.1274 | AB46: FALSE | AC46: EDF OA | AD46: ENEDIS | AE46: 689.347 | AF46: 46.60384 | AG46: 3.61714 | AH46: N°3 - Fuji (SPV 11&15) | AI46: Mot de passe onduleur : Exploitaiton2023 | AJ46: EIFFAGE | AK46: Eric LOGNON | AL46: alain.lognon@orange.fr | AN46: +33610916907 | AP46: PROSUNFRANCE | AQ46: PROSUNFRANCE | AR46: FALSE | AV46: FALSE | AZ46: FALSE | BD46: Yasser BADREZZAMANE | BE46: Jean-Paul THOROGOOD | BF46: Charbel BOUZERDAN | BG46: Sébastien GUYOUX | BH46: MTN-CONT-004-Contrat_EIFFAGE_maintenance_PV_BT-001 | BI46: DEV-CONT-SPV011-Contrat_DEV_EPC_DAVAI_ENR-1 | BJ46: EX-CONT-SPV011-Contrat_Suivi_O&M_Gestion_Actifs_DAVAI_ENR-1 | BK46: 856 | BL46: 129.00983 | BX46: stabulation | CB46: FALSE | CC46: Élément | CD46: sites/ServiceOM-AssetManagement/Lists/Exploitation Data Centrale
A47: 95309 | B47: LOGNON | C47: DAVAI ENRSPV11 | D47: 45863 | E47: Château des Millets | F47: 03230 | G47: Chevagnes | H47: BE | I47: Toiture inclinée | J47: Agriculteur | K47: S21 | L47: BTA0949433 | M47: 9129750 | N47: 1 | O47: 50084016909949 | P47: 324.87 | Q47: 250 | R47: 249.9 | S47: 1200 | T47: 389844 | U47: 0.054 | V47: 0.8624 | W47: 1180.46 | X47: BT | Y47: 44838 | Z47: 0.1274 | AB47: FALSE | AC47: EDF OA | AD47: ENEDIS | AE47: 1426.649 | AF47: 46.60446 | AG47: 3.61907 | AH47: N°3 - Fuji (SPV 11&15) | AI47: Mot de passe onduleur : Exploitaiton2023 | AJ47: EIFFAGE | AK47: Eric LOGNON | AL47: alain.lognon@orange.fr | AN47: +33610916907 | AP47: PROSUNFRANCE | AQ47: CANCE | AR47: FALSE | AV47: FALSE | AZ47: FALSE | BD47: Yasser BADREZZAMANE | BE47: Jean-Paul THOROGOOD | BF47: Charbel BOUZERDAN | BG47: Sébastien GUYOUX | BH47: MTN-CONT-004-Contrat_EIFFAGE_maintenance_PV_BT-001 | BI47: DEV-CONT-SPV011-Contrat_DEV_EPC_DAVAI_ENR-1 | BJ47: EX-CONT-SPV011-Contrat_Suivi_O&M_Gestion_Actifs_DAVAI_ENR-1 | BK47: 856 | BL47: 190.62729 | BX47: stockage de matériel/foin et fourrage | CB47: FALSE | CC47: Élément | CD47: sites/ServiceOM-AssetManagement/Lists/Exploitation Data Centrale
A48: 32074 | B48: PRIEUR | C48: DAVAI ENRSPV10 | D48: 45862 | E48: Franconnet | F48: 26120 | G48: Montmeyran | H48: BaC | I48: Toiture inclinée | J48: Agriculteur | K48: S21 | L48: BTA1097189 | BTA1096997 | M48: 9137850 | 9139050 | N48: 1 | O48: 50008325850228 | 50057093344597 | P48: 499.59 | Q48: 440 | R48: 392 | S48: 1257.132 | T48: 628050.58 | U48: 0.054 | V48: 0.8662 | W48: 1232.64 | X48: BT | Y48: 45127 | Z48: 0.1274 | AB48: FALSE | AC48: EDF OA | AD48: ENEDIS | AE48: 2193.922 | AF48: 44.84159 | AG48: 4.96118 | AH48: N°3 - Kyoto (SPV 10,13 &14) | AI48: Mot de passe onduleur : Exploitation2023 | AJ48: EIFFAGE | AK48: Christian DIDIER | AL48: krystine.didier26@gmail.com | AN48: +33608125049 | AP48: KEVEL | AQ48: ROINE | AR48: FALSE | AV48: FALSE | AZ48: FALSE | BD48: Yasser BADREZZAMANE | BE48: Johan LAGARDE | BF48: Sophie ROGIER | BG48: Hilal KAAOUANA | BH48: MTN-CONT-004-Contrat_EIFFAGE_maintenance_PV_BT-001 | BI48: DEV-CONT-SPV010-Contrat_DEV_EPC_DAVAI_ENR-1 | BJ48: EX-CONT-SPV010-Contrat_Suivi_O&M_Gestion_Actifs_DAVAI_ENR-1 | BK48: 856 | BL48: 254.74953 | BX48: Manège | CB48: FALSE | CC48: Élément | CD48: sites/ServiceOM-AssetManagement/Lists/Exploitation Data Centrale
A49: 96147 | B49: CHASSON | C49: DAVAI ENRSPV13 | D49: 45859 | E49: 525 Rue Jean Rostand | F49: 26800 | G49: Portes-lès-Valence | H49: BaC | I49: Toiture inclinée | J49: Tertiaire | K49: S21 | L49: BTA1209245 | BTA1203877 | M49: 9341700 | 9337100 | N49: 2 | O49: 50062303719998 | 50011652489934 | P49: 388.04 | Q49: 500 | R49: 368 | S49: 1268 | T49: 492034.72 | U49: 0.054 | V49: 0.8684 | W49: 1259.19 | X49: BT | Y49: 45328 | Z49: 0.1151 | AB49: FALSE | AC49: EDF OA | AD49: ENEDIS | AE49: 1742.35 | AF49: 44.89225 | AG49: 4.87492 | AH49: N°3 - Kyoto (SPV 10,13 &14) | AI49: Mot de passe onduleur : Exploitation2023 | AJ49: EIFFAGE | AK49: Benjamin CHASSON | AL49: francois.jallerat0038@orange.fr | AN49: +33664620294 | AP49: NEOXOM | AQ49: MOMSTEEL | AR49: FALSE | AV49: FALSE | AZ49: FALSE | BD49: Yasser BADREZZAMANE | BE49: Johan LAGARDE | BF49: Sophie ROGIER | BG49: Hilal KAAOUANA | BH49: MTN-CONT-004-Contrat_EIFFAGE_maintenance_PV_BT-001 | BI49: DEV-CONT-SPV013-Contrat_DEV_EPC_DAVAI_ENR-1 | BJ49: EX-CONT-SPV013-Contrat_Suivi_OM_Gestion_Actifs_DAVAI -ENR-01 | BK49: 856 | BL49: 213.81068 | BX49: ERT , stockage de marchandises véhicules produits et marchandises divers | CB49: FALSE | CC49: Élément | CD49: sites/ServiceOM-AssetManagement/Lists/Exploitation Data Centrale
A50: 82721 | B50: CHERAUD | C50: DAVAI ENRSPV13 | D50: 45856 | E50: Bellevue | F50: 44260 | G50: Malville | H50: BaC | I50: Toiture inclinée | J50: Agriculteur | K50: S21 | L50: BTA1093289 | BTA1093282 | M50: 9058000 | 9094150 | N50: 2 | O50: 50053767344853 | 50065634204653 | P50: 499.59 | Q50: 417 | R50: 417 | S50: 1106 | T50: 552546.54 | U50: 0.054 | V50: 0.8769 | W50: 1102.59 | X50: BT | Y50: 45132 | Z50: 0.1274 | AB50: FALSE | AC50: EDF OA | AD50: ENEDIS | AE50: 2193.922 | AF50: 47.355 | AG50: -1.83701 | AH50: N°3 - Kyoto (SPV 10,13 &14) | AI50: Pas de communication PDL1 → mise en réserve construction | AJ50: EIFFAGE | AK50: CHERAUD Nicolas | AL50: nicolas.cheraud@orange.fr | AN50: 0668055111 | AP50: OFT | AQ50: WOLF | AR50: FALSE | AV50: FALSE | AZ50: FALSE | BD50: Parfait MEZEME ONA | BE50: Johan LAGARDE | BF50: Nicolas PETROPAVLOVSKY | BG50: Loïc GUILLEUX | BH50: MTN-CONT-004-Contrat_EIFFAGE_maintenance_PV_BT-001 | BI50: DEV-CONT-SPV013-Contrat_DEV_EPC_DAVAI_ENR-1 | BJ50: EX-CONT-SPV013-Contrat_Suivi_OM_Gestion_Actifs_DAVAI -ENR-01 | BK50: 856 | BL50: 254.74953 | BM50: 45856 | BX50: Stockage fourrage + stabulation | CB50: FALSE | CC50: Élément | CD50: sites/ServiceOM-AssetManagement/Lists/Exploitation Data Centrale
A51: 30516 | B51: LAMIOT | C51: DAVAI ENRSPV10 | D51: 45854 | E51: La Gélopière | F51: 42110 | G51: Feurs | H51: BaC | I51: Toiture inclinée | J51: Agriculteur | K51: S21 | L51: BTA1085310 | M51: 8820650 | N51: 1 | O51: 50035677987321 | P51: 343.07 | Q51: 250 | R51: 249.9 | S51: 1129 | T51: 387326.03 | U51: 0.054 | V51: 0.8775 | W51: 1152.63 | X51: BT | Y51: 45118 | Z51: 0.1274 | AB51: FALSE | AC51: EDF OA | AD51: ENEDIS | AE51: 1506.573 | AF51: 45.73247 | AG51: 4.2053 | AH51: N°3 - Kyoto (SPV 10,13 &14) | AI51: Mot de passe onduleur : Exploitation2023 | AJ51: EIFFAGE | AK51: SIMON LAMIOT | AL51: lamiot.pro@gmail.com | AN51: +33623883570 | AO51: +33630103634 | AP51: PROSUNFRANCE | AQ51: MOMSTEEL | AR51: FALSE | AV51: FALSE | AZ51: FALSE | BD51: Yasser BADREZZAMANE | BE51: Johan LAGARDE | BF51: Nicolas PETROPAVLOVSKY | BG51: Alexandre COL | BH51: MTN-CONT-004-Contrat_EIFFAGE_maintenance_PV_BT-001 | BI51: DEV-CONT-SPV010-Contrat_DEV_EPC_DAVAI_ENR-1 | BJ51: EX-CONT-SPV010-Contrat_Suivi_O&M_Gestion_Actifs_DAVAI_ENR-1 | BK51: 856 | BL51: 197.30669 | BX51: Stockage matériel agricole | CB51: FALSE | CC51: Élément | CD51: sites/ServiceOM-AssetManagement/Lists/Exploitation Data Centrale
A52: 59512 | B52: BOIS BELLOIR | C52: DAVAI ENRSPV14 | D52: 45854 | E52: Le Château | F52: 85190 | G52: La Génétouze | H52: BaC | I52: Toiture inclinée | J52: Agriculteur | K52: S21 | L52: BTA1165477 | M52: 8755850 | N52: 1 | O52: 50096313186405 | P52: 327.6 | Q52: 250 | R52: 249 | S52: 1100 | T52: 360360 | U52: 0.054 | V52: 0.876 | W52: 1110.3 | X52: BT | Y52: 45257 | Z52: 0.1208 | AB52: FALSE | AC52: EDF OA | AD52: ENEDIS | AE52: 1438.638 | AF52: 46.72134 | AG52: -1.48315 | AH52: N°3 - Kyoto (SPV 10,13 &14) | AI52: Mot de passe onduleur : Exploitation2023 | AJ52: EIFFAGE | AK52: VALERIE HOUSET | AL52: valdenormandie@outlook.fr | AN52: +33682345960 | AP52: REGISOLAIR | AQ52: JAMES | AR52: FALSE | AV52: FALSE | AZ52: FALSE | BD52: Yasser BADREZZAMANE | BE52: Victor PONTAIS | BF52: Nicolas PETROPAVLOVSKY | BG52: Loïc GUILLEUX | BH52: MTN-CONT-004-Contrat_EIFFAGE_maintenance_PV_BT-001 | BI52: DEV-CONT-SPV014_Contrat_DEV_EPC_DAVAI_ENR-1 (signed) (1) | BJ52: EX-CONT-SPV014-Contrat_Suivi_OM_Gestion_Actifs_DAVAI -ENR-01 (1) | BK52: 856 | BL52: 191.6292 | BX52: Manège equestre | CB52: FALSE | CC52: Élément | CD52: sites/ServiceOM-AssetManagement/Lists/Exploitation Data Centrale
A53: 29815 | B53: FERRAND | C53: DAVAI ENRSPV7 | D53: 45853 | E53: Lieu Dit Rochereau | F53: 33190 | G53: Pondaurat | H53: BaC | I53: Toiture inclinée | J53: Agriculteur | K53: S21 | L53: BTA.33331.000006 | M53: 33331.000006 | N53: 1 | O53: 85601939985904 | P53: 388.08 | Q53: 330 | R53: 249 | S53: 1115 | T53: 432709.2 | U53: 0.05 | V53: 0.853 | W53: 1137.2 | X53: BT | Y53: 44986 | Z53: 0.1312 | AB53: FALSE | AC53: REGIE D’ELECTRICITE DU SYNDICAT DU SUD-DE-LA REOLE | AD53: REGIE D’ELECTRICITE DU SYNDICAT DU SUD-DE-LA REOLE | AE53: 1762.331 | AF53: 44.53908 | AG53: -0.08101 | AH53: N°2 - Finergreen - Construction 2023 | AI53: Mot de passe onduleur : Exploitation2023 | AJ53: EIFFAGE | AK53: EMILIE FERRAND | AL53: ecuriesdeginkgo@hotmail.fr | AN53: +33630311451 | AP53: LE TRIANGLE | AQ53: TRIANGLE | AR53: FALSE | AV53: FALSE | AZ53: FALSE | BD53: Yasser BADREZZAMANE | BE53: Johan LAGARDE | BF53: Ibtissam ABSSI | BG53: Charlie BLAIZEAU | BH53: MTN-CONT-004-Contrat_EIFFAGE_maintenance_PV_BT-001 | BI53: DEV-CONT-SPV007-Contrat_DEV_EPC_DAVAI_ENR-1 | BJ53: EX-CONT-SPV007-Contrat_Suivi_O&M_Gestion_Actifs_DAVAI_ENR-1 | BK53: 856 | BL53: 207.52536 | BM53: 45914 | BN53: 45926 | BX53: Manège et boxes à chevaux. Stockage de paille, foin, fourrage. | BY53: 45853 | BZ53: 53050 | CA53: 45925 | CB53: FALSE | CC53: Élément | CD53: sites/ServiceOM-AssetManagement/Lists/Exploitation Data Centrale
A54: 98037 | B54: PLANTIER | C54: DAVAI ENRSPV14 | D54: 45848 | E54: Hameau de Balaguier | F54: 11230 | G54: Corbières | H54: BaC | I54: Toiture inclinée | J54: Agriculteur | K54: S21 | L54: BTA1042669 | M54: 9194450 | N54: 1 | O54: 50098920381644 | P54: 296 | Q54: 250 | R54: 249.9 | S54: 1249 | T54: 369704 | U54: 0.054 | V54: 0.873 | W54: 1251.6 | X54: BT | Y54: 45040 | Z54: 0.1312 | AB54: FALSE | AC54: EDF OA | AD54: ENEDIS | AE54: 1301 | AF54: 43.04144 | AG54: 1.99681 | AH54: N°3 - Kyoto (SPV 10,13 &14) | AI54: RAS | AJ54: EIFFAGE | AK54: Céline Plantier | AL54: plantier.celine@hotmail.fr | AN54: +33 6 74 26 31 03 | AO54: +33 6 87 11 68 66 | AP54: YAMA ENERGIES | AQ54: CANCE | AR54: FALSE | AV54: FALSE | AZ54: FALSE | BD54: Parfait MEZEME ONA | BE54: Victor PONTAIS | BF54: Maxime DENIAU | BG54: Gabriel AYMA | BH54: MTN-CONT-004-Contrat_EIFFAGE_maintenance_PV_BT-001 | BI54: DEV-CONT-SPV014_Contrat_DEV_EPC_DAVAI_ENR-1 (signed) (1) | BJ54: EX-CONT-SPV014-Contrat_Suivi_OM_Gestion_Actifs_DAVAI -ENR-01 (1) | BK54: 856 | BL54: 180.032 | BX54: Stabulation | CB54: FALSE | CC54: Élément | CD54: sites/ServiceOM-AssetManagement/Lists/Exploitation Data Centrale
A55: 83800 | B55: PHILIPPON | C55: DAVAI ENRSPV13 | D55: 45840 | E55: 1740 Rte du Pouzin | F55: 07210 | G55: Baix | H55: BaC | I55: Toiture inclinée | J55: Agriculteur | K55: S21 | L55: BTA1045251 | BTA1045263 | M55: 9563750 | 9564700 | N55: 2 | O55: 50022219904640 | 50019614984445 | P55: 417.69 | Q55: 330 | R55: 330 | S55: 1283.0837 | T55: 535931.24 | U55: 0.054 | V55: 0.8657 | W55: 1287.35 | X55: BT | Y55: 45040 | Z55: 0.1274 | AB55: FALSE | AC55: EDF OA | AD55: ENEDIS | AE55: 1834.263 | AF55: 44.72915 | AG55: 4.74238 | AH55: N°3 - Kyoto (SPV 10,13 &14) | AI55: Mot de passe onduleur : Exploitation2023 | AJ55: EIFFAGE | AK55: Jérôme PHILIPPON | AL55: jerome.philippon3@wanadoo.fr | AN55: +33677884361 | AP55: PROSUNFRANCE | AQ55: GIRAUD | AR55: FALSE | AV55: FALSE | AZ55: FALSE | BD55: Yasser BADREZZAMANE | BE55: Johan LAGARDE | BF55: Charbel BOUZERDAN | BG55: Thibault RAHMOUNI | BH55: MTN-CONT-004-Contrat_EIFFAGE_maintenance_PV_BT-001 | BI55: DEV-CONT-SPV013-Contrat_DEV_EPC_DAVAI_ENR-1 | BJ55: EX-CONT-SPV013-Contrat_Suivi_OM_Gestion_Actifs_DAVAI -ENR-01 | BK55: 856 | BL55: 224.69223 | BX55: Stockage matériel et productions fruitières -conditionnement -calibrage et chambres froides | CB55: FALSE | CC55: Élément | CD55: sites/ServiceOM-AssetManagement/Lists/Exploitation Data Centrale
A56: 48851 | B56: BARASSIN | C56: DAVAI ENRSPV8 | D56: 45840 | E56: 414 Route de Caen, Le Lieu Allais | F56: 14130 | G56: Clarbec | H56: BaC | I56: Toiture inclinée | J56: Agriculteur | K56: S21 | L56: BTA1006713 | M56: 8317600 | N56: 1 | O56: 50071425315635 | P56: 335.53 | Q56: 250 | R56: 249.9 | S56: 992 | T56: 332845.76 | U56: 0.054 | V56: 0.866 | W56: 979.4 | X56: BT | Y56: 44984 | Z56: 0.1312 | AB56: FALSE | AC56: EDF OA | AD56: ENEDIS | AE56: 1506.573 | AF56: 49.26446 | AG56: 0.1355 | AH56: N°2 - Finergreen - Construction 2023 | AI56: Mot de passe onduleur : Exploitation2023 | AJ56: EIFFAGE | AK56: Philippe BARASSIN | AL56: sophie.du14@hotmail.fr | AN56: +33673239787 | AP56: LE TRIANGLE | AQ56: TRIANGLE | AR56: FALSE | AV56: FALSE | AZ56: FALSE | BD56: Yasser BADREZZAMANE | BE56: Johan LAGARDE | BF56: Ibtissam ABSSI | BG56: Kalil KRIFA | BH56: MTN-CONT-004-Contrat_EIFFAGE_maintenance_PV_BT-001 | BI56: DEV-CONT-SPV008-Contrat_DEV_EPC_DAVAI_ENR-1 | BJ56: EX-CONT-SPV008-Contrat_Suivi_O&M_Gestion_Actifs_DAVAI_ENR-1 | BK56: 856 | BL56: 188.23951 | BM56: 45888 | BN56: 45926 | BX56: Stockage et boxes | CB56: FALSE | CC56: Élément | CD56: sites/ServiceOM-AssetManagement/Lists/Exploitation Data Centrale
A57: 59503 | B57: FRAGNON | C57: DAVAI ENRSPV11 | D57: 45840 | E57: Lieu-dit les Passets | F57: 03160 | G57: Franchesse | H57: BaC | I57: Toiture inclinée | J57: Agriculteur | K57: S21 | L57: BTA1087742 | M57: 9224200 | N57: 1 | O57: 50059265338008 | P57: 309.4 | Q57: 250 | R57: 249.9 | S57: 1073 | T57: 331986.2 | U57: 0.054 | V57: 0.8722 | W57: 1094.66 | X57: BT | Y57: 45114 | Z57: 0.1274 | AB57: FALSE | AC57: EDF OA | AD57: ENEDIS | AE57: 1358.713 | AF57: 46.66373 | AG57: 3.06683 | AH57: N°3 - Fuji (SPV 11&15) | AI57: Mot de passe onduleur : Exploitation2023 | AJ57: EIFFAGE | AK57: Christophe FRAGNON | AL57: c.chfragnon@orange.fr | AN57: +33680256111 | AO57: +33680202796 | AP57: OFT | AQ57: MOMSTEEL | AR57: FALSE | AV57: FALSE | AZ57: FALSE | BD57: Yasser BADREZZAMANE | BE57: Jean-Paul THOROGOOD | BF57: Ibtissam ABSSI | BG57: Sébastien GUYOUX | BH57: MTN-CONT-004-Contrat_EIFFAGE_maintenance_PV_BT-001 | BI57: DEV-CONT-SPV011-Contrat_DEV_EPC_DAVAI_ENR-1 | BJ57: EX-CONT-SPV011-Contrat_Suivi_O&M_Gestion_Actifs_DAVAI_ENR-1 | BK57: 856 | BL57: 184.9498 | BX57: Stabulation | CB57: FALSE | CC57: Élément | CD57: sites/ServiceOM-AssetManagement/Lists/Exploitation Data Centrale
A58: 35280 | B58: BLANCHET | C58: DAVAI ENRSPV14 | D58: 45838 | E58: Route de Vinsobres, Les Esclis | F58: 26110 | G58: Venterol | H58: BaC | I58: Toiture inclinée | J58: Agriculteur | K58: S21 | L58: BTA1090163 | M58: 9321300 | N58: 1 | O58: 50050148812315 | P58: 159.25 | Q58: 165 | R58: 143 | S58: 1316 | T58: 209573 | U58: 0.054 | V58: 0.871 | W58: 1366.5 | X58: BT | Y58: 45100 | Z58: 0.1274 | AB58: FALSE | AC58: EDF OA | AD58: ENEDIS | AE58: 699.338 | AF58: 44.36059 | AG58: 5.07619 | AH58: N°3 - Kyoto (SPV 10,13 &14) | AI58: Mot de passe onduleur : Exploitation2023 | AJ58: EIFFAGE | AK58: Patrick BLANCHET | AL58: blanchetpatrick0925@orange.fr | AN58: +33683143539 | AP58: KEVEL | AQ58: HBBAT | AR58: FALSE | AV58: FALSE | AZ58: FALSE | BD58: Yasser BADREZZAMANE | BE58: Victor PONTAIS | BF58: Charbel BOUZERDAN | BG58: Thibault RAHMOUNI | BH58: MTN-CONT-004-Contrat_EIFFAGE_maintenance_PV_BT-001 | BI58: DEV-CONT-SPV014_Contrat_DEV_EPC_DAVAI_ENR-1 (signed) (1) | BJ58: EX-CONT-SPV014-Contrat_Suivi_OM_Gestion_Actifs_DAVAI -ENR-01 (1) | BK58: 856 | BL58: 129.84475 | BX58: Stockage de matériel agricole et viticole | CB58: FALSE | CC58: Élément | CD58: sites/ServiceOM-AssetManagement/Lists/Exploitation Data Centrale
A59: 3334 | B59: MATHIEU VINCENT | C59: GIRASPV15 | D59: 45838 | E59: Lieu-dit Les Avals | F59: 11700 | G59: LA REDORTE | H59: BaC | I59: Toiture inclinée | J59: Agriculteur | K59: S21 | L59: BTA1201391 | M59: 9337150 | N59: 1 | O59: 50070552162298 | P59: 218.4 | Q59: 165 | R59: 165 | S59: 1242 | T59: 271252.8 | U59: 0.054 | V59: 0.872 | W59: 1294.1 | X59: BT | Y59: 45324 | Z59: 0.1151 | AB59: FALSE | AC59: EDF OA | AD59: ENEDIS | AE59: 959.092 | AF59: 43.24989 | AG59: 2.64117 | AH59: N°3 - Fuji (SPV 11&15) | AI59: Mot de passe onduleur : Exploitation2023 | AJ59: EIFFAGE | AK59: Vincent MATHIEU | AL59: Vincentmathieu11@icloud.com | AN59: +33687565530 | AP59: KEVEL | AQ59: GIRAUD | AR59: FALSE | AV59: FALSE | AZ59: FALSE | BD59: Yasser BADREZZAMANE | BE59: Jean-Paul THOROGOOD | BF59: Maxime DENIAU | BG59: Gabriel AYMA | BH59: MTN-CONT-004-Contrat_EIFFAGE_maintenance_PV_BT-001 | BI59: DEV-CONT-SPV015_Contrat_DEV_EPC_DAVAI_ENR-1 (signed) (1) | BJ59: EX-CONT-SPV015-Contrat_Suivi_OM_Gestion_Actifs_DAVAI -ENR-01 | BK59: 856 | BL59: 151.5528 | BR59: Vincent MATHIEU | BS59: 4 rue des Rosiers | BT59: La Redorte | BU59: 11700 | BW59: 56795 | BX59: Stockage matériel, coin atelier | CB59: FALSE | CC59: Élément | CD59: sites/ServiceOM-AssetManagement/Lists/Exploitation Data Centrale
A60: 60829 | B60: BOUVIER | C60: DAVAI ENRSPV10 | D60: 45835 | E60: Les Guillemins | F60: 03340 | G60: Neuilly-le-Réal | H60: BaC | I60: Toiture inclinée | J60: Agriculteur | K60: S21 | L60: BTA1033748 | M60: 9251050 | N60: 1 | O60: 50038283597580 | P60: 249.795 | Q60: 220 | R60: 208 | S60: 1093 | T60: 273025.93 | U60: 0.054 | V60: 0.8752 | W60: 1081.56 | X60: BT | Y60: 44712 | Z60: 0.1312 | AB60: FALSE | AC60: EDF OA | AD60: ENEDIS | AE60: 1096.961 | AF60: 46.4599 | AG60: 3.43744 | AH60: N°3 - Kyoto (SPV 10,13 &14) | AI60: Mot de passe onduleur : Exploitation2023 | AJ60: EIFFAGE | AK60: Pierre BOUVIER | AL60: gaecdesguillemins03@gmail.com | AN60: +33681250350 | AP60: PROSUNFRANCE | AQ60: CANCE | AR60: FALSE | AV60: FALSE | AZ60: FALSE | BD60: Yasser BADREZZAMANE | BE60: Johan LAGARDE | BF60: Charbel BOUZERDAN | BG60: Sébastien GUYOUX | BH60: MTN-CONT-004-Contrat_EIFFAGE_maintenance_PV_BT-001 | BI60: DEV-CONT-SPV010-Contrat_DEV_EPC_DAVAI_ENR-1 | BJ60: EX-CONT-SPV010-Contrat_Suivi_O&M_Gestion_Actifs_DAVAI_ENR-1 | BK60: 856 | BL60: 163.07477 | BX60: stockage matériel et fourrage, stabulation | CB60: FALSE | CC60: Élément | CD60: sites/ServiceOM-AssetManagement/Lists/Exploitation Data Centrale
A61: 60832 | B61: BOUVIER | C61: DAVAI ENRSPV10 | D61: 45835 | E61: Les Guillemins | F61: 03340 | G61: Neuilly-le-Réal | H61: BaC | I61: Toiture inclinée | J61: Agriculteur | K61: S21 | L61: BTA1033591 | M61: 9228850 | N61: 1 | O61: 50031047707531 | P61: 249.795 | Q61: 220 | R61: 208 | S61: 1098 | T61: 274274.91 | U61: 0.054 | V61: 0.876 | W61: 1083.1 | X61: BT | Y61: 44712 | Z61: 0.1312 | AB61: FALSE | AC61: EDF OA | AD61: ENEDIS | AE61: 1096.961 | AF61: 46.46043 | AG61: 3.43816 | AH61: N°3 - Kyoto (SPV 10,13 &14) | AI61: Mot de passe onduleur : Exploitation2023 | AJ61: EIFFAGE | AK61: Pierre BOUVIER | AL61: gaecdesguillemins03@gmail.com | AN61: +33681250350 | AP61: PROSUNFRANCE | AQ61: CANCE | AR61: FALSE | AV61: FALSE | AZ61: FALSE | BD61: Yasser BADREZZAMANE | BE61: Johan LAGARDE | BF61: Charbel BOUZERDAN | BG61: Sébastien GUYOUX | BH61: MTN-CONT-004-Contrat_EIFFAGE_maintenance_PV_BT-001 | BI61: DEV-CONT-SPV010-Contrat_DEV_EPC_DAVAI_ENR-1 | BJ61: EX-CONT-SPV010-Contrat_Suivi_O&M_Gestion_Actifs_DAVAI_ENR-1 | BK61: 856 | BL61: 163.07477 | BX61: stabulation | CB61: FALSE | CC61: Élément | CD61: sites/ServiceOM-AssetManagement/Lists/Exploitation Data Centrale
A62: 76546 | B62: PANSIER | C62: DAVAI ENRSPV13 | D62: 45833 | E62: 109 Chem. de Trespeaux | F62: 30340 | G62: Mons | H62: BaC | I62: Toiture inclinée | J62: Agriculteur | K62: S21 | L62: BTA0981145 | M62: 9110650 | N62: 1 | O62: 50050586054027 | P62: 163.8 | Q62: 165 | R62: 143 | S62: 1382 | T62: 226371.6 | U62: 0.054 | V62: 0.8654 | W62: 1431.23 | X62: BT | Y62: 44910 | Z62: 0.1311 | AB62: FALSE | AC62: EDF OA | AD62: ENEDIS | AE62: 719.319 | AF62: 44.12266 | AG62: 4.1517 | AH62: N°3 - Kyoto (SPV 10,13 &14) | AI62: Mot de passe onduleur : Exploitation2023 | AJ62: EIFFAGE | AK62: Jacques PANSIER | AL62: pansier.jacques@wanadoo.fr | AN62: +33 6 11 81 12 44 | AP62: KEVEL | AQ62: GIRAUD | AR62: FALSE | AV62: FALSE | AZ62: FALSE | BD62: Yasser BADREZZAMANE | BE62: Johan LAGARDE | BF62: Charbel BOUZERDAN | BG62: Gabriel AYMA | BH62: MTN-CONT-004-Contrat_EIFFAGE_maintenance_PV_BT-001 | BI62: DEV-CONT-SPV013-Contrat_DEV_EPC_DAVAI_ENR-1 | BJ62: EX-CONT-SPV013-Contrat_Suivi_OM_Gestion_Actifs_DAVAI -ENR-01 | BK62: 856 | BL62: 131.5146 | BX62: stockage matériel et semences | CB62: FALSE | CC62: Élément | CD62: sites/ServiceOM-AssetManagement/Lists/Exploitation Data Centrale
A63: 3384 | B63: CONCEPT-TY | C63: DAVAI ENRSPV7 | D63: 45832 | E63: Rue Etienne Cosson | F63: 37170 | G63: Chambray-lès-Tours | H63: BE | I63: Toiture inclinée | J63: Agriculteur | K63: S21 | L63: BTA1117650 | M63: 8833350 | N63: 1 | O63: 50017732008744 | P63: 118.37 | Q63: 110 | R63: 99 | S63: 1142 | T63: 135178.54 | U63: 0.054 | V63: 0.84513641 | W63: 1111.92 | X63: BT | Y63: 45174 | Z63: 0.124 | AB63: FALSE | AC63: EDF OA | AD63: ENEDIS | AE63: 531 | AF63: 47.32796 | AG63: 0.70112 | AH63: N°2 - Finergreen - Construction 2023 | AI63: Mot de passe onduleur : Exploitation2023 | AJ63: EIFFAGE | AK63: Paul-Henri AUBRUN | AL63: ph.aubrun@concept-ty.com | AN63: +33667793414 | AP63: REGISOLAIR | AQ63: PV READY | AR63: TRUE | AS63: 46022 | AT63: 46022 | AU63: Fixe Indexé | AV63: FALSE | AX63: 850 | AY63: Annuelle | AZ63: TRUE | BA63: fixe | BC63: 850 | BD63: Yasser BADREZZAMANE | BE63: Johan LAGARDE | BF63: Nicolas PETROPAVLOVSKY | BG63: Loïc GUILLEUX | BH63: MTN-CONT-004-Contrat_EIFFAGE_maintenance_PV_BT-001 | BI63: DEV-CONT-SPV007-Contrat_DEV_EPC_DAVAI_ENR-1 | BJ63: EX-CONT-SPV007-Contrat_Suivi_O&M_Gestion_Actifs_DAVAI_ENR-1 | BK63: 856 | BL63: 108.54179 | BM63: 45848 | BN63: 45929 | BR63: ACTI CHAMBRAY 2 | BS63: 8 rue Deroyer | BT63: DINAN | BU63: 22100 | BV63: 910869635 | BX63: Bâtiment d'activité | CB63: TRUE | CC63: Élément | CD63: sites/ServiceOM-AssetManagement/Lists/Exploitation Data Centrale
A64: 90189 | B64: HARAS DE LA MAJORIE / MANOHA | C64: DAVAI ENRSPV10 | D64: 45831 | E64: 1635 Rte de l'Heaume | F64: 07790 | G64: Saint-Alban-d'Ay | H64: BaC | I64: Toiture inclinée | J64: Agriculteur | K64: S21 | L64: BTA1134201 | BTA1134101 | M64: 9519200 | 9546050 | N64: 2 | O64: 50020191865012 | 50002391575340 | P64: 499.59 | Q64: 440 | R64: 416 | S64: 1186.2705 | T64: 592648.9 | U64: 0.054 | V64: 0.8773 | W64: 1188.33 | X64: BT | Y64: 45205 | Z64: 0.124 | AB64: FALSE | AC64: EDF OA | AD64: ENEDIS | AE64: 2193.922 | AF64: 45.19709 | AG64: 4.66906 | AH64: N°3 - Kyoto (SPV 10,13 &14) | AI64: Mot de passe onduleur : Exploitation2023 | AJ64: EIFFAGE | AK64: Christian MANOHA | AL64: christian.manoha@gmail.com | AN64: +33680611381 | AP64: KEVEL | AQ64: MOMSTEEL | AR64: FALSE | AV64: FALSE | AZ64: FALSE | BD64: Yasser BADREZZAMANE | BE64: Johan LAGARDE | BF64: Ibtissam ABSSI | BG64: Thibault RAHMOUNI | BH64: MTN-CONT-004-Contrat_EIFFAGE_maintenance_PV_BT-001 | BI64: DEV-CONT-SPV010-Contrat_DEV_EPC_DAVAI_ENR-1 | BJ64: EX-CONT-SPV010-Contrat_Suivi_O&M_Gestion_Actifs_DAVAI_ENR-1 | BK64: 856 | BL64: 254.74953 | BX64: Carrière équestre | CB64: FALSE | CC64: Élément | CD64: sites/ServiceOM-AssetManagement/Lists/Exploitation Data Centrale
A65: 61429 | B65: CARTERET | C65: DAVAI ENRSPV11 | D65: 45827 | E65: 490 chemin de Formahoun | F65: 81630 | G65: Salvagnac | H65: BaC | I65: Toiture inclinée | J65: Agriculteur | K65: S21 | L65: BTA1089259 | M65: 9028600 | N65: 1 | O65: 50081118261960 | P65: 263.9 | Q65: 220 | R65: 212.7 | S65: 1213 | T65: 320110.7 | U65: 0.054 | V65: 0.8729 | W65: 1200.67 | X65: BT | Y65: 45126 | Z65: 0.1274 | AB65: FALSE | AC65: EDF OA | AD65: ENEDIS | AE65: 1158.903 | AF65: 43.9335 | AG65: 1.70046 | AH65: N°3 - Fuji (SPV 11&15) | AI65: Mot de passe onduleur : Exploitation2023 | AJ65: EIFFAGE | AK65: Margaux CARTERET | AL65: margaux81@me.com | AN65: +33631264233 | AP65: KEVEL | AQ65: GIRAUD | AR65: FALSE | AV65: FALSE | AZ65: FALSE | BD65: Parfait MEZEME ONA | BE65: Jean-Paul THOROGOOD | BF65: Maxime DENIAU | BG65: Nicolas CADENE | BH65: MTN-CONT-004-Contrat_EIFFAGE_maintenance_PV_BT-001 | BI65: DEV-CONT-SPV011-Contrat_DEV_EPC_DAVAI_ENR-1 | BJ65: EX-CONT-SPV011-Contrat_Suivi_O&M_Gestion_Actifs_DAVAI_ENR-1 | BK65: 856 | BL65: 168.2513 | BX65: Manège + boxes à chevaux | CB65: FALSE | CC65: Élément | CD65: sites/ServiceOM-AssetManagement/Lists/Exploitation Data Centrale
A66: 94569 | B66: BOUILLET | C66: DAVAI ENRSPV13 | D66: 45826 | E66: Les Quatre Vents | F66: 03470 | G66: Saligny-sur-Roudon | H66: BE | I66: Toiture inclinée | J66: Agriculteur | K66: S21 | L66: BTA0945579 | | M66: 9039250 | 9045200 | N66: 2 | O66: 50063177518305 | 50084885188305 | P66: 499.59 | Q66: 470 | R66: 425.9 | S66: 1129.116 | T66: 564095.06 | U66: 0.054 | V66: 0.8664 | W66: 1130.6 | X66: BT | Y66: 44858 | Z66: 0.1311 | AB66: FALSE | AC66: EDF OA | AD66: ENEDIS | AE66: 2193.923 | AF66: 46.47118 | AG66: 3.7797 | AH66: N°3 - Kyoto (SPV 10,13 &14) | AI66: 2 Bâtiments Mot de passe onduleur : Exploitation2023 | AJ66: EIFFAGE | AK66: FABRICE BOUILLET | AL66: fabrice.bouillet70@gmail.com | AN66: +33676318305 | AP66: PROSUNFRANCE | AQ66: CANCE | AR66: FALSE | AV66: FALSE | AZ66: FALSE | BD66: Yasser BADREZZAMANE | BE66: Johan LAGARDE | BF66: Charbel BOUZERDAN | BG66: Sébastien GUYOUX | BH66: MTN-CONT-004-Contrat_EIFFAGE_maintenance_PV_BT-001 | BI66: DEV-CONT-SPV013-Contrat_DEV_EPC_DAVAI_ENR-1 | BJ66: EX-CONT-SPV013-Contrat_Suivi_OM_Gestion_Actifs_DAVAI -ENR-01 | BK66: 856 | BL66: 254.74953 | BR66: GFA des quatres vents | BS66: les Quatre vents | BT66: SALIGNY-SUR-ROUDON | BU66: 03470 | BV66: 415269844 | BX66: stockage de matériel et de fourrage | CB66: FALSE | CC66: Élément | CD66: sites/ServiceOM-AssetManagement/Lists/Exploitation Data Centrale
A67: 95992 | B67: RUDELLE | C67: DAVAI ENRSPV11 | D67: 45826 | E67: Crayssac | F67: 12120 | G67: Salmiech | H67: BaC | I67: Toiture inclinée | J67: Agriculteur | K67: S21 | L67: BTA1197755 | M67: 8922900 | N67: 1 | O67: 50018024096540 | P67: 309.4 | Q67: 250 | R67: 249.9 | S67: 1226 | T67: 379324.4 | U67: 0.054 | V67: 0.8762 | W67: 1223.6 | X67: BT | Y67: 44966 | Z67: 0.1312 | AB67: FALSE | AC67: EDF OA | AD67: ENEDIS | AE67: 1358.713 | AF67: 44.21679 | AG67: 2.63349 | AH67: N°3 - Fuji (SPV 11&15) | AI67: Mot de passe onduleur : Exploitation2023 | AJ67: EIFFAGE | AK67: Sebastien RUDELLE | AL67: rudelle.sebastien@gmail.com | AN67: +33676637183 | AP67: 3C INSTAL | AQ67: GIRAUD | AR67: FALSE | AV67: FALSE | AZ67: FALSE | BD67: Parfait MEZEME ONA | BE67: Jean-Paul THOROGOOD | BF67: Charbel BOUZERDAN | BG67: Nicolas CADENE | BH67: MTN-CONT-004-Contrat_EIFFAGE_maintenance_PV_BT-001 | BI67: DEV-CONT-SPV011-Contrat_DEV_EPC_DAVAI_ENR-1 | BJ67: EX-CONT-SPV011-Contrat_Suivi_O&M_Gestion_Actifs_DAVAI_ENR-1 | BK67: 856 | BL67: 184.9498 | BX67: stockage de matériel/foin et fourrage | CB67: FALSE | CC67: Élément | CD67: sites/ServiceOM-AssetManagement/Lists/Exploitation Data Centrale
A68: 97469 | B68: BLANC | C68: DAVAI ENRSPV13 | D68: 45825 | E68: Rte de Bellegarde | F68: 38270 | G68: Pact | H68: BaC | I68: Toiture inclinée | J68: Agriculteur | K68: S21 | L68: BTA1101288 | M68: 9241400 | N68: 1 | O68: 50010930770400 | P68: 318.5 | Q68: 250 | R68: 249 | S68: 1214 | T68: 386659 | U68: 0.054 | V68: 0.8705 | W68: 1210.03 | X68: BT | Y68: 45138 | Z68: 0.1274 | AB68: FALSE | AC68: EDF OA | AD68: ENEDIS | AE68: 1398.676 | AF68: 45.36296 | AG68: 4.97986 | AH68: N°3 - Kyoto (SPV 10,13 &14) | AI68: Mot de passe onduleur : Exploitation2023 | AJ68: EIFFAGE | AK68: Daniel BLANC | AL68: danydoo3839@gmail.com | AN68: +33677056678 | AP68: PROSUNFRANCE | AQ68: MOMSTEEL | AR68: FALSE | AV68: FALSE | AZ68: FALSE | BD68: Yasser BADREZZAMANE | BE68: Johan LAGARDE | BF68: Romain BESNARD | BG68: Thibault RAHMOUNI | BH68: MTN-CONT-004-Contrat_EIFFAGE_maintenance_PV_BT-001 | BI68: DEV-CONT-SPV013-Contrat_DEV_EPC_DAVAI_ENR-1 | BJ68: EX-CONT-SPV013-Contrat_Suivi_OM_Gestion_Actifs_DAVAI -ENR-01 | BK68: 856 | BL68: 188.2895 | BX68: Stockage matériel, stockage paille, foin et fourrage, céréales et produits phytosanitaires dans la limite de 50% | CB68: FALSE | CC68: Élément | CD68: sites/ServiceOM-AssetManagement/Lists/Exploitation Data Centrale
A69: 63567 | B69: QUINTARD | C69: DAVAI ENRSPV10 | D69: 45820 | E69: 13 Route du Petit Morlut | F69: 17800 | G69: Chadenac | H69: BaC | I69: Toiture inclinée | J69: Agriculteur | K69: S21 | L69: BTA1046861 | M69: 9336500 | N69: 1 | O69: 50016865500332 | P69: 227.045 | Q69: 220 | R69: 181 | S69: 1250 | T69: 283806.25 | U69: 0.054 | V69: 0.874 | W69: 1235.2 | X69: BT | Y69: 45044 | Z69: 0.1312 | AB69: FALSE | AC69: EDF OA | AD69: ENEDIS | AE69: 997.056 | AF69: 45.53069 | AG69: -0.437 | AH69: N°3 - Kyoto (SPV 10,13 &14) | AI69: Mot de passe onduleur : Exploitation2023 | AJ69: EIFFAGE | AK69: Thomas QUINTARD | AL69: thomas.cognacdufrolet@gmail.com | AN69: +33686151889 | AP69: PROSUNFRANCE | AQ69: GIRAUD | AR69: FALSE | AV69: FALSE | AZ69: FALSE | BD69: Parfait MEZEME ONA | BE69: Johan LAGARDE | BF69: Ibtissam ABSSI | BG69: Loïc GUILLEUX | BH69: MTN-CONT-004-Contrat_EIFFAGE_maintenance_PV_BT-001 | BI69: DEV-CONT-SPV010-Contrat_DEV_EPC_DAVAI_ENR-1 | BJ69: EX-CONT-SPV010-Contrat_Suivi_O&M_Gestion_Actifs_DAVAI_ENR-1 | BK69: 856 | BL69: 154.72552 | BR69: Bastien QUINTARD | BS69: 13 route du petit Morlut | BT69: CHADENAC | BU69: 17800 | BX69: Stockage de matériel | CB69: FALSE | CC69: Élément | CD69: sites/ServiceOM-AssetManagement/Lists/Exploitation Data Centrale
A70: 58966 | B70: TARROUX | C70: DAVAI ENRSPV8 | D70: 45819 | E70: RUE DE LA GARE LIEU-DIT LA PLAINE | F70: 82200 | G70: MALAUSE | H70: BE | I70: Toiture inclinée | J70: Industrie | K70: S21 | L70: BTA0996440 | M70: 8800200 | N70: 1 | O70: 50053914058709 | P70: 334.425 | Q70: 250 | R70: 214.7 | S70: 1120 | T70: 374556 | U70: 0.054 | V70: 0.851 | W70: 1101.6 | X70: BT | Y70: 44957 | Z70: 0.1312 | AB70: FALSE | AC70: EDF OA | AD70: ENEDIS | AE70: 1468.609 | AF70: 44.08957 | AG70: 0.97191 | AH70: N°2 - Finergreen - Construction 2023 | AI70: Mot de passe onduleur : Exploitation2023 Pour accéder au local onduleur, il faut demander les clés au propriétaire | AJ70: EIFFAGE | AK70: Stéphane TARROUX | AL70: stephanetarroux@ttprefa.fr | AN70: +33662075544 | AP70: ACROM | AQ70: SAMAPRO | AR70: TRUE | AS70: 46022 | AT70: 46022 | AU70: Fixe | AV70: FALSE | AX70: 3784 | AY70: Annuelle | AZ70: TRUE | BA70: fixe | BC70: 3784 | BD70: Parfait MEZEME ONA | BE70: Johan LAGARDE | BF70: Ibtissam ABSSI | BG70: Charlie BLAIZEAU | BH70: MTN-CONT-004-Contrat_EIFFAGE_maintenance_PV_BT-001 | BI70: DEV-CONT-SPV008-Contrat_DEV_EPC_DAVAI_ENR-1 | BJ70: EX-CONT-SPV008-Contrat_Suivi_O&M_Gestion_Actifs_DAVAI_ENR-1 | BK70: 856 | BL70: 187.83398 | BM70: 45843 | BN70: 45926 | BR70: SCI CAMAZO | BS70: 1924 ROUTE DE LA MEGERE | BT70: MOISSAC | BU70: 82200 | BX70: Produits béton | CB70: FALSE | CC70: Élément | CD70: sites/ServiceOM-AssetManagement/Lists/Exploitation Data Centrale
A71: 89744 | B71: FAURE | C71: DAVAI ENRSPV11 | D71: 45818 | E71: 19 Rte du Tort | F71: 17240 | G71: Saint-Sigismond-de-Clermont | H71: BaC | I71: Toiture inclinée | J71: Agriculteur | K71: S21 | L71: BTA1047656 | BTA1047405 | M71: 9356600 | 9389900 | N71: 2 | O71: 50024101385378 | 50078370562842 | P71: 378.56 | Q71: 330 | R71: 330 | S71: 1174.226 | T71: 444514.99 | U71: 0.054 | V71: 0.8699 | W71: 1124.59 | X71: BT | Y71: 45042 | Z71: 0.1313 | AB71: FALSE | AC71: EDF OA | AD71: ENEDIS | AE71: 1662.426 | AF71: 45.44663 | AG71: -0.54257 | AH71: N°3 - Fuji (SPV 11&15) | AI71: 3 Bâtiments Mot de passe onduleur : Exploitation2023 Mise en service PDL1 : 10/06/2025 Mise en service PDL2 : 02/07/2025 | AJ71: EIFFAGE | AK71: Thierry FAURE | AL71: faure.t@wanadoo.fr | AN71: +33681096647 | AP71: INNOVA | AQ71: CANCE | AR71: FALSE | AV71: FALSE | AZ71: FALSE | BD71: Parfait MEZEME ONA | BE71: Jean-Paul THOROGOOD | BF71: Nicolas PETROPAVLOVSKY | BG71: Loïc GUILLEUX | BH71: MTN-CONT-004-Contrat_EIFFAGE_maintenance_PV_BT-001 | BI71: DEV-CONT-SPV011-Contrat_DEV_EPC_DAVAI_ENR-1 | BJ71: EX-CONT-SPV011-Contrat_Suivi_O&M_Gestion_Actifs_DAVAI_ENR-1 | BK71: 856 | BL71: 210.33152 | BX71: Stockage | CB71: FALSE | CC71: Élément | CD71: sites/ServiceOM-AssetManagement/Lists/Exploitation Data Centrale
A72: 90034 | B72: SINAUD | C72: DAVAI ENRSPV11 | D72: 45812 | E72: LA DRABLE | F72: 23300 | G72: Saint-Priest-la-Feuille | H72: BaC | I72: Toiture inclinée | J72: Agriculteur | K72: S21 | L72: BTA1026867 | M72: 9135600 | N72: 1 | O72: 50003545946507 | P72: 218.4 | Q72: 150 | R72: 172.9 | S72: 1075 | T72: 234780 | U72: 0.054 | V72: 0.8783 | W72: 1103.57 | X72: BT | Y72: 45016 | Z72: 0.1312 | AB72: FALSE | AC72: EDF OA | AD72: ENEDIS | AE72: 959.092 | AF72: 46.23163 | AG72: 1.52775 | AH72: N°3 - Fuji (SPV 11&15) | AI72: Mot de passe onduleur : Exploitation2023 | AJ72: EIFFAGE | AK72: Frederic SINAUD | AL72: gaec.sinaud@orange.fr | AN72: +33689500942 | AP72: INNOVA | AQ72: CANCE | AR72: FALSE | AV72: FALSE | AZ72: FALSE | BD72: Parfait MEZEME ONA | BE72: Jean-Paul THOROGOOD | BF72: Maxime DENIAU | BG72: Alexandre COL | BH72: MTN-CONT-004-Contrat_EIFFAGE_maintenance_PV_BT-001 | BI72: DEV-CONT-SPV011-Contrat_DEV_EPC_DAVAI_ENR-1 | BJ72: EX-CONT-SPV011-Contrat_Suivi_O&M_Gestion_Actifs_DAVAI_ENR-1 | BK72: 856 | BL72: 151.5528 | BX72: Animaux : 60 % Fourrage paille : 25 % Couloir de circulation : 25 % | CB72: FALSE | CC72: Élément | CD72: sites/ServiceOM-AssetManagement/Lists/Exploitation Data Centrale
A73: 86550 | B73: SINAUD | C73: DAVAI ENRSPV11 | D73: 45812 | E73: 11 La Quaire | F73: 23240 | G73: Saint-Priest-la-Plaine | H73: BaC | I73: Toiture inclinée | J73: Agriculteur | K73: S21 | L73: BTA1048684 | BTA1048686 | M73: 9046450 | 9045850 | N73: 2 | O73: 50024535517011 | 50054781537102 | P73: 499.59 | Q73: 440 | R73: 416.6 | S73: 1081.35 | T73: 540231.65 | U73: 0.054 | V73: 0.8783 | W73: 1104.03 | X73: BT | Y73: 45042 | Z73: 0.1274 | AB73: FALSE | AC73: EDF OA | AD73: ENEDIS | AE73: 2193.923 | AF73: 46.2183 | AG73: 1.65147 | AH73: N°3 - Fuji (SPV 11&15) | AI73: RASaMot de passe onduleur : Exploitation2023 | AJ73: EIFFAGE | AK73: Frederic SINAUD | AL73: gaec.sinaud@orange.fr | AN73: +33689500942 | AP73: INNOVA | AQ73: MOMSTEEL | AR73: FALSE | AV73: FALSE | AZ73: FALSE | BD73: Parfait MEZEME ONA | BE73: Jean-Paul THOROGOOD | BF73: Maxime DENIAU | BG73: Alexandre COL | BH73: MTN-CONT-004-Contrat_EIFFAGE_maintenance_PV_BT-001 | BI73: DEV-CONT-SPV011-Contrat_DEV_EPC_DAVAI_ENR-1 | BJ73: EX-CONT-SPV011-Contrat_Suivi_O&M_Gestion_Actifs_DAVAI_ENR-1 | BK73: 856 | BL73: 254.74953 | BX73: Fourrage paille : 50 %, Matériel : 50 % | CB73: FALSE | CC73: Élément | CD73: sites/ServiceOM-AssetManagement/Lists/Exploitation Data Centrale
A74: 99917 | B74: THETE | C74: GIRASPV15 | D74: 45805 | E74: Vers la Fontaine | F74: 01480 | G74: Chaleins | H74: BaC | I74: Toiture inclinée | J74: Agriculteur | K74: S21 | L74: BTA1202492 | M74: 9263250 | N74: 1 | O74: 50001522051958 | P74: 277.095 | Q74: 250 | R74: 224 | S74: 1286 | T74: 356344.17 | U74: 0.054 | V74: 0.869 | W74: 1243.5 | X74: BT | Y74: 45315 | Z74: 0.1209 | AB74: FALSE | AC74: EDF OA | AD74: ENEDIS | AE74: 1216.848 | AF74: 46.02859 | AG74: 4.77295 | AH74: N°3 - Fuji (SPV 11&15) | AI74: Mot de passe onduleur : Exploitation2023 | AJ74: EIFFAGE | AK74: PHILIPPE THETE | AL74: cithete@laposte.net | AN74: +33608923480 | AP74: OFT | AQ74: RAVOYARD | AR74: FALSE | AV74: FALSE | AZ74: FALSE | BD74: Yasser BADREZZAMANE | BE74: Jean-Paul THOROGOOD | BF74: Romain BESNARD | BG74: Sébastien GUYOUX | BH74: MTN-CONT-004-Contrat_EIFFAGE_maintenance_PV_BT-001 | BI74: DEV-CONT-SPV015_Contrat_DEV_EPC_DAVAI_ENR-1 (signed) (1) | BJ74: EX-CONT-SPV015-Contrat_Suivi_OM_Gestion_Actifs_DAVAI -ENR-01 | BK74: 856 | BL74: 173.09386 | BX74: Stockage matériel + fourrage | CB74: FALSE | CC74: Élément | CD74: sites/ServiceOM-AssetManagement/Lists/Exploitation Data Centrale
A75: 89610 | B75: MOESSNER | C75: DAVAI ENRSPV11 | D75: 45804 | E75: Le Banquet Bas | F75: 12550 | G75: Plaisance | H75: BaC | I75: Toiture inclinée | J75: Agriculteur | K75: S21 | L75: 1079522 | M75: 8492500 | N75: 1 | O75: 50016285224763 | P75: 309.4 | Q75: 253 | R75: 250 | S75: 1195 | T75: 369733 | U75: 0.054 | V75: 0.8716 | W75: 1191 | X75: BT | Y75: 45114 | Z75: 0.1274 | AB75: FALSE | AC75: EDF OA | AD75: ENEDIS | AE75: 1358.7 | AF75: 43.91806 | AG75: 2.56148 | AH75: N°3 - Fuji (SPV 11&15) | AI75: RAS | AJ75: EIFFAGE | AK75: Karine Moessner | AL75: gaecdelacigogne@orange.fr | AN75: +33 6 74 52 69 75 | AO75: +33 4 75 64 99 99 | AP75: YAMA ENERGIES | AQ75: GIRAUD | AR75: FALSE | AV75: FALSE | AZ75: FALSE | BD75: Parfait MEZEME ONA | BE75: Jean-Paul THOROGOOD | BF75: Stéphane Vialettes | BG75: Nicolas CADENE | BH75: MTN-CONT-004-Contrat_EIFFAGE_maintenance_PV_BT-001 | BI75: DEV-CONT-SPV011-Contrat_DEV_EPC_DAVAI_ENR-1 | BJ75: EX-CONT-SPV011-Contrat_Suivi_O&M_Gestion_Actifs_DAVAI_ENR-1 | BK75: 856 | BL75: 184.9498 | BX75: stockage matériel et fourrage | CB75: FALSE | CC75: Élément | CD75: sites/ServiceOM-AssetManagement/Lists/Exploitation Data Centrale
A76: 89615 | B76: MOESSNER | C76: DAVAI ENRSPV11 | D76: 45804 | E76: Lieu-dit Le Banquet Bas | F76: 12550 | G76: Plaisance | H76: BE | I76: Toiture inclinée | J76: Agriculteur | K76: S21 | L76: 1079521 | M76: 8490000 | N76: 1 | O76: 50009049334789 | P76: 140.1 | Q76: 126.5 | R76: 117 | S76: 1200 | T76: 168120 | U76: 0.054 | V76: 0.8683 | W76: 1223.18 | X76: BT | Y76: 45114 | Z76: 0.1274 | AB76: FALSE | AC76: EDF OA | AD76: ENEDIS | AE76: 615.4 | AF76: 43.918843 | AG76: 2.56322 | AH76: N°3 - Fuji (SPV 11&15) | AI76: RAS | AJ76: EIFFAGE | AK76: Karine Moessner | AL76: gaecdelacigogne@orange.fr | AN76: +33 6 74 52 69 75 | AP76: YAMA ENERGIES | AQ76: PV READY | AR76: FALSE | AV76: FALSE | AZ76: FALSE | BD76: Yasser BADREZZAMANE | BE76: Jean-Paul THOROGOOD | BF76: Stéphane Vialettes | BG76: Nicolas CADENE | BH76: MTN-CONT-004-Contrat_EIFFAGE_maintenance_PV_BT-001 | BI76: DEV-CONT-SPV011-Contrat_DEV_EPC_DAVAI_ENR-1 | BJ76: EX-CONT-SPV011-Contrat_Suivi_O&M_Gestion_Actifs_DAVAI_ENR-1 | BK76: 856 | BL76: 122.8167 | BX76: stockage de matériel/d'engrais/céréales/Foin et fourrage | CB76: FALSE | CC76: Élément | CD76: sites/ServiceOM-AssetManagement/Lists/Exploitation Data Centrale
A77: 95918 | B77: CASTET | C77: DAVAI ENRSPV9 | D77: 45803 | E77: 11, Carrère de la Goutille | F77: 31160 | G77: Estadens | H77: BaC | I77: Toiture inclinée | J77: Agriculteur | K77: S21 | L77: BTA1115759 | M77: 9096200 | N77: 1 | O77: 50062305094972 | P77: 309.4 | Q77: 253 | R77: 249 | S77: 1130 | T77: 349622 | U77: 0.054 | V77: 0.841 | W77: 1110.2 | X77: BT | Y77: 45170 | Z77: 0.1238 | AB77: FALSE | AC77: EDF OA | AD77: ENEDIS | AE77: 1358.7 | AF77: 43.043825 | AG77: 0.859333 | AH77: N°2 - Finergreen - Construction 2023 | AI77: RAS | AJ77: EIFFAGE | AK77: Frédéric Castet | AL77: castet45@sfr.fr | AN77: 06 84 07 75 94 | AP77: KEVEL | AQ77: METAL R | AR77: FALSE | AV77: FALSE | AZ77: FALSE | BD77: Yasser BADREZZAMANE | BE77: Victor PONTAIS | BF77: Gwendal HART | BG77: Nicolas CADENE | BH77: MTN-CONT-004-Contrat_EIFFAGE_maintenance_PV_BT-001 | BI77: DEV-CONT-SPV009-Contrat_DEV_EPC_DAVAI_ENR-1 | BJ77: EX-CONT-SPV009-Contrat_Suivi_O&M_Gestion_Actifs_DAVAI_ENR-1 | BK77: 856 | BL77: 178.6498 | BM77: 45924 | BN77: 45926 | BR77: Frédéric Yannick CASTET | BS77: 11 Carrère de la Goutille | BT77: Estadens | BU77: 31160 | BX77: Stockage de matériel agricole + fourrage + stabulation | CB77: FALSE | CC77: Élément | CD77: sites/ServiceOM-AssetManagement/Lists/Exploitation Data Centrale
A78: 95919 | B78: CASTET | C78: DAVAI ENRSPV13 | D78: 45803 | E78: 11 Carrère de la Goutille | F78: 31160 | G78: Estadens | H78: BE | I78: Toiture inclinée | J78: Agriculteur | K78: S21 | L78: BTA1116013 | M78: 9094700 | N78: 1 | O78: 50004417974932 | P78: 268.65 | Q78: 253 | R78: 231 | S78: 1162 | T78: 312171.3 | U78: 0.054 | V78: 0.8737 | W78: 1145.01 | X78: BT | Y78: 45170 | Z78: 0.1238 | AB78: FALSE | AC78: EDF OA | AD78: ENEDIS | AE78: 1258.8 | AF78: 43.043896 | AG78: 0.859961 | AH78: N°3 - Kyoto (SPV 10,13 &14) | AI78: RAS | AJ78: EIFFAGE | AK78: Frédéric Yannick CASTET | AL78: castet45@sfr.fr | AN78: 06 84 07 75 94 | AP78: NEOXOM | AQ78: METAL R | AR78: TRUE | AS78: 46022 | AT78: 46022 | AU78: Fixe | AV78: FALSE | AX78: 7300 | AY78: Annuelle | AZ78: TRUE | BA78: fixe | BC78: 7300 | BD78: Yasser BADREZZAMANE | BE78: Johan LAGARDE | BF78: Gwendal HART | BG78: Nicolas CADENE | BH78: MTN-CONT-004-Contrat_EIFFAGE_maintenance_PV_BT-001 | BI78: DEV-CONT-SPV013-Contrat_DEV_EPC_DAVAI_ENR-1 | BJ78: EX-CONT-SPV013-Contrat_Suivi_OM_Gestion_Actifs_DAVAI -ENR-01 | BK78: 856 | BL78: 169.99455 | BR78: Frédéric Yannick CASTET | BS78: 11 carrere de la goutille | BT78: Estadens | BU78: 31160 | BX78: Stabulation | CB78: FALSE | CC78: Élément | CD78: sites/ServiceOM-AssetManagement/Lists/Exploitation Data Centrale
A79: 97180 | B79: MARKEY | C79: DAVAI ENRSPV11 | D79: 45803 | E79: Av. de Provence | F79: 04220 | G79: Sainte-Tulle | H79: BE | I79: Toiture inclinée | J79: Agriculteur | K79: S21 | L79: 1042667 | M79: 9271800 | N79: 1 | O79: 50010063032062 | P79: 177.9 | Q79: 165 | R79: 149 | S79: 1374 | T79: 244434.6 | U79: 0.054 | V79: 0.8613 | W79: 1366.17 | X79: BT | Y79: 45040 | Z79: 0.1312 | AB79: FALSE | AC79: EDF OA | AD79: ENEDIS | AE79: 781.26 | AF79: 43.79806 | AG79: 5.78372 | AH79: N°3 - Fuji (SPV 11&15) | AI79: RAS | AJ79: EIFFAGE | AK79: Amaury MARKEY | AL79: markey.p@orange.fr | AN79: +33 6 07 15 17 55 | AP79: KEVEL | AQ79: PV READY | AR79: FALSE | AV79: FALSE | AZ79: FALSE | BD79: Yasser BADREZZAMANE | BE79: Jean-Paul THOROGOOD | BF79: Sophie ROGIER | BG79: Thibault RAHMOUNI | BH79: MTN-CONT-004-Contrat_EIFFAGE_maintenance_PV_BT-001 | BI79: DEV-CONT-SPV011-Contrat_DEV_EPC_DAVAI_ENR-1 | BJ79: EX-CONT-SPV011-Contrat_Suivi_O&M_Gestion_Actifs_DAVAI_ENR-1 | BK79: 856 | BL79: 136.6893 | BX79: Entrepôt stockage de vins | CB79: FALSE | CC79: Élément | CD79: sites/ServiceOM-AssetManagement/Lists/Exploitation Data Centrale
A80: 99373 | B80: CLEMENT | C80: GIRASPV15 | D80: 45800 | E80: Gazailles | F80: 31160 | G80: Estadens | H80: BaC | I80: Toiture inclinée | J80: Agriculteur | K80: S21 | L80: BTA1202706 | M80: 9042900 | N80: 1 | O80: 50064764471298 | P80: 331.24 | Q80: 250 | R80: 249 | S80: 1150 | T80: 380926 | U80: 0.054 | V80: 0.878 | W80: 1212.6 | X80: BT | Y80: 45315 | Z80: 0.1208 | AB80: FALSE | AC80: EDF OA | AD80: ENEDIS | AE80: 1454.623 | AF80: 43.04786 | AG80: 0.85301 | AH80: N°3 - Fuji (SPV 11&15) | AI80: Mot de passe onduleur : Exploitation2023 | AJ80: EIFFAGE | AK80: Yannick CLEMENT | AL80: clement.yannick31@gmail.com | AN80: +33610332718 | AP80: KEVEL | AQ80: GIRAUD | AR80: FALSE | AV80: FALSE | AZ80: FALSE | BD80: Parfait MEZEME ONA | BE80: Jean-Paul THOROGOOD | BF80: Gwendal HART | BG80: Nicolas CADENE | BH80: MTN-CONT-004-Contrat_EIFFAGE_maintenance_PV_BT-001 | BI80: DEV-CONT-SPV015_Contrat_DEV_EPC_DAVAI_ENR-1 (signed) (1) | BJ80: EX-CONT-SPV015-Contrat_Suivi_OM_Gestion_Actifs_DAVAI -ENR-01 | BK80: 856 | BL80: 192.96508 | BX80: Stabulation, fourrage (+ matériel plus tard peut - être) | CB80: FALSE | CC80: Élément | CD80: sites/ServiceOM-AssetManagement/Lists/Exploitation Data Centrale
A81: 90361 | B81: MALTAVERNE | C81: DAVAI ENRSPV10 | D81: 45799 | E81: Rte de Chard | F81: 71320 | G81: Sainte-Radegonde | H81: BaC | I81: Toiture inclinée | J81: Agriculteur | K81: S21 | L81: BTA1016812 | M81: 9175250 | N81: 1 | O81: 50063176138379 | P81: 218.855 | Q81: 250 | R81: 164.3 | S81: 1051 | T81: 230016.61 | U81: 0.054 | V81: 0.8696 | W81: 1096.97 | X81: BT | Y81: 45000 | Z81: 0.1312 | AB81: FALSE | AC81: EDF OA | AD81: ENEDIS | AE81: 961.09 | AF81: 46.6938 | AG81: 4.10361 | AH81: N°3 - Kyoto (SPV 10,13 &14) | AI81: 2 Bâtiments Mot de passe onduleur : Exploiation2023 | AJ81: EIFFAGE | AK81: Serge MALTAVERNE | AL81: maltaverne71320@gmail.com | AN81: +33748122092 | AP81: PROSUNFRANCE | AQ81: PROSUNFRANCE | AR81: FALSE | AV81: FALSE | AZ81: FALSE | BD81: Yasser BADREZZAMANE | BE81: Johan LAGARDE | BF81: Nicolas PETROPAVLOVSKY | BG81: Sébastien GUYOUX | BH81: MTN-CONT-004-Contrat_EIFFAGE_maintenance_PV_BT-001 | BI81: DEV-CONT-SPV010-Contrat_DEV_EPC_DAVAI_ENR-1 | BJ81: EX-CONT-SPV010-Contrat_Suivi_O&M_Gestion_Actifs_DAVAI_ENR-1 | BK81: 856 | BL81: 151.71979 | BX81: Stabulation et stockage de matériel | CB81: FALSE | CC81: Élément | CD81: sites/ServiceOM-AssetManagement/Lists/Exploitation Data Centrale
A82: 33559 | B82: CARRERE | C82: DAVAI ENRSPV7 | D82: 45793 | E82: 32 chemin de marjeau | F82: 47600 | G82: Montagnac-sur-Auvignon | H82: BaC | I82: Toiture inclinée | J82: Agriculteur | K82: S21 | L82: BTA0998687 | BTA0998690 | M82: 7887550 | 7897650 | N82: 2 | O82: 50078659800673 | 50064188020640 | P82: 278.005 | Q82: 275 | R82: 243 | S82: 1119.0791 | T82: 311109.6 | U82: 0.054 | V82: 0.852 | W82: 1267.8 | X82: BT | Y82: 44963 | Z82: 0.1312 | AB82: FALSE | AC82: EDF OA | AD82: ENEDIS | AE82: 1220.844 | AF82: 44.14804 | AG82: 0.44966 | AH82: N°2 - Finergreen - Construction 2023 | AI82: 2 Bâtiments Mot de passe onduleur : Exploiation2023 | AJ82: EIFFAGE | AK82: Christophe CARRERE | AL82: christophe-carrere@orange.fr | AN82: +33607115337 | AP82: ACROM | AQ82: CANCE | AR82: FALSE | AV82: FALSE | AZ82: FALSE | BD82: Parfait MEZEME ONA | BE82: Johan LAGARDE | BF82: Romain BESNARD | BG82: Charlie BLAIZEAU | BH82: MTN-CONT-004-Contrat_EIFFAGE_maintenance_PV_BT-001 | BI82: DEV-CONT-SPV007-Contrat_DEV_EPC_DAVAI_ENR-1 | BJ82: EX-CONT-SPV007-Contrat_Suivi_O&M_Gestion_Actifs_DAVAI_ENR-1 | BK82: 856 | BL82: 167.12784 | BM82: 45915 | BN82: 45926 | BX82: Stockage matériel, céréales, paille, foin limité à 50% de la surface au sol du bâtiment | CB82: FALSE | CC82: Élément | CD82: sites/ServiceOM-AssetManagement/Lists/Exploitation Data Centrale
A83: 27429 | B83: LARRAT | C83: DAVAI ENRSPV6 | D83: 45792 | E83: Lieudit Les Clos | F83: 63500 | G83: Perrier | H83: BaC | I83: Toiture inclinée | J83: Agriculteur | K83: S21 | L83: BTA0912461 | M83: 6274050 | N83: 1 | O83: 50069835867765 | P83: 301 | Q83: 250 | R83: 249.9 | S83: 1136 | T83: 341936 | U83: 0.054 | V83: 0.863 | W83: 1113.1 | X83: BT | Y83: 44708 | Z83: 0.1312 | AB83: FALSE | AC83: EDF OA | AD83: ENEDIS | AE83: 1362.102 | AF83: 45.54768 | AG83: 3.18646 | AH83: N°2 - Finergreen - Construction 2023 | AI83: Mot de passe onduleur : Exploitation2023 | AJ83: EIFFAGE | AK83: Guy LARRAT | AL83: guylarrat@wanadoo.fr | AN83: +33683148255 | AP83: PROSUNFRANCE | AQ83: CANCE | AR83: FALSE | AV83: FALSE | AZ83: FALSE | BD83: Yasser BADREZZAMANE | BE83: Jean-Paul THOROGOOD | BF83: Maxime DENIAU | BG83: Sébastien GUYOUX | BH83: MTN-CONT-004-Contrat_EIFFAGE_maintenance_PV_BT-001 | BI83: DEV-CONT-SPV006-Contrat_DEV_EPC_DAVAI_ENR-1 | BJ83: EX-CONT-SPV006-Contrat_Suivi_O&M_Gestion_Actifs_DAVAI_ENR-1 | BK83: 856 | BL83: 175.567 | BM83: 45809 | BN83: 45824 | BX83: Stockage de matériel, céréales, paille, foin et fourrage | CB83: FALSE | CC83: Élément | CD83: sites/ServiceOM-AssetManagement/Lists/Exploitation Data Centrale
A84: 66418 | B84: GAEC JOURCY 42 | C84: DAVAI ENRSPV11 | D84: 45791 | E84: 460 Chem. de Jourcy | F84: 42470 | G84: Saint-Symphorien-de-Lay | H84: BaC | I84: Toiture inclinée | J84: Agriculteur | K84: S21 | L84: BTA1092953 | BTA1092954 | M84: 8820850 | 8821450 | N84: 2 | O84: 50073449140237 | 50032494001586 | P84: 499.59 | Q84: 440 | R84: 416.6 | S84: 1136.487 | T84: 567777.54 | U84: 0.054 | V84: 0.8751 | W84: 1136.37 | X84: BT | Y84: 45120 | Z84: 0.1274 | AA84: TRUE | AB84: FALSE | AC84: EDF OA | AD84: ENEDIS | AE84: 2193.922 | AF84: 45.94016 | AG84: 4.22738 | AH84: N°3 - Fuji (SPV 11&15) | AI84: Mot de passe onduleur : Exploitation2023 | AJ84: EIFFAGE | AK84: Pierre Marie COLOMBAT | AL84: gaec.dejourcy@42.sideral.fr | AN84: +33616443944 | AP84: PROSUNFRANCE | AQ84: MOMSTEEL | AR84: FALSE | AV84: FALSE | AZ84: FALSE | BD84: Yasser BADREZZAMANE | BE84: Jean-Paul THOROGOOD | BF84: Ibtissam ABSSI | BG84: Alexandre COL | BH84: MTN-CONT-004-Contrat_EIFFAGE_maintenance_PV_BT-001 | BI84: DEV-CONT-SPV011-Contrat_DEV_EPC_DAVAI_ENR-1 | BJ84: EX-CONT-SPV011-Contrat_Suivi_O&M_Gestion_Actifs_DAVAI_ENR-1 | BK84: 856 | BL84: 254.74953 | BX84: Stabulation + stockage de paille, foin et fourrage | CB84: FALSE | CC84: Élément | CD84: sites/ServiceOM-AssetManagement/Lists/Exploitation Data Centrale
A85: 58166 | B85: GAYET 42 | C85: DAVAI ENRSPV10 | D85: 45790 | E85: 419 Chemin des Seigles | F85: 42210 | G85: Craintilleux | H85: BaC | I85: Toiture inclinée | J85: Agriculteur | K85: S21 | L85: BTA1085800 | M85: 9261950 | N85: 1 | O85: 50043203170116 | P85: 309.4 | Q85: 250 | R85: 249.9 | S85: 1145 | T85: 354263 | U85: 0.054 | V85: 0.8754 | W85: 1167.83 | X85: BT | Y85: 45118 | Z85: 0.1274 | AB85: FALSE | AC85: EDF OA | AD85: ENEDIS | AE85: 1358.713 | AF85: 45.57895 | AG85: 4.21851 | AH85: N°3 - Kyoto (SPV 10,13 &14) | AI85: Mot de passe onduleur : Exploitation2023 | AJ85: EIFFAGE | AK85: Julie GAYET | AL85: gayet.blanchard@orange.fr | AN85: +33664743675 | AP85: 3C INSTAL | AQ85: MOMSTEEL | AR85: FALSE | AV85: FALSE | AZ85: FALSE | BD85: Yasser BADREZZAMANE | BE85: Johan LAGARDE | BF85: Nicolas PETROPAVLOVSKY | BG85: Alexandre COL | BH85: MTN-CONT-004-Contrat_EIFFAGE_maintenance_PV_BT-001 | BI85: DEV-CONT-SPV010-Contrat_DEV_EPC_DAVAI_ENR-1 | BJ85: EX-CONT-SPV010-Contrat_Suivi_O&M_Gestion_Actifs_DAVAI_ENR-1 | BK85: 856 | BL85: 184.9498 | BM85: 45806 | BX85: stockage de matériel, paille, foin et fourrage. | CB85: FALSE | CC85: Élément | CD85: sites/ServiceOM-AssetManagement/Lists/Exploitation Data Centrale
A86: 3292 | B86: TALLET | C86: DAVAI ENRSPV6 | D86: 45790 | E86: ZA du Maine | F86: 24270 | G86: Angoisse | H86: BaC | I86: Toiture inclinée | J86: Tertiaire | K86: S21 | L86: BTA1199293 | M86: 8896350 | N86: 1 | O86: 50014690361878 | P86: 238.875 | Q86: 220 | R86: 193 | S86: 1253 | T86: 299310.38 | U86: 0.054 | V86: 0.79189944 | W86: 1134 | X86: BT | Y86: 45314 | Z86: 0.1208 | AA86: TRUE | AB86: FALSE | AC86: EDF OA | AD86: ENEDIS | AE86: 1049.007 | AF86: 45.40966 | AG86: 1.14797 | AH86: N°2 - Finergreen - Construction 2023 | AI86: Mot de passe onduleur : Exploitation2023 | AJ86: EIFFAGE | AK86: Thierry TALLET | AL86: thierry.tallet1981@gmail.com | AN86: +33670028138 | AP86: ACROM | AQ86: MOMSTEEL | AR86: FALSE | AV86: FALSE | AZ86: FALSE | BD86: Parfait MEZEME ONA | BE86: Jean-Paul THOROGOOD | BF86: Gwendal HART | BG86: Charlie BLAIZEAU | BH86: MTN-CONT-004-Contrat_EIFFAGE_maintenance_PV_BT-001 | BI86: DEV-CONT-SPV006-Contrat_DEV_EPC_DAVAI_ENR-1 | BJ86: EX-CONT-SPV006-Contrat_Suivi_O&M_Gestion_Actifs_DAVAI_ENR-1 | BK86: 856 | BL86: 152.76712 | BM86: 45806 | BN86: 45926 | BR86: SAS MANALY | BS86: Zone d'activités du Maine | BT86: Angoisse | BU86: 24270 | BV86: 920645231 | BX86: Stockage matériaux construction | CB86: FALSE | CC86: Élément | CD86: sites/ServiceOM-AssetManagement/Lists/Exploitation Data Centrale
A87: 97374 | B87: OZIOL | C87: DAVAI ENRSPV10 | D87: 45789 | E87: Coustas | F87: 82190 | G87: Touffailles | H87: BE | I87: Toiture inclinée | J87: Agriculteur | K87: S21 | L87: BTA1020759 | M87: 8821250 | N87: 1 | O87: 50028877479005 | P87: 159.705 | Q87: 125 | R87: 112.4 | S87: 1109 | T87: 177112.85 | U87: 0.054 | V87: 0.8706 | W87: 1163.89 | X87: BT | Y87: 45016 | Z87: 0.1312 | AB87: FALSE | AC87: EDF OA | AD87: ENEDIS | AE87: 701.336 | AF87: 44.25616 | AG87: 1.03909 | AH87: N°3 - Kyoto (SPV 10,13 &14) | AI87: Mot de passe onduleur : Exploitation2023 | AJ87: EIFFAGE | AK87: Philippe OZIOL | AL87: patrick3182@hotmail.fr | AN87: +33688117525 | AP87: ACROM | AQ87: ACC | AR87: TRUE | AS87: 46022 | AT87: 46022 | AU87: Fixe | AV87: TRUE | AX87: 5160 | AY87: Annuelle | AZ87: TRUE | BA87: fixe | BC87: 5160 | BD87: Parfait MEZEME ONA | BE87: Johan LAGARDE | BF87: Gwendal HART | BG87: Charlie BLAIZEAU | BH87: MTN-CONT-004-Contrat_EIFFAGE_maintenance_PV_BT-001 | BI87: DEV-CONT-SPV010-Contrat_DEV_EPC_DAVAI_ENR-1 | BJ87: EX-CONT-SPV010-Contrat_Suivi_O&M_Gestion_Actifs_DAVAI_ENR-1 | BK87: 856 | BL87: 130.01173 | BR87: Philippe Stéphane OZIOL | BS87: 70, impasse de Coustas | BT87: TOUFFAILLES | BU87: 82190 | BX87: Stockage de matériel et fourrage | CB87: FALSE | CC87: Élément | CD87: sites/ServiceOM-AssetManagement/Lists/Exploitation Data Centrale
A88: 95190 | B88: BALAVOINE | C88: DAVAI ENRSPV10 | D88: 45786 | E88: A Courtiade | F88: 32500 | G88: Fleurance | H88: BaC | I88: Toiture inclinée | J88: Agriculteur | K88: S21 | L88: BTA1049231 | BTA1049413 | M88: 9158700 | 9158350 | N88: 2 | O88: 50024244719249 | 50031480609223 | P88: 499.59 | Q88: 440 | R88: 410.4 | S88: 1050.41 | T88: 524774.33 | U88: 0.054 | V88: 0.8713 | W88: 1261.54 | X88: BT | Y88: 45043 | Z88: 0.1312 | AB88: FALSE | AC88: EDF OA | AD88: ENEDIS | AE88: 2193.923 | AF88: 43.82165 | AG88: 0.66652 | AH88: N°3 - Kyoto (SPV 10,13 &14) | AI88: RAS | AJ88: EIFFAGE | AK88: Denis BALAVOINE | AL88: d.e.b.negoce@gmail.com | AN88: 0607158226 | AP88: ACROM | AQ88: GIRAUD | AR88: FALSE | AV88: FALSE | AZ88: FALSE | BD88: Parfait MEZEME ONA | BE88: Johan LAGARDE | BF88: Gwendal HART | BG88: Charlie BLAIZEAU | BH88: MTN-CONT-004-Contrat_EIFFAGE_maintenance_PV_BT-001 | BI88: DEV-CONT-SPV010-Contrat_DEV_EPC_DAVAI_ENR-1 | BJ88: EX-CONT-SPV010-Contrat_Suivi_O&M_Gestion_Actifs_DAVAI_ENR-1 | BK88: 856 | BL88: 254.74953 | BR88: Denis Balavoine | BS88: 75 avenue de la Cote d'argent | BT88: Fleurance | BU88: 32500 | BX88: Stockage matériel (20%), stockage fourrage et produits finis (40%), Transformation (40%) | CB88: FALSE | CC88: Élément | CD88: sites/ServiceOM-AssetManagement/Lists/Exploitation Data Centrale
A89: 58178 | B89: VERZEILLE | C89: DAVAI ENRSPV13 | D89: 45786 | E89: 1 All. de la Condamine | F89: 11250 | G89: VERZEILLE | H89: BaC | I89: Toiture inclinée | J89: Collectivités | K89: S21 | L89: BTA1199195 | M89: 9258700 | N89: 1 | O89: 50096022393692 | P89: 328 | Q89: 249 | R89: 249 | S89: 1192 | T89: 390976 | U89: 0.054 | V89: 0.8636 | W89: 1214.61 | X89: BT | Y89: 45313 | Z89: 0.1209 | AB89: FALSE | AC89: EDF OA | AD89: ENEDIS | AE89: 1439 | AF89: 43.124 | AG89: 2.32231 | AH89: N°3 - Kyoto (SPV 10,13 &14) | AI89: Vis onduleur dans le sachet sur la portière du schelter | AJ89: EIFFAGE | AK89: Commune De Verzeille | AL89: mairiedeverzeille@outlook.fr | AN89: 04 68 69 41 71 | AP89: YAMA ENERGIES | AQ89: N/C | AR89: TRUE | AS89: 45657 | AT89: 46022 | AU89: Fixe | AV89: FALSE | AX89: 4500 | AY89: Annuelle | AZ89: TRUE | BA89: fixe | BC89: 4500 | BD89: Parfait MEZEME ONA | BE89: Johan LAGARDE | BF89: Maxime DENIAU | BG89: Vincent KEZADRI | BH89: MTN-CONT-004-Contrat_EIFFAGE_maintenance_PV_BT-001 | BI89: DEV-CONT-SPV013-Contrat_DEV_EPC_DAVAI_ENR-1 | BJ89: EX-CONT-SPV013-Contrat_Suivi_OM_Gestion_Actifs_DAVAI -ENR-01 | BK89: 856 | BL89: 191.776 | BM89: 45786 | BX89: Halle multi-activités sportives | CB89: TRUE | CC89: Élément | CD89: sites/ServiceOM-AssetManagement/Lists/Exploitation Data Centrale
A90: 83705 | B90: AZEMAR | C90: DAVAI ENRSPV13 | D90: 45783 | E90: Impasse de la Bouffie | F90: 12160 | G90: CAMBOULAZET | H90: BaC | I90: Toiture inclinée | J90: Agriculteur | K90: S21 | L90: BTA0955373 | M90: 9049150 | N90: 1 | O90: 50003262828779 | P90: 319 | Q90: 253 | R90: 249 | S90: 1228 | T90: 391732 | U90: 0.054 | V90: 0.869 | W90: 1212.2 | X90: BT | Y90: 44854 | Z90: 0.1312 | AB90: FALSE | AC90: EDF OA | AD90: ENEDIS | AE90: 1403 | AF90: 44.25786 | AG90: 2.45787 | AH90: N°3 - Kyoto (SPV 10,13 &14) | AI90: RAS | AJ90: EIFFAGE | AK90: Valentin AZEMAR | AL90: azemdu12@orange.fr | AN90: +33 6 78 52 91 23 | AO90: +33 5 55 66 22 80 | AP90: 3C INSTAL | AQ90: CANCE | AR90: FALSE | AV90: FALSE | AZ90: FALSE | BD90: Parfait MEZEME ONA | BE90: Johan LAGARDE | BF90: Charbel BOUZERDAN | BG90: Nicolas CADENE | BH90: MTN-CONT-004-Contrat_EIFFAGE_maintenance_PV_BT-001 | BI90: DEV-CONT-SPV013-Contrat_DEV_EPC_DAVAI_ENR-1 | BJ90: EX-CONT-SPV013-Contrat_Suivi_OM_Gestion_Actifs_DAVAI -ENR-01 | BK90: 856 | BL90: 188.473 | BQ90: 7578.67 | BR90: Valentin Azemar | BS90: Lacombe | BT90: Camboulazet | BU90: 12160 | BX90: Agriculture | CB90: FALSE | CC90: Élément | CD90: sites/ServiceOM-AssetManagement/Lists/Exploitation Data Centrale
A91: 95683 | B91: DUMON | C91: DAVAI ENRSPV9 | D91: 45783 | E91: 2 Le Montimbert | F91: 23240 | G91: Saint-Priest-la-Plaine | H91: BE | I91: Toiture inclinée | J91: Agriculteur | K91: S21 | L91: BTA1001839 | BTA1001817 | M91: 8674400 | 8880100 | N91: 2 | O91: 50018458193298 | 50025694083285 | P91: 353.99 | Q91: 330 | R91: 284.9 | S91: 1111 | T91: 393282.89 | U91: 0.054 | V91: 0.863 | W91: 1081.7 | X91: BT | Y91: 44977 | Z91: 0.1312 | AB91: FALSE | AC91: EDF OA | AD91: ENEDIS | AE91: 1554 | AF91: 46.19822 | AG91: 1.66066 | AH91: N°2 - Finergreen - Construction 2023 | AI91: RAS | AJ91: EIFFAGE | AK91: Emmanuel DUMON | AL91: emmanueldumon68@gmail.com | AN91: +33602720021 | AP91: NEOXOM | AQ91: METAL R | AR91: TRUE | AS91: 46022 | AT91: 46022 | AU91: En une fois | AV91: FALSE | AX91: 1200 | AZ91: FALSE | BD91: Parfait MEZEME ONA | BE91: Victor PONTAIS | BF91: Charbel BOUZERDAN | BG91: Loïc GUILLEUX | BH91: MTN-CONT-004-Contrat_EIFFAGE_maintenance_PV_BT-001 | BI91: DEV-CONT-SPV009-Contrat_DEV_EPC_DAVAI_ENR-1 | BJ91: EX-CONT-SPV009-Contrat_Suivi_O&M_Gestion_Actifs_DAVAI_ENR-1 | BK91: 856 | BL91: 195.01433 | BM91: 45799 | BN91: 45826 | BR91: Emmanuel Claude DUMON | BS91: 2 B le Montimbert | BT91: SAINT-PRIEST-LA-PLAINE | BU91: 23240 | BX91: RAS | CB91: FALSE | CC91: Élément | CD91: sites/ServiceOM-AssetManagement/Lists/Exploitation Data Centrale
A92: 49018 | B92: SOARES | C92: DAVAI ENRSPV8 | D92: 45782 | E92: Les Montaux | F92: 26110 | G92: Bésignan | H92: BaC | I92: Toiture inclinée | J92: Agriculteur | K92: S21 | L92: BTA1110752 | M92: 8885900 | N92: 1 | O92: 50028007235629 | P92: 222.5 | Q92: 165 | R92: 190.7 | S92: 1310 | T92: 291475 | U92: 0.033 | V92: 0.838 | W92: 1289.3 | X92: BT | Y92: 45161 | Z92: 0.1238 | AB92: FALSE | AC92: EDF OA | AD92: ENEDIS | AE92: 989.44 | AF92: 44.32126 | AG92: 5.3118 | AH92: N°2 - Finergreen - Construction 2023 | AI92: RAS | AJ92: EIFFAGE | AK92: Fernandes SOARES | AL92: msfexploitation@yahoo.fr | AM92: mairiedebesignan@orange.fr | AN92: 0670886646 | AO92: 0630203118 | AP92: KEVEL | AQ92: GIRAUD | AR92: FALSE | AV92: FALSE | AZ92: FALSE | BD92: Yasser BADREZZAMANE | BE92: Johan LAGARDE | BF92: Ibtissam ABSSI | BG92: Thibault RAHMOUNI | BH92: MTN-CONT-004-Contrat_EIFFAGE_maintenance_PV_BT-001 | BI92: DEV-CONT-SPV008-Contrat_DEV_EPC_DAVAI_ENR-1 | BJ92: EX-CONT-SPV008-Contrat_Suivi_O&M_Gestion_Actifs_DAVAI_ENR-1 | BK92: 856 | BL92: 146.7575 | BM92: 45798 | BN92: 45800 | BR92: Eliane MERINDOL et Mickael SOARES | BS92: Lieudit les Granges | BT92: Bézignan | BU92: 26110 | BX92: Stockage matériel et foin | CB92: FALSE | CC92: Élément | CD92: sites/ServiceOM-AssetManagement/Lists/Exploitation Data Centrale
A93: 96017 | B93: LAPRADE REBEIX | C93: DAVAI ENRSPV13 | D93: 45777 | E93: 2 Le Bois Neuf | F93: 23210 | G93: Marsac | H93: BE | I93: Toiture inclinée | J93: Agriculteur | K93: S21 | L93: BTA1046549 | M93: 9080250 | N93: 1 | O93: 50058538633548 | P93: 232.05 | Q93: 250 | R93: 205.7 | S93: 1130 | T93: 262216.5 | U93: 0.054 | V93: 0.8786 | W93: 1133.63 | X93: BT | Y93: 45044 | Z93: 0.1313 | AB93: FALSE | AC93: EDF OA | AD93: ENEDIS | AE93: 1019.035 | AF93: 46.11992 | AG93: 1.588 | AH93: N°3 - Kyoto (SPV 10,13 &14) | AI93: Mot de passe onduleur : Exploitation2023 | AJ93: EIFFAGE | AK93: Michel REBEIX | AL93: michel.rebeix1@orange.fr | AN93: +33607695838 | AP93: HBBAT | AQ93: HBBAT | AR93: FALSE | AV93: FALSE | AZ93: FALSE | BD93: Parfait MEZEME ONA | BE93: Johan LAGARDE | BF93: Maxime DENIAU | BG93: Alexandre COL | BH93: MTN-CONT-004-Contrat_EIFFAGE_maintenance_PV_BT-001 | BI93: DEV-CONT-SPV013-Contrat_DEV_EPC_DAVAI_ENR-1 | BJ93: EX-CONT-SPV013-Contrat_Suivi_OM_Gestion_Actifs_DAVAI -ENR-01 | BK93: 856 | BL93: 156.56235 | BX93: Stabulation | CB93: FALSE | CC93: Élément | CD93: sites/ServiceOM-AssetManagement/Lists/Exploitation Data Centrale
A94: 77027 | B94: FAUREL | C94: DAVAI ENRSPV7 | D94: 45776 | E94: Lac Ferrié | F94: 46600 | G94: Gignac | H94: BaC | I94: Toiture inclinée | J94: Agriculteur | K94: S21 | L94: BTA1027948 | M94: 6035250 | N94: 1 | O94: 50079679722958 | P94: 137 | Q94: 110 | R94: 111 | S94: 1268 | T94: 173716 | U94: 0.054 | V94: 0.851 | W94: 1232.8 | X94: BT | Y94: 44564 | Z94: 0.1228 | AB94: FALSE | AC94: EDF OA | AD94: ENEDIS | AE94: 622.6752 | AF94: 45.00932 | AG94: 1.43847 | AH94: N°2 - Finergreen - Construction 2023 | AI94: RAS | AJ94: EIFFAGE | AK94: Jean Marc FAUREL | AL94: jean-marc.faurel@orange.fr | AN94: +33678449759 | AP94: LE TRIANGLE | AQ94: TRIANGLE | AR94: FALSE | AV94: FALSE | AZ94: FALSE | BD94: Parfait MEZEME ONA | BE94: Johan LAGARDE | BF94: Charbel BOUZERDAN | BG94: Charlie BLAIZEAU | BH94: MTN-CONT-004-Contrat_EIFFAGE_maintenance_PV_BT-001 | BI94: DEV-CONT-SPV007-Contrat_DEV_EPC_DAVAI_ENR-1 | BJ94: EX-CONT-SPV007-Contrat_Suivi_O&M_Gestion_Actifs_DAVAI_ENR-1 | BK94: 856 | BL94: 115.379 | BM94: 45796 | BN94: 45818 | BX94: stockage matériel et fourrage | CB94: FALSE | CC94: Élément | CD94: sites/ServiceOM-AssetManagement/Lists/Exploitation Data Centrale
A95: 32075 | B95: THURIES | C95: DAVAI ENRSPV10 | D95: 45776 | E95: Les Escors | F95: 11400 | G95: Saint-Papoul | H95: BaC | I95: Toiture inclinée | J95: Agriculteur | K95: S21 | L95: BTA1090552 | M95: 9092150 | N95: 1 | O95: 50086038954566 | P95: 343.07 | Q95: 250 | R95: 249.9 | S95: 1183 | T95: 405851.81 | U95: 0.054 | V95: 0.865 | W95: 1214.6 | X95: BT | Y95: 45125 | Z95: 0.1274 | AB95: FALSE | AC95: EDF OA | AD95: ENEDIS | AE95: 1506.573 | AF95: 43.308414 | AG95: 2.04129 | AH95: N°3 - Kyoto (SPV 10,13 &14) | AI95: Mot de passe onduleur : Exploitation2023 | AJ95: EIFFAGE | AK95: Frédéric THURIES | AL95: frederic_thuries@orange.fr | AN95: +33468949721 | AO95: +33750376891 | AP95: KEVEL | AQ95: GIRAUD | AR95: FALSE | AV95: FALSE | AZ95: FALSE | BD95: Parfait MEZEME ONA | BE95: Johan LAGARDE | BF95: Maxime DENIAU | BG95: Vincent KEZADRI | BH95: MTN-CONT-004-Contrat_EIFFAGE_maintenance_PV_BT-001 | BI95: DEV-CONT-SPV010-Contrat_DEV_EPC_DAVAI_ENR-1 | BJ95: EX-CONT-SPV010-Contrat_Suivi_O&M_Gestion_Actifs_DAVAI_ENR-1 | BK95: 856 | BL95: 197.30669 | BR95: Monsieur Frédéric Jean-Christophe THURIES | BS95: 12 rue Général d'Hautpoul | BT95: SAINT-PAPOUL | BU95: 11400 | BX95: Stockage matériel | CB95: FALSE | CC95: Élément | CD95: sites/ServiceOM-AssetManagement/Lists/Exploitation Data Centrale
A96: 94378 | B96: ESTABES | C96: DAVAI ENRSPV11 | D96: 45771 | E96: Plaine de Minique | F96: 81310 | G96: Parisot | H96: BaC | I96: Toiture inclinée | J96: Agriculteur | K96: S21 | L96: BTA1082259 | M96: 8962100 | N96: 1 | O96: 50095301164101 | P96: 300.3 | Q96: 250 | R96: 249.9 | S96: 1187 | T96: 356456.1 | U96: 0.054 | V96: 0.8687 | W96: 1202.7 | X96: BT | Y96: 45118 | Z96: 0.1274 | AB96: FALSE | AC96: EDF OA | AD96: ENEDIS | AE96: 1318.751 | AF96: 43.79701 | AG96: 1.80851 | AH96: N°3 - Fuji (SPV 11&15) | AI96: Mot de passe onduleur : Exploitation2023 | AJ96: EIFFAGE | AK96: Fréderic ESTABES | AL96: cambournacestabes@gmail.com | AN96: +33683735746 | AP96: KEVEL | AQ96: CANCE | AR96: FALSE | AV96: FALSE | AZ96: FALSE | BD96: Parfait MEZEME ONA | BE96: Jean-Paul THOROGOOD | BF96: Maxime DENIAU | BG96: Nicolas CADENE | BH96: MTN-CONT-004-Contrat_EIFFAGE_maintenance_PV_BT-001 | BI96: DEV-CONT-SPV011-Contrat_DEV_EPC_DAVAI_ENR-1 | BJ96: EX-CONT-SPV011-Contrat_Suivi_O&M_Gestion_Actifs_DAVAI_ENR-1 | BK96: 856 | BL96: 181.6101 | BX96: Stockage de matériel agricole + fourrage + céréales | CB96: FALSE | CC96: Élément | CD96: sites/ServiceOM-AssetManagement/Lists/Exploitation Data Centrale
A97: 15843 | B97: ROUX | C97: DAVAI ENRSPV6 | D97: 45769 | E97: Rue de Vareine cros et vareine | F97: 15260 | G97: Neuvéglise-sur-Truyère | H97: BaC | I97: Toiture inclinée | J97: Agriculteur | K97: S21 | L97: BTA1003861 | M97: 8137350 | N97: 1 | O97: 50012958545080 | P97: 313.95 | Q97: 220 | R97: 220 | S97: 1163 | T97: 365123.85 | U97: 0.054 | V97: 0.865 | W97: 1173.7 | X97: BT | Y97: 44977 | Z97: 0.1312 | AB97: FALSE | AC97: EDF OA | AD97: ENEDIS | AE97: 1378.695 | AF97: 44.92782 | AG97: 2.98992 | AH97: N°2 - Finergreen - Construction 2023 | AI97: RAS | AJ97: EIFFAGE | AK97: Laurent ROUX | AL97: elroux15@gmail.com | AN97: +33786270472 | AP97: YAMA ENERGIES | AQ97: GIRAUD | AR97: FALSE | AV97: FALSE | AZ97: FALSE | BD97: Parfait MEZEME ONA | BE97: Jean-Paul THOROGOOD | BF97: Maxime DENIAU | BG97: Vincent KEZADRI | BH97: MTN-CONT-004-Contrat_EIFFAGE_maintenance_PV_BT-001 | BI97: DEV-CONT-SPV006-Contrat_DEV_EPC_DAVAI_ENR-1 | BJ97: EX-CONT-SPV006-Contrat_Suivi_O&M_Gestion_Actifs_DAVAI_ENR-1 | BK97: 856 | BL97: 180.31965 | BM97: 45785 | BN97: 45824 | BX97: Stockage de matériel, paille, foin et fourrage | CB97: FALSE | CC97: Élément | CD97: sites/ServiceOM-AssetManagement/Lists/Exploitation Data Centrale
A98: 94626 | B98: PELLERIN | C98: DAVAI ENRSPV6 | D98: 45764 | E98: Les Janins | F98: 33580 | G98: Dieulivol | H98: BE | I98: Toiture inclinée | J98: Agriculteur | K98: S21 | L98: BTA1030422 | M98: 8886350 | N98: 1 | O98: 50041757391179 | P98: 169.99 | Q98: 165 | R98: 120.5 | S98: 1210 | T98: 205687.9 | U98: 0.054 | V98: 0.851 | W98: 1163.6 | X98: BT | Y98: 45022 | Z98: 0.1312 | AB98: FALSE | AC98: EDF OA | AD98: ENEDIS | AE98: 763.277 | AF98: 44.671704 | AG98: 0.121951 | AH98: N°2 - Finergreen - Construction 2023 | AI98: Mot de passe onduleur : Exploitation2023 2 toitures | AJ98: EIFFAGE | AK98: François PELLERIN | AL98: myriam.pellerin@wanadoo.fr | AN98: +33688573753 | AP98: KEVEL | AQ98: BARAN | AR98: FALSE | AV98: FALSE | AZ98: FALSE | BD98: Parfait MEZEME ONA | BE98: Jean-Paul THOROGOOD | BF98: Ibtissam ABSSI | BG98: Charlie BLAIZEAU | BH98: MTN-CONT-004-Contrat_EIFFAGE_maintenance_PV_BT-001 | BI98: DEV-CONT-SPV006-Contrat_DEV_EPC_DAVAI_ENR-1 | BJ98: EX-CONT-SPV006-Contrat_Suivi_O&M_Gestion_Actifs_DAVAI_ENR-1 | BK98: 856 | BL98: 127.48633 | BM98: 45779 | BN98: 45793 | BX98: Stockage de matériel + engrais | CB98: FALSE | CC98: Élément | CD98: sites/ServiceOM-AssetManagement/Lists/Exploitation Data Centrale
A99: 98584 | B99: VAN ZANTEN | C99: DAVAI ENRSPV7 | D99: 45763 | E99: La Tuque | F99: 47210 | G99: Parranquet | H99: BaC | I99: Toiture inclinée | J99: Agriculteur | K99: S21 | L99: BTA1167370 | M99: 9077900 | N99: 1 | O99: 50012810881102 | P99: 330.785 | Q99: 250 | R99: 249 | S99: 1186 | T99: 392311.01 | U99: 0.054 | V99: 0.836 | W99: 1154 | X99: BT | Y99: 45258 | Z99: 0.1208 | AB99: FALSE | AC99: EDF OA | AD99: ENEDIS | AE99: 1452.625 | AF99: 44.66239 | AG99: 0.83643 | AH99: N°2 - Finergreen - Construction 2023 | AI99: Mot de passe onduleur : Exploitation2023 | AJ99: EIFFAGE | AK99: Richard VAN ZANTEN | AL99: earllavision@gmail.com | AN99: +33679206582 | AP99: ACROM | AQ99: GONZALEZ | AR99: FALSE | AV99: FALSE | AZ99: FALSE | BD99: Yasser BADREZZAMANE | BE99: Johan LAGARDE | BF99: Gwendal HART | BG99: Charlie BLAIZEAU | BH99: MTN-CONT-004-Contrat_EIFFAGE_maintenance_PV_BT-001 | BI99: DEV-CONT-SPV007-Contrat_DEV_EPC_DAVAI_ENR-1 | BJ99: EX-CONT-SPV007-Contrat_Suivi_O&M_Gestion_Actifs_DAVAI_ENR-1 | BK99: 856 | BL99: 186.4981 | BM99: 45777 | BN99: 45926 | BX99: Stockage fourrage matériel et nurserie | CB99: FALSE | CC99: Élément | CD99: sites/ServiceOM-AssetManagement/Lists/Exploitation Data Centrale
A100: 34484 | B100: SCEA GENRE | C100: DAVAI ENRSPV6 | D100: 45763 | E100: 2767 Rte de Pourrières | F100: 13530 | G100: Trets | H100: BaC | I100: Toiture inclinée | J100: Agriculteur | K100: S21 | L100: BTA1024015 | M100: 7896850 | N100: 1 | O100: 50091974609473 | P100: 288.1 | Q100: 250 | R100: 249.9 | S100: 1367 | T100: 393832.7 | U100: 0.054 | V100: 0.849 | W100: 1359.7 | X100: BT | Y100: 45020 | Z100: 0.1312 | AB100: FALSE | AC100: EDF OA | AD100: ENEDIS | AE100: 1303.726 | AF100: 43.472031 | AG100: 5.709361 | AH100: N°2 - Finergreen - Construction 2023 | AI100: Mot de passe onduleur : Exploitation2023 | AJ100: EIFFAGE | AK100: David GENRE | AL100: d.genre@groupegenre.com | AN100: +33442613699 | AO100: +33616090475 | AP100: NEOXOM | AQ100: GIRAUD | AR100: FALSE | AV100: FALSE | AZ100: FALSE | BD100: Yasser BADREZZAMANE | BE100: Jean-Paul THOROGOOD | BF100: Sophie ROGIER | BG100: Thibault RAHMOUNI | BH100: MTN-CONT-004-Contrat_EIFFAGE_maintenance_PV_BT-001 | BI100: DEV-CONT-SPV006-Contrat_DEV_EPC_DAVAI_ENR-1 | BJ100: EX-CONT-SPV006-Contrat_Suivi_O&M_Gestion_Actifs_DAVAI_ENR-1 | BK100: 856 | BL100: 170.8327 | BM100: 45777 | BN100: 45929 | BX100: Stockage matériel pépinière | CB100: FALSE | CC100: Élément | CD100: sites/ServiceOM-AssetManagement/Lists/Exploitation Data Centrale
...
